Workbook

Sheet Antecedentes
A7: Cotizacion N°: | B7: 513.1
A8: Empresa: | B8: Agrícola Peumo Ltda.
A9: Rut:
A10: Correo: | B10: aaravena@grupobrota.com
A11: Nombre Contacto: | B11: Adolfo Aravena
A12: Telefono:
A13: Tipo Proyecto: | B13: Llave en Mano Rafia
A14: Especie: | B14: Cerezas
A15: Sup. A Cotizar Há: | B15: =+'Cotizador de Insumos'!D2 -> 13.1848

Sheet Diseño estructura &CP
H2: * | I2: NO MODIFICAR NINGUN PARAMETRO DENTRO DEL ESQUEMA SOLO EN DATOS | AN2: PARAMETROS | BZ2: PERIMETRO FRONTAL
H3: * | I3: NO MODIFICAR NINGUN PARAMETRO DENTRO DEL ESQUEMA SOLO EN DATOS | AN3: Largo poste | AO3: 5 | AP3: Metros | AX3: Parámetros de alambres | BA3: Parámetros de Madera
AN4: Enterrado central | AO4: 0.8 | AP4: Metros | AX4: Nombre | AY4: tipo de alambre | AZ4: mts x rollo | BA4: Tipo | BB4: Nombre
AN5: Caída de agua | AO5: 0.8 | AP5: Metros | AX5: Cumbreras | AY5: Piola 4mm | AZ5: 1000 | BA5: Central | BB5: Polin4a5''x5mts
G6: Diseño de Estructura Recomendada | AN6: Corte Superior | AO6: 0.1 | AP6: Metros | AX6: Perímetro | AY6: Perimetro piola 6mm | AZ6: 500 | BA6: Cabezal | BB6: 5 a 6"x5mts
AN7: Ancho de lámina | AO7: 2 | AP7: Metros | AX7: Hombros | AY7: Piola 4mm | AZ7: 1000 | BA7: Cabezal Transversal | BB7: 5 a 6"x 4,5mts
AN8: recorrido elastico | AO8: 0.1 | AP8: Metros | AX8: TRANS. | AY8: Transversal piola 5 mm | AZ8: 500 | BA8: Esquinero | BB8: 6 a 7"x 4,5mt
AN9: Ancho entre hilera | AO9: =AO11 -> 4 | AP9: Metros | AX9: Guatana C | AY9: dulce 10 | AZ9: 700 | BA9: Yugo | BB9: 2 a 3"x2,4mts (60cm)
AN10: Largo de carpa | AO10: 12 | AP10: Metros | AX10: Guatana P | AY10: dulce 8 | AZ10: 480
AF11: =+AE12+AO8&"m" -> 2,1m | AJ11: =AO3-AO4 -> 4.2 | AN11: Distancia entre hileras | AO11: 4 | AX11: Riendas | AY11: Piola 6 mm | AZ11: 500
L12: m | O12: =AO7 -> 2 | P12: m | W12: =+AO7 -> 2 | X12: m | AE12: =O12 -> 2 | AF12: m | AN12: Distancia sobre hileras | AO12: 2 | AX12: Formación 1 | AY12: ALAMBRE 17/15 | AZ12: 1100
F13: =+AF11 -> 2,1m | L13: =AO5 -> 0.8 | AX13: Formación 2 | AY13: ALAMBRE N°12 BCC | AZ13: 1050
H14: Rafia | N14: Rafia | X14: Rafia | AD14: Rafia | AQ14: =3.5/2 -> 1.75 | AX14: Formación 3 | AY14: ALAMBRE DEL N°11 | AZ14: 1596
Q15: 0,1m | U15: 0,1m | AG15: 0,1m
M17: =AR22 -> 1.9416488 | R17: =(AO11-(M17+X17)) -> 0.11670243 | X17: =M17 -> 1.9416488
M18: m | S18: m | X18: m
AQ19: Cálculo
AQ20: largo hipotenusa | AR20: =AO6+AO7 -> 2.1 | AS20: m | AY20: Hip
AK21: mts | AQ21: largo cateto 1 | AR21: =AO5 -> 0.8 | AS21: m | AV21: Cat 1
AD22: m | AQ22: Largo cateto 2 | AR22: =SQRT((AR20*AR20)-(AR21*AR21)) -> 1.9416488 | AS22: m
AD23: =(AO3-AO4-AO5-AO6) -> 3.3
AY25: Cat 2
AQ28: Diseño de cobertor
AQ30: Ancho 2,2 mts | BZ30: PERIMETRO LATERAL
AQ31: Largo 10 mts
R33: =AO9 -> 4 | U33: m
F36: ="Diseño con cobertor de "&AO10&"m"&" con 10 cm de recorrido de elástico." -> Diseño con cobertor de 12m con 10 cm de recorrido de elástico.
CC53: * | CD53: Nota: Medidas Referenciales

Sheet Datos
B7: Especie: | C7: =+Antecedentes!$B$14 -> Cerezas | E7: Marco plantación | G7: Marco de Plantación Modificable | V7: Especie: | W7: =+Antecedentes!$B$14 -> Cerezas | Y7: Marco plantación | AA7: Marco de Plantación Modificable | AP7: Especie: | AQ7: =+Antecedentes!$B$14 -> Cerezas | AS7: Marco plantación | AU7: Marco de Plantación Modificable | BJ7: Especie: | BK7: =+Antecedentes!$B$14 -> Cerezas | BM7: Marco plantación | BO7: Marco de Plantación Modificable | CD7: Especie: | CE7: =+Antecedentes!$B$14 -> Cerezas | CG7: Marco plantación | CI7: Marco de Plantación Modificable | CX7: Especie: | CY7: =+Antecedentes!$B$14 -> Cerezas | DA7: Marco plantación | DC7: Marco de Plantación Modificable | DR7: Especie: | DS7: =+Antecedentes!$B$14 -> Cerezas | DU7: Marco plantación | DW7: Marco de Plantación Modificable | EL7: Especie: | EM7: =+Antecedentes!$B$14 -> Cerezas | EO7: Marco plantación | EQ7: Marco de Plantación Modificable | FF7: Especie: | FG7: =+Antecedentes!$B$14 -> Cerezas | FI7: Marco plantación | FK7: Marco de Plantación Modificable | FZ7: Especie: | GA7: =+Antecedentes!$B$14 -> Cerezas | GC7: Marco plantación | GE7: Marco de Plantación Modificable
B8: Variedad: | C8: Santina | E8: Entre hileras: | F8: 4 | G8: Entre Hileras | H8: Sobre Hileras | V8: Variedad: | W8: Santina | Y8: Entre hileras: | Z8: 4 | AA8: Entre Hileras | AB8: Sobre Hileras | AP8: Variedad: | AQ8: Santina | AS8: Entre hileras: | AT8: 4 | AU8: Entre Hileras | AV8: Sobre Hileras | BJ8: Variedad: | BM8: Entre hileras: | BN8: 4.5 | BO8: Entre Hileras | BP8: Sobre Hileras | CD8: Variedad: | CG8: Entre hileras: | CI8: Entre Hileras | CJ8: Sobre Hileras | CX8: Variedad: | DA8: Entre hileras: | DC8: Entre Hileras | DD8: Sobre Hileras | DR8: Variedad: | DU8: Entre hileras: | DW8: Entre Hileras | DX8: Sobre Hileras | EL8: Variedad: | EO8: Entre hileras: | EQ8: Entre Hileras | ER8: Sobre Hileras | FF8: Variedad: | FI8: Entre hileras: | FK8: Entre Hileras | FL8: Sobre Hileras | FZ8: Variedad: | GC8: Entre hileras: | GE8: Entre Hileras | GF8: Sobre Hileras
B9: Superficie (Ha): | C9: =+(F8*E14)/10000 -> 4.0938 | E9: Entre plantas: | F9: 2 | G9: 4 | H9: 2 | V9: Superficie (Ha): | W9: =+(Z8*Y14)/10000 -> 2.7578 | Y9: Entre plantas: | Z9: 2 | AA9: 4 | AB9: 2 | AP9: Superficie (Ha): | AQ9: =+(AT8*AS14)/10000 -> 4.5044 | AS9: Entre plantas: | AT9: 2 | AU9: 4 | AV9: 2 | BJ9: Superficie (Ha): | BK9: =+(BN8*BM14)/10000 -> 1.8288 | BM9: Entre plantas: | BN9: 2.2 | BO9: 4.5 | BP9: 2.2 | CD9: Superficie (Ha): | CE9: =+(CH8*CG14)/10000 -> 0 | CG9: Entre plantas: | CX9: Superficie (Ha): | CY9: =+(DB8*DA14)/10000 -> 0 | DA9: Entre plantas: | DR9: Superficie (Ha): | DS9: =+(DV8*DU14)/10000 -> 0 | DU9: Entre plantas: | EL9: Superficie (Ha): | EM9: =+(EP8*EO14)/10000 -> 0 | EO9: Entre plantas: | FF9: Superficie (Ha): | FG9: =+(FJ8*FI14)/10000 -> 0 | FI9: Entre plantas: | FZ9: Superficie (Ha): | GA9: =+(GD8*GC14)/10000 -> 0 | GC9: Entre plantas:
B10: Altura de plantas (m): | C10: =+C9/4 -> 1.02345 | G10: Nombre cuartel | H10: UTILIZACION DE CUARTEL | J10: PERIMETRO | P10: TRANSVERSAL | V10: Altura de plantas (m): | W10: =+W9/4 -> 0.68945 | AA10: Nombre cuartel | AB10: UTILIZACION DE CUARTEL | AD10: PERIMETRO | AJ10: TRANSVERSAL | AP10: Altura de plantas (m): | AQ10: =+AQ9/4 -> 1.1261 | AU10: Nombre cuartel | AV10: UTILIZACION DE CUARTEL | AX10: PERIMETRO | BD10: TRANSVERSAL | BJ10: Altura de plantas (m): | BK10: =+BK9/4 -> 0.4572 | BO10: Nombre cuartel | BP10: UTILIZACION DE CUARTEL | BR10: PERIMETRO | BX10: TRANSVERSAL | CD10: Altura de plantas (m): | CE10: =+CE9/4 -> 0 | CI10: Nombre cuartel | CJ10: UTILIZACION DE CUARTEL | CL10: PERIMETRO | CR10: TRANSVERSAL | CX10: Altura de plantas (m): | CY10: =+CY9/4 -> 0 | DC10: Nombre cuartel | DD10: UTILIZACION DE CUARTEL | DF10: PERIMETRO | DL10: TRANSVERSAL | DR10: Altura de plantas (m): | DS10: =+DS9/4 -> 0 | DW10: Nombre cuartel | DX10: UTILIZACION DE CUARTEL | DZ10: PERIMETRO | EF10: TRANSVERSAL | EL10: Altura de plantas (m): | EM10: =+EM9/4 -> 0 | EQ10: Nombre cuartel | ER10: UTILIZACION DE CUARTEL | ET10: PERIMETRO | EZ10: TRANSVERSAL | FF10: Altura de plantas (m): | FG10: =+FG9/4 -> 0 | FK10: Nombre cuartel | FL10: UTILIZACION DE CUARTEL | FN10: PERIMETRO | FT10: TRANSVERSAL | FZ10: Altura de plantas (m): | GA10: =+GA9/4 -> 0 | GE10: Nombre cuartel | GF10: UTILIZACION DE CUARTEL | GH10: PERIMETRO | GN10: TRANSVERSAL
G11: sector 1 | H11: SI | AA11: sector 2 | AB11: SI | AU11: sector 3 | AV11: SI | BO11: sector 4 | BP11: SI | CI11: sector 5 | CJ11: NO | DC11: sector 6 | DD11: NO | DW11: sector 7 | DX11: NO | EQ11: sector 8 | ER11: NO | FK11: sector 9 | FL11: NO | GE11: sector 10 | GF11: NO
B12: N° de Cuartel | C12: 1 | F12: 0 | R12: 1 | S12: cant de cortadas | V12: N° de Cuartel | W12: 2 | Z12: 0 | AL12: 1 | AM12: cant de cortadas | AP12: N° de Cuartel | AQ12: 3 | AT12: 0 | BF12: 1 | BG12: cant de cortadas | BJ12: N° de Cuartel | BK12: 4 | BN12: 0 | BZ12: 1 | CA12: cant de cortadas | CD12: N° de Cuartel | CE12: 5 | CH12: 0 | CT12: 1 | CU12: cant de cortadas | CX12: N° de Cuartel | CY12: 6 | DB12: 0 | DN12: 1 | DO12: cant de cortadas | DR12: N° de Cuartel | DS12: 7 | DV12: 0 | EH12: 1 | EI12: cant de cortadas | EL12: N° de Cuartel | EM12: 8 | EP12: 0 | FB12: 1 | FC12: cant de cortadas | FF12: N° de Cuartel | FG12: 9 | FJ12: 0 | FV12: 1 | FW12: cant de cortadas | FZ12: N° de Cuartel | GA12: 10 | GD12: 0 | GP12: 1 | GQ12: cant de cortadas
B13: Distancia centrales | C13: 12 | E13: metros | F13: Mts Camino central | H13: =F14+AB14 -> 906 | K13: =IF(H11="SI",ROUNDUP(K14/'Diseño estructura &CP'!$AZ$6,0),0) -> 3 | Q13: =COUNT(Q16:Q75) -> 23 | R13: =+Q13 -> 23 | S13: cant transversales | V13: Distancia centrales | W13: 12 | Y13: metros | Z13: Mts Camino central | AA13: 5 | AE13: =IF(AB11="SI",ROUNDUP(AE14/'Diseño estructura &CP'!$AZ$6,0),0) -> 2 | AK13: =COUNT(AK16:AK75) -> 16 | AL13: =IF(AB11="SI",COUNTA(AJ16:AJ150)*AL12,0) -> 16 | AM13: cant transversales | AP13: Distancia centrales | AQ13: 12 | AS13: metros | AT13: Mts Camino central | AY13: =IF(AV11="SI",ROUNDUP(AY14/'Diseño estructura &CP'!$AZ$6,0),0) -> 3 | BE13: =COUNT(BE16:BE75) -> 14 | BF13: =IF(AV11="SI",COUNTA(BD16:BD150)*BF12,0) -> 14 | BG13: cant transversales | BJ13: Distancia centrales | BK13: 11 | BM13: metros | BN13: Mts Camino central | BS13: =IF(BP11="SI",ROUNDUP(BS14/'Diseño estructura &CP'!$AZ$6,0),0) -> 2 | BY13: =COUNT(BY16:BY75) -> 18 | BZ13: =IF(BP11="SI",COUNTA(BX16:BX150)*BZ12,0) -> 18 | CA13: cant transversales | CD13: Distancia centrales | CG13: metros | CH13: Mts Camino central | CM13: =IF(CJ11="SI",ROUNDUP(CM14/'Diseño estructura &CP'!$AZ$6,0),0) -> 0 | CS13: =COUNT(CS16:CS75) -> 0 | CT13: =IF(CJ11="SI",COUNTA(CR16:CR150)*CT12,0) -> 0 | CU13: cant transversales | CX13: Distancia centrales | DA13: metros | DB13: Mts Camino central | DG13: =IF(DD11="SI",ROUNDUP(DG14/'Diseño estructura &CP'!$AZ$6,0),0) -> 0 | DM13: =COUNT(DM16:DM75) -> 0 | DN13: =IF(DD11="SI",COUNTA(DL16:DL150)*DN12,0) -> 0 | DO13: cant transversales | DR13: Distancia centrales | DU13: metros | DV13: Mts Camino central | EA13: =IF(DX11="SI",ROUNDUP(EA14/'Diseño estructura &CP'!$AZ$6,0),0) -> 0 | EG13: =COUNT(EG16:EG75) -> 0 | EH13: =IF(DX11="SI",COUNTA(EF16:EF150)*EH12,0) -> 0 | EI13: cant transversales | EL13: Distancia centrales | EO13: metros | EP13: Mts Camino central | EU13: =IF(ER11="SI",ROUNDUP(EU14/'Diseño estructura &CP'!$AZ$6,0),0) -> 0 | FA13: =COUNT(FA16:FA75) -> 0 | FB13: =IF(ER11="SI",COUNTA(EZ16:EZ150)*FB12,0) -> 0 | FC13: cant transversales | FF13: Distancia centrales | FI13: metros | FJ13: Mts Camino central | FO13: =IF(FL11="SI",ROUNDUP(FO14/'Diseño estructura &CP'!$AZ$6,0),0) -> 0 | FU13: =COUNT(FU16:FU75) -> 0 | FV13: =IF(FL11="SI",COUNTA(FT16:FT150)*FV12,0) -> 0 | FW13: cant transversales | FZ13: Distancia centrales | GC13: metros | GD13: Mts Camino central | GI13: =IF(GF11="SI",ROUNDUP(GI14/'Diseño estructura &CP'!$AZ$6,0),0) -> 0 | GO13: =COUNT(GO16:GO75) -> 0 | GP13: =IF(GF11="SI",COUNTA(GN16:GN150)*GP12,0) -> 0 | GQ13: cant transversales
B14: =MAX(B16:B265) -> 106 | C14: =IF($H$11="SI",SUMIF(C16:C265,">"&0,C16:C265),0) -> 5117.25 | D14: =IF($H$11="SI",SUMIF(D16:D265,">"&0,D16:D265),0) -> 801 | E14: =IF($H$11="SI",SUMIF(E16:E265,">"&0,E16:E265),0) -> 10234.5 | F14: =IF($H$11="SI",SUMIF(F16:F265,">"&0,F16:F265),0) -> 906 | G14: =IF($H$11="SI",SUMIF(G16:G265,">"&0,G16:G265)+1,0) -> 11.820076 | J14: Total | K14: =+SUM(K16:K48) -> 1168 | M14: =IF(H11="SI",ROUNDUP(K14/'Diseño estructura &CP'!$AZ$6,0),0) -> 3 | P14: Total | R14: =SUM(R16:R75) -> 9752 | S14: =ROUNDUP((R14/'Diseño estructura &CP'!$AZ$6),0) -> 20 | V14: =MAX(V16:V265) -> 55 | W14: =IF($H$11="SI",SUMIF(W16:W265,">"&0,W16:W265),0) -> 3447.25 | X14: =IF($H$11="SI",SUMIF(X16:X265,">"&0,X16:X265),0) -> 547 | Y14: =IF($H$11="SI",SUMIF(Y16:Y265,">"&0,Y16:Y265),0) -> 6894.5 | Z14: =IF($H$11="SI",SUMIF(Z16:Z265,">"&0,Z16:Z265),0) -> 600 | AA14: =IF($H$11="SI",SUMIF(AA16:AA265,">"&0,AA16:AA265)+1,0) -> 8.5296364 | AD14: Total | AE14: =+SUM(AE16:AE48) -> 818 | AG14: =IF(AB11="SI",ROUNDUP(AE14/'Diseño estructura &CP'!$AZ$6,0),0) -> 2 | AJ14: Total | AL14: =SUM(AL16:AL75) -> 3520 | AM14: =ROUNDUP((AL14/'Diseño estructura &CP'!$AZ$6),0) -> 8 | AP14: =MAX(AP16:AP265) -> 76 | AQ14: =IF($H$11="SI",SUMIF(AQ16:AQ265,">"&0,AQ16:AQ265),0) -> 5630.5 | AR14: =IF($H$11="SI",SUMIF(AR16:AR265,">"&0,AR16:AR265),0) -> 901 | AS14: =IF($H$11="SI",SUMIF(AS16:AS265,">"&0,AS16:AS265),0) -> 11261 | AT14: =IF($H$11="SI",SUMIF(AT16:AT265,">"&0,AT16:AT265),0) -> 977 | AU14: =IF($H$11="SI",SUMIF(AU16:AU265,">"&0,AU16:AU265)+1,0) -> 12.605107 | AX14: Total | AY14: =+SUM(AY16:AY48) -> 1102 | BA14: =IF(AV11="SI",ROUNDUP(AY14/'Diseño estructura &CP'!$AZ$6,0),0) -> 3 | BD14: Total | BF14: =SUM(BF16:BF75) -> 4256 | BG14: =ROUNDUP((BF14/'Diseño estructura &CP'!$AZ$6),0) -> 9 | BJ14: =MAX(BJ16:BJ265) -> 30 | BK14: =IF($H$11="SI",SUMIF(BK16:BK265,">"&0,BK16:BK265),0) -> 2032 | BL14: =IF($H$11="SI",SUMIF(BL16:BL265,">"&0,BL16:BL265),0) -> 355 | BM14: =IF($H$11="SI",SUMIF(BM16:BM265,">"&0,BM16:BM265),0) -> 4064 | BN14: =IF($H$11="SI",SUMIF(BN16:BN265,">"&0,BN16:BN265),0) -> 385 | BO14: =IF($H$11="SI",SUMIF(BO16:BO265,">"&0,BO16:BO265)+1,0) -> 5.2494061 | BR14: Total | BS14: =+SUM(BS16:BS48) -> 809.5 | BU14: =IF(BP11="SI",ROUNDUP(BS14/'Diseño estructura &CP'!$AZ$6,0),0) -> 2 | BX14: Total | BZ14: =SUM(BZ16:BZ75) -> 2160 | CA14: =ROUNDUP((BZ14/'Diseño estructura &CP'!$AZ$6),0) -> 5 | CD14: =MAX(CD16:CD265) -> 0 | CE14: =IF($H$11="SI",SUMIF(CE16:CE265,">"&0,CE16:CE265),0) -> 0 | CF14: =IF($H$11="SI",SUMIF(CF16:CF265,">"&0,CF16:CF265),0) -> 0 | CG14: =IF($H$11="SI",SUMIF(CG16:CG265,">"&0,CG16:CG265),0) -> 0 | CH14: =IF($H$11="SI",SUMIF(CH16:CH265,">"&0,CH16:CH265),0) -> 0 | CI14: =IF($H$11="SI",SUMIF(CI16:CI265,">"&0,CI16:CI265)+1,0) -> 1 | CL14: Total | CM14: =+SUM(CM16:CM48) -> 0 | CO14: =IF(CJ11="SI",ROUNDUP(CM14/'Diseño estructura &CP'!$AZ$6,0),0) -> 0 | CR14: Total | CT14: =SUM(CT16:CT75) -> 0 | CU14: =ROUNDUP((CT14/'Diseño estructura &CP'!$AZ$6),0) -> 0 | CX14: =MAX(CX16:CX265) -> 0 | CY14: =IF($H$11="SI",SUMIF(CY16:CY265,">"&0,CY16:CY265),0) -> 0 | CZ14: =IF($H$11="SI",SUMIF(CZ16:CZ265,">"&0,CZ16:CZ265),0) -> 0 | DA14: =IF($H$11="SI",SUMIF(DA16:DA265,">"&0,DA16:DA265),0) -> 0 | DB14: =IF($H$11="SI",SUMIF(DB16:DB265,">"&0,DB16:DB265),0) -> 0 | DC14: =IF($H$11="SI",SUMIF(DC16:DC265,">"&0,DC16:DC265)+1,0) -> 1 | DF14: Total | DG14: =+SUM(DG16:DG48) -> 0 | DI14: =IF(DD11="SI",ROUNDUP(DG14/'Diseño estructura &CP'!$AZ$6,0),0) -> 0 | DL14: Total | DN14: =SUM(DN16:DN75) -> 0 | DO14: =ROUNDUP((DN14/'Diseño estructura &CP'!$AZ$6),0) -> 0 | DR14: =MAX(DR16:DR265) -> 0 | DS14: =IF($H$11="SI",SUMIF(DS16:DS265,">"&0,DS16:DS265),0) -> 0 | DT14: =IF($H$11="SI",SUMIF(DT16:DT265,">"&0,DT16:DT265),0) -> 0 | DU14: =IF($H$11="SI",SUMIF(DU16:DU265,">"&0,DU16:DU265),0) -> 0 | DV14: =IF($H$11="SI",SUMIF(DV16:DV265,">"&0,DV16:DV265),0) -> 0 | DW14: =IF($H$11="SI",SUMIF(DW16:DW265,">"&0,DW16:DW265)+1,0) -> 1 | DZ14: Total | EA14: =+SUM(EA16:EA48) -> 0 | EC14: =IF(DX11="SI",ROUNDUP(EA14/'Diseño estructura &CP'!$AZ$6,0),0) -> 0 | EF14: Total | EH14: =SUM(EH16:EH75) -> 0 | EI14: =ROUNDUP((EH14/'Diseño estructura &CP'!$AZ$6),0) -> 0 | EL14: =MAX(EL16:EL265) -> 0 | EM14: =IF($H$11="SI",SUMIF(EM16:EM265,">"&0,EM16:EM265),0) -> 0 | EN14: =IF($H$11="SI",SUMIF(EN16:EN265,">"&0,EN16:EN265),0) -> 0 | EO14: =IF($H$11="SI",SUMIF(EO16:EO265,">"&0,EO16:EO265),0) -> 0 | EP14: =IF($H$11="SI",SUMIF(EP16:EP265,">"&0,EP16:EP265),0) -> 0 | EQ14: =IF($H$11="SI",SUMIF(EQ16:EQ265,">"&0,EQ16:EQ265)+1,0) -> 1 | ET14: Total | EU14: =+SUM(EU16:EU48) -> 0 | EW14: =IF(ER11="SI",ROUNDUP(EU14/'Diseño estructura &CP'!$AZ$6,0),0) -> 0 | EZ14: Total | FB14: =SUM(FB16:FB75) -> 0 | FC14: =ROUNDUP((FB14/'Diseño estructura &CP'!$AZ$6),0) -> 0 | FF14: =MAX(FF16:FF265) -> 0 | FG14: =IF($H$11="SI",SUMIF(FG16:FG265,">"&0,FG16:FG265),0) -> 0 | FH14: =IF($H$11="SI",SUMIF(FH16:FH265,">"&0,FH16:FH265),0) -> 0 | FI14: =IF($H$11="SI",SUMIF(FI16:FI265,">"&0,FI16:FI265),0) -> 0 | FJ14: =IF($H$11="SI",SUMIF(FJ16:FJ265,">"&0,FJ16:FJ265),0) -> 0 | FK14: =IF($H$11="SI",SUMIF(FK16:FK265,">"&0,FK16:FK265)+1,0) -> 1 | FN14: Total | FO14: =+SUM(FO16:FO48) -> 0 | FQ14: =IF(FL11="SI",ROUNDUP(FO14/'Diseño estructura &CP'!$AZ$6,0),0) -> 0 | FT14: Total | FV14: =SUM(FV16:FV75) -> 0 | FW14: =ROUNDUP((FV14/'Diseño estructura &CP'!$AZ$6),0) -> 0 | FZ14: =MAX(FZ16:FZ265) -> 0 | GA14: =IF($H$11="SI",SUMIF(GA16:GA265,">"&0,GA16:GA265),0) -> 0 | GB14: =IF($H$11="SI",SUMIF(GB16:GB265,">"&0,GB16:GB265),0) -> 0 | GC14: =IF($H$11="SI",SUMIF(GC16:GC265,">"&0,GC16:GC265),0) -> 0 | GD14: =IF($H$11="SI",SUMIF(GD16:GD265,">"&0,GD16:GD265),0) -> 0 | GE14: =IF($H$11="SI",SUMIF(GE16:GE265,">"&0,GE16:GE265)+1,0) -> 1 | GH14: Total | GI14: =+SUM(GI16:GI48) -> 0 | GK14: =IF(GF11="SI",ROUNDUP(GI14/'Diseño estructura &CP'!$AZ$6,0),0) -> 0 | GN14: Total | GP14: =SUM(GP16:GP75) -> 0 | GQ14: =ROUNDUP((GP14/'Diseño estructura &CP'!$AZ$6),0) -> 0
B15: N° hilera | C15: N° plantas | D15: Centrales | E15: Largo (m) | F15: Carpas | G15: Aprovechamiento | H15: hebras por rollo | J15: Perímetro | M15: Aprovechamiento | N15: hebras por rollo | P15: Transversal | R15: =IF(H11="SI",F8,0) -> 4 | S15: Aprovechamiento | T15: hebras por rollo | V15: N° hilera | W15: N° plantas | X15: Centrales | Y15: Largo (m) | Z15: Carpas | AA15: Aprovechamiento | AB15: hebras por rollo | AD15: Perímetro | AG15: Aprovechamiento | AH15: hebras por rollo | AJ15: Transversal | AL15: =IF(AB11="SI",Z8,0) -> 4 | AM15: Aprovechamiento | AN15: hebras por rollo | AP15: N° hilera | AQ15: N° plantas | AR15: Centrales | AS15: Largo (m) | AT15: Carpas | AU15: Aprovechamiento | AV15: hebras por rollo | AX15: Perímetro | BA15: Aprovechamiento | BB15: hebras por rollo | BD15: Transversal | BF15: =IF(AV11="SI",AT8,0) -> 4 | BG15: Aprovechamiento | BH15: hebras por rollo | BJ15: N° hilera | BK15: N° plantas | BL15: Centrales | BM15: Largo (m) | BN15: Carpas | BO15: Aprovechamiento | BP15: hebras por rollo | BR15: Perímetro | BU15: Aprovechamiento | BV15: hebras por rollo | BX15: Transversal | BZ15: =IF(BP11="SI",BN8,0) -> 4.5 | CA15: Aprovechamiento | CB15: hebras por rollo | CD15: N° hilera | CE15: N° plantas | CF15: Centrales | CG15: Largo (m) | CH15: Carpas | CI15: Aprovechamiento | CJ15: hebras por rollo | CL15: Perímetro | CO15: Aprovechamiento | CP15: hebras por rollo | CR15: Transversal | CT15: =IF(CJ11="SI",CH8,0) -> 0 | CU15: Aprovechamiento | CV15: hebras por rollo | CX15: N° hilera | CY15: N° plantas | CZ15: Centrales | DA15: Largo (m) | DB15: Carpas | DC15: Aprovechamiento | DD15: hebras por rollo | DF15: Perímetro | DI15: Aprovechamiento | DJ15: hebras por rollo | DL15: Transversal | DN15: =IF(DD11="SI",DB8,0) -> 0 | DO15: Aprovechamiento | DP15: hebras por rollo | DR15: N° hilera | DS15: N° plantas | DT15: Centrales | DU15: Largo (m) | DV15: Carpas | DW15: Aprovechamiento | DX15: hebras por rollo | DZ15: Perímetro | EC15: Aprovechamiento | ED15: hebras por rollo | EF15: Transversal | EH15: =IF(DX11="SI",DV8,0) -> 0 | EI15: Aprovechamiento | EJ15: hebras por rollo | EL15: N° hilera | EM15: N° plantas | EN15: Centrales | EO15: Largo (m) | EP15: Carpas | EQ15: Aprovechamiento | ER15: hebras por rollo | ET15: Perímetro | EW15: Aprovechamiento | EX15: hebras por rollo | EZ15: Transversal | FB15: =IF(ER11="SI",EP8,0) -> 0 | FC15: Aprovechamiento | FD15: hebras por rollo | FF15: N° hilera | FG15: N° plantas | FH15: Centrales | FI15: Largo (m) | FJ15: Carpas | FK15: Aprovechamiento | FL15: hebras por rollo | FN15: Perímetro | FQ15: Aprovechamiento | FR15: hebras por rollo | FT15: Transversal | FV15: =IF(FL11="SI",FJ8,0) -> 0 | FW15: Aprovechamiento | FX15: hebras por rollo | FZ15: N° hilera | GA15: N° plantas | GB15: Centrales | GC15: Largo (m) | GD15: Carpas | GE15: Aprovechamiento | GF15: hebras por rollo | GH15: Perímetro | GK15: Aprovechamiento | GL15: hebras por rollo | GN15: Transversal | GP15: =IF(GF11="SI",GD8,0) -> 0 | GQ15: Aprovechamiento | GR15: hebras por rollo
B16: =+IF(H11="SI",1,"") -> 1 | C16: =+E16/$H$9 -> 3.5 | D16: =ROUNDDOWN(E16/$C$13,0) -> 0 | E16: 7 | F16: =IF(D16=0,0,D16+1) -> 0 | G16: =IF(H16="","",1/(H16+0.01)) -> 0.0070417576 | H16: =IF(E16>0,ROUNDDOWN(('Diseño estructura &CP'!$AZ$5/E16),0),"") -> 142 | J16: Lado 1 | K16: =IF(H11="SI",MAX(E16:E224),0) -> 160 | L16: metros | M16: =IFERROR(1/(N16+0.01),0) -> 0.33222591 | N16: =IFERROR(IF(K16="",0,ROUNDDOWN(('Diseño estructura &CP'!$AZ$6/K16),0)),0) -> 3 | P16: T1 | Q16: =IF(H$11="SI",B$14,"") -> 106 | R16: =IF(Q16="","",Q16*$R$15) -> 424 | S16: =1/(T16+0.01) -> 0.99009901 | T16: =IFERROR(ROUNDDOWN(('Diseño estructura &CP'!$AZ$8/R16),0),0) -> 1 | V16: =+IF(AB11="SI",1,"") -> 1 | W16: =+Y16/$H$9 -> 75 | X16: =ROUNDDOWN(Y16/$C$13,0) -> 12 | Y16: 150 | Z16: =IF(X16=0,0,X16+1) -> 13 | AA16: =IF(AB16="","",1/(AB16+0.01)) -> 0.16638935 | AB16: =IF(Y16>0,ROUNDDOWN(('Diseño estructura &CP'!$AZ$5/Y16),0),"") -> 6 | AD16: Lado 1 | AE16: =IF(AB11="SI",MAX(Y16:Y224),0) -> 189 | AF16: metros | AG16: =IFERROR(1/(AH16+0.01),0) -> 0.49751244 | AH16: =IFERROR(IF(AE16="",0,ROUNDDOWN(('Diseño estructura &CP'!$AZ$6/AE16),0)),0) -> 2 | AJ16: T1 | AK16: =IF(AB$11="SI",V$14,"") -> 55 | AL16: =IF(AK16="","",AK16*$R$15) -> 220 | AM16: =1/(AN16+0.01) -> 0.49751244 | AN16: =IFERROR(ROUNDDOWN(('Diseño estructura &CP'!$AZ$8/AL16),0),0) -> 2 | AP16: =+IF(AV11="SI",1,"") -> 1 | AQ16: =+AS16/$H$9 -> 80.5 | AR16: =ROUNDDOWN(AS16/$C$13,0) -> 13 | AS16: 161 | AT16: =IF(AR16=0,0,AR16+1) -> 14 | AU16: =IF(AV16="","",1/(AV16+0.01)) -> 0.16638935 | AV16: =IF(AS16>0,ROUNDDOWN(('Diseño estructura &CP'!$AZ$5/AS16),0),"") -> 6 | AX16: Lado 1 | AY16: =IF(AV11="SI",MAX(AS16:AS224),0) -> 164 | AZ16: metros | BA16: =IFERROR(1/(BB16+0.01),0) -> 0.33222591 | BB16: =IFERROR(IF(AY16="",0,ROUNDDOWN(('Diseño estructura &CP'!$AZ$6/AY16),0)),0) -> 3 | BD16: T1 | BE16: =IF(AV$11="SI",AP$14,"") -> 76 | BF16: =IF(BE16="","",BE16*$R$15) -> 304 | BG16: =1/(BH16+0.01) -> 0.99009901 | BH16: =IFERROR(ROUNDDOWN(('Diseño estructura &CP'!$AZ$8/BF16),0),0) -> 1 | BJ16: =+IF(BP11="SI",1,"") -> 1 | BK16: =+BM16/$H$9 -> 99.75 | BL16: =ROUNDDOWN(BM16/$BK$13,0) -> 18 | BM16: 199.5 | BN16: =IF(BL16=0,0,BL16+1) -> 19 | BO16: =IF(BP16="","",1/(BP16+0.01)) -> 0.1996008 | BP16: =IF(BM16>0,ROUNDDOWN(('Diseño estructura &CP'!$AZ$5/BM16),0),"") -> 5 | BR16: Lado 1 | BS16: =IF(BP11="SI",MAX(BM16:BM224),0) -> 199.5 | BT16: metros | BU16: =IFERROR(1/(BV16+0.01),0) -> 0.49751244 | BV16: =IFERROR(IF(BS16="",0,ROUNDDOWN(('Diseño estructura &CP'!$AZ$6/BS16),0)),0) -> 2 | BX16: T1 | BY16: =IF(BP$11="SI",BJ$14,"") -> 30 | BZ16: =IF(BY16="","",BY16*$R$15) -> 120 | CA16: =1/(CB16+0.01) -> 0.24937656 | CB16: =IFERROR(ROUNDDOWN(('Diseño estructura &CP'!$AZ$8/BZ16),0),0) -> 4 | CD16: =+IF(CJ11="SI",1,"") | CE16: =+CG16/$H$9 -> 0 | CF16: =ROUNDDOWN(CG16/$C$13,0) -> 0 | CH16: =IF(CF16=0,0,CF16+1) -> 0 | CI16: =IF(CJ16="","",1/(CJ16+0.01)) | CJ16: =IF(CG16>0,ROUNDDOWN(('Diseño estructura &CP'!$AZ$5/CG16),0),"") | CL16: Lado 1 | CM16: =IF(CJ11="SI",MAX(CG16:CG224),0) -> 0 | CN16: metros | CO16: =IFERROR(1/(CP16+0.01),0) -> 100 | CP16: =IFERROR(IF(CM16="",0,ROUNDDOWN(('Diseño estructura &CP'!$AZ$6/CM16),0)),0) -> 0 | CR16: T1 | CS16: =IF(CJ$11="SI",CD$14,"") | CT16: =IF(CS16="","",CS16*$R$15) | CU16: =1/(CV16+0.01) -> 100 | CV16: =IFERROR(ROUNDDOWN(('Diseño estructura &CP'!$AZ$8/CT16),0),0) -> 0 | CX16: =+IF(DD11="SI",1,"") | CY16: =+DA16/$H$9 -> 0 | CZ16: =ROUNDDOWN(DA16/$C$13,0) -> 0 | DB16: =IF(CZ16=0,0,CZ16+1) -> 0 | DC16: =IF(DD16="","",1/(DD16+0.01)) | DD16: =IF(DA16>0,ROUNDDOWN(('Diseño estructura &CP'!$AZ$5/DA16),0),"") | DF16: Lado 1 | DG16: =IF(DD11="SI",MAX(DA16:DA224),0) -> 0 | DH16: metros | DI16: =IFERROR(1/(DJ16+0.01),0) -> 100 | DJ16: =IFERROR(IF(DG16="",0,ROUNDDOWN(('Diseño estructura &CP'!$AZ$6/DG16),0)),0) -> 0 | DL16: T1 | DM16: =IF(DD$11="SI",CX$14,"") | DN16: =IF(DM16="","",DM16*$R$15) | DO16: =1/(DP16+0.01) -> 100 | DP16: =IFERROR(ROUNDDOWN(('Diseño estructura &CP'!$AZ$8/DN16),0),0) -> 0 | DR16: =+IF(DX11="SI",1,"") | DS16: =+DU16/$H$9 -> 0 | DT16: =ROUNDDOWN(DU16/$C$13,0) -> 0 | DV16: =IF(DT16=0,0,DT16+1) -> 0 | DW16: =IF(DX16="","",1/(DX16+0.01)) | DX16: =IF(DU16>0,ROUNDDOWN(('Diseño estructura &CP'!$AZ$5/DU16),0),"") | DZ16: Lado 1 | EA16: =IF(DX11="SI",MAX(DU16:DU224),0) -> 0 | EB16: metros | EC16: =IFERROR(1/(ED16+0.01),0) -> 100 | ED16: =IFERROR(IF(EA16="",0,ROUNDDOWN(('Diseño estructura &CP'!$AZ$6/EA16),0)),0) -> 0 | EF16: T1 | EG16: =IF(DX$11="SI",DR$14,"") | EH16: =IF(EG16="","",EG16*$R$15) | EI16: =1/(EJ16+0.01) -> 100 | EJ16: =IFERROR(ROUNDDOWN(('Diseño estructura &CP'!$AZ$8/EH16),0),0) -> 0 | EL16: =+IF(ER11="SI",1,"") | EM16: =+EO16/$H$9 -> 0 | EN16: =ROUNDDOWN(EO16/$C$13,0) -> 0 | EP16: =IF(EN16=0,0,EN16+1) -> 0 | EQ16: =IF(ER16="","",1/(ER16+0.01)) | ER16: =IF(EO16>0,ROUNDDOWN(('Diseño estructura &CP'!$AZ$5/EO16),0),"") | ET16: Lado 1 | EU16: =IF(ER11="SI",MAX(EO16:EO224),0) -> 0 | EV16: metros | EW16: =IFERROR(1/(EX16+0.01),0) -> 100 | EX16: =IFERROR(IF(EU16="",0,ROUNDDOWN(('Diseño estructura &CP'!$AZ$6/EU16),0)),0) -> 0 | EZ16: T1 | FA16: =IF(ER$11="SI",EL$14,"") | FB16: =IF(FA16="","",FA16*$R$15) | FC16: =1/(FD16+0.01) -> 100 | FD16: =IFERROR(ROUNDDOWN(('Diseño estructura &CP'!$AZ$8/FB16),0),0) -> 0 | FF16: =+IF(FL11="SI",1,"") | FG16: =+FI16/$H$9 -> 0 | FH16: =ROUNDDOWN(FI16/$C$13,0) -> 0 | FJ16: =IF(FH16=0,0,FH16+1) -> 0 | FK16: =IF(FL16="","",1/(FL16+0.01)) | FL16: =IF(FI16>0,ROUNDDOWN(('Diseño estructura &CP'!$AZ$5/FI16),0),"") | FN16: Lado 1 | FO16: =IF(FL11="SI",MAX(FI16:FI224),0) -> 0 | FP16: metros | FQ16: =IFERROR(1/(FR16+0.01),0) -> 100 | FR16: =IFERROR(IF(FO16="",0,ROUNDDOWN(('Diseño estructura &CP'!$AZ$6/FO16),0)),0) -> 0 | FT16: T1 | FU16: =IF(FL$11="SI",FF$14,"") | FV16: =IF(FU16="","",FU16*$R$15) | FW16: =1/(FX16+0.01) -> 100 | FX16: =IFERROR(ROUNDDOWN(('Diseño estructura &CP'!$AZ$8/FV16),0),0) -> 0 | FZ16: =+IF(GF11="SI",1,"") | GA16: =+GC16/$H$9 -> 0 | GB16: =ROUNDDOWN(GC16/$C$13,0) -> 0 | GD16: =IF(GB16=0,0,GB16+1) -> 0 | GE16: =IF(GF16="","",1/(GF16+0.01)) | GF16: =IF(GC16>0,ROUNDDOWN(('Diseño estructura &CP'!$AZ$5/GC16),0),"") | GH16: Lado 1 | GI16: =IF(GF11="SI",MAX(GC16:GC224),0) -> 0 | GJ16: metros | GK16: =IFERROR(1/(GL16+0.01),0) -> 100 | GL16: =IFERROR(IF(GI16="",0,ROUNDDOWN(('Diseño estructura &CP'!$AZ$6/GI16),0)),0) -> 0 | GN16: T1 | GO16: =IF(GF$11="SI",FZ$14,"") | GP16: =IF(GO16="","",GO16*$R$15) | GQ16: =1/(GR16+0.01) -> 100 | GR16: =IFERROR(ROUNDDOWN(('Diseño estructura &CP'!$AZ$8/GP16),0),0) -> 0
B17: =+IF(C17=0,"",B16+1) -> 2 | C17: =+E17/$H$9 -> 6 | D17: =ROUNDDOWN(E17/$C$13,0) -> 1 | E17: 12 | F17: =IF(D17=0,0,D17+1) -> 2 | G17: =IF(H17="","",1/(H17+0.01)) -> 0.012046741 | H17: =IF(E17>0,ROUNDDOWN(('Diseño estructura &CP'!$AZ$5/E17),0),"") -> 83 | J17: Lado 2 | K17: =IF(H11="SI",MAX(E16:E224),0) -> 160 | L17: metros | M17: =IFERROR(1/(N17+0.01),0) -> 0.33222591 | N17: =IFERROR(IF(K17="",0,ROUNDDOWN(('Diseño estructura &CP'!$AZ$6/K17),0)),0) -> 3 | P17: T2 | Q17: =IF(H$11="SI",B$14,"") -> 106 | R17: =IF(Q17="","",Q17*$R$15) -> 424 | S17: =1/(T17+0.01) -> 0.99009901 | T17: =IFERROR(ROUNDDOWN(('Diseño estructura &CP'!$AZ$8/R17),0),0) -> 1 | V17: =+IF(W17=0,"",V16+1) -> 2 | W17: =+Y17/$H$9 -> 76 | X17: =ROUNDDOWN(Y17/$C$13,0) -> 12 | Y17: 152 | Z17: =IF(X17=0,0,X17+1) -> 13 | AA17: =IF(AB17="","",1/(AB17+0.01)) -> 0.16638935 | AB17: =IF(Y17>0,ROUNDDOWN(('Diseño estructura &CP'!$AZ$5/Y17),0),"") -> 6 | AD17: Lado 2 | AE17: =IF(AB11="SI",MAX(Y16:Y224),0) -> 189 | AF17: metros | AG17: =IFERROR(1/(AH17+0.01),0) -> 0.49751244 | AH17: =IFERROR(IF(AE17="",0,ROUNDDOWN(('Diseño estructura &CP'!$AZ$6/AE17),0)),0) -> 2 | AJ17: T2 | AK17: =IF(AB$11="SI",V$14,"") -> 55 | AL17: =IF(AK17="","",AK17*$R$15) -> 220 | AM17: =1/(AN17+0.01) -> 0.49751244 | AN17: =IFERROR(ROUNDDOWN(('Diseño estructura &CP'!$AZ$8/AL17),0),0) -> 2 | AP17: =+IF(AQ17=0,"",AP16+1) -> 2 | AQ17: =+AS17/$H$9 -> 81 | AR17: =ROUNDDOWN(AS17/$C$13,0) -> 13 | AS17: 162 | AT17: =IF(AR17=0,0,AR17+1) -> 14 | AU17: =IF(AV17="","",1/(AV17+0.01)) -> 0.16638935 | AV17: =IF(AS17>0,ROUNDDOWN(('Diseño estructura &CP'!$AZ$5/AS17),0),"") -> 6 | AX17: Lado 2 | AY17: 330 | AZ17: metros | BA17: =IFERROR(1/(BB17+0.01),0) -> 0.99009901 | BB17: =IFERROR(IF(AY17="",0,ROUNDDOWN(('Diseño estructura &CP'!$AZ$6/AY17),0)),0) -> 1 | BD17: T2 | BE17: =IF(AV$11="SI",AP$14,"") -> 76 | BF17: =IF(BE17="","",BE17*$R$15) -> 304 | BG17: =1/(BH17+0.01) -> 0.99009901 | BH17: =IFERROR(ROUNDDOWN(('Diseño estructura &CP'!$AZ$8/BF17),0),0) -> 1 | BJ17: =+IF(BK17=0,"",BJ16+1) -> 2 | BK17: =+BM17/$H$9 -> 99.5 | BL17: =ROUNDDOWN(BM17/$BK$13,0) -> 18 | BM17: 199 | BN17: =IF(BL17=0,0,BL17+1) -> 19 | BO17: =IF(BP17="","",1/(BP17+0.01)) -> 0.1996008 | BP17: =IF(BM17>0,ROUNDDOWN(('Diseño estructura &CP'!$AZ$5/BM17),0),"") -> 5 | BR17: Lado 2 | BS17: 340 | BT17: metros | BU17: =IFERROR(1/(BV17+0.01),0) -> 0.99009901 | BV17: =IFERROR(IF(BS17="",0,ROUNDDOWN(('Diseño estructura &CP'!$AZ$6/BS17),0)),0) -> 1 | BX17: T2 | BY17: =IF(BP$11="SI",BJ$14,"") -> 30 | BZ17: =IF(BY17="","",BY17*$R$15) -> 120 | CA17: =1/(CB17+0.01) -> 0.24937656 | CB17: =IFERROR(ROUNDDOWN(('Diseño estructura &CP'!$AZ$8/BZ17),0),0) -> 4 | CD17: =+IF(CE17=0,"",CD16+1) | CE17: =+CG17/$H$9 -> 0 | CF17: =ROUNDDOWN(CG17/$C$13,0) -> 0 | CH17: =IF(CF17=0,0,CF17+1) -> 0 | CI17: =IF(CJ17="","",1/(CJ17+0.01)) | CJ17: =IF(CG17>0,ROUNDDOWN(('Diseño estructura &CP'!$AZ$5/CG17),0),"") | CL17: Lado 2 | CM17: =IF(CJ11="SI",MAX(CG16:CG224),0) -> 0 | CN17: metros | CO17: =IFERROR(1/(CP17+0.01),0) -> 100 | CP17: =IFERROR(IF(CM17="",0,ROUNDDOWN(('Diseño estructura &CP'!$AZ$6/CM17),0)),0) -> 0 | CR17: T2 | CS17: =IF(CJ$11="SI",CD$14,"") | CT17: =IF(CS17="","",CS17*$R$15) | CU17: =1/(CV17+0.01) -> 100 | CV17: =IFERROR(ROUNDDOWN(('Diseño estructura &CP'!$AZ$8/CT17),0),0) -> 0 | CX17: =+IF(CY17=0,"",CX16+1) | CY17: =+DA17/$H$9 -> 0 | CZ17: =ROUNDDOWN(DA17/$C$13,0) -> 0 | DB17: =IF(CZ17=0,0,CZ17+1) -> 0 | DC17: =IF(DD17="","",1/(DD17+0.01)) | DD17: =IF(DA17>0,ROUNDDOWN(('Diseño estructura &CP'!$AZ$5/DA17),0),"") | DF17: Lado 2 | DG17: =IF(DD11="SI",MAX(DA16:DA224),0) -> 0 | DH17: metros | DI17: =IFERROR(1/(DJ17+0.01),0) -> 100 | DJ17: =IFERROR(IF(DG17="",0,ROUNDDOWN(('Diseño estructura &CP'!$AZ$6/DG17),0)),0) -> 0 | DL17: T2 | DM17: =IF(DD$11="SI",CX$14,"") | DN17: =IF(DM17="","",DM17*$R$15) | DO17: =1/(DP17+0.01) -> 100 | DP17: =IFERROR(ROUNDDOWN(('Diseño estructura &CP'!$AZ$8/DN17),0),0) -> 0 | DR17: =+IF(DS17=0,"",DR16+1) | DS17: =+DU17/$H$9 -> 0 | DT17: =ROUNDDOWN(DU17/$C$13,0) -> 0 | DV17: =IF(DT17=0,0,DT17+1) -> 0 | DW17: =IF(DX17="","",1/(DX17+0.01)) | DX17: =IF(DU17>0,ROUNDDOWN(('Diseño estructura &CP'!$AZ$5/DU17),0),"") | DZ17: Lado 2 | EA17: =IF(DX11="SI",MAX(DU16:DU224),0) -> 0 | EB17: metros | EC17: =IFERROR(1/(ED17+0.01),0) -> 100 | ED17: =IFERROR(IF(EA17="",0,ROUNDDOWN(('Diseño estructura &CP'!$AZ$6/EA17),0)),0) -> 0 | EF17: T2 | EG17: =IF(DX$11="SI",DR$14,"") | EH17: =IF(EG17="","",EG17*$R$15) | EI17: =1/(EJ17+0.01) -> 100 | EJ17: =IFERROR(ROUNDDOWN(('Diseño estructura &CP'!$AZ$8/EH17),0),0) -> 0 | EL17: =+IF(EM17=0,"",EL16+1) | EM17: =+EO17/$H$9 -> 0 | EN17: =ROUNDDOWN(EO17/$C$13,0) -> 0 | EP17: =IF(EN17=0,0,EN17+1) -> 0 | EQ17: =IF(ER17="","",1/(ER17+0.01)) | ER17: =IF(EO17>0,ROUNDDOWN(('Diseño estructura &CP'!$AZ$5/EO17),0),"") | ET17: Lado 2 | EU17: =IF(ER11="SI",MAX(EO16:EO224),0) -> 0 | EV17: metros | EW17: =IFERROR(1/(EX17+0.01),0) -> 100 | EX17: =IFERROR(IF(EU17="",0,ROUNDDOWN(('Diseño estructura &CP'!$AZ$6/EU17),0)),0) -> 0 | EZ17: T2 | FA17: =IF(ER$11="SI",EL$14,"") | FB17: =IF(FA17="","",FA17*$R$15) | FC17: =1/(FD17+0.01) -> 100 | FD17: =IFERROR(ROUNDDOWN(('Diseño estructura &CP'!$AZ$8/FB17),0),0) -> 0 | FF17: =+IF(FG17=0,"",FF16+1) | FG17: =+FI17/$H$9 -> 0 | FH17: =ROUNDDOWN(FI17/$C$13,0) -> 0 | FJ17: =IF(FH17=0,0,FH17+1) -> 0 | FK17: =IF(FL17="","",1/(FL17+0.01)) | FL17: =IF(FI17>0,ROUNDDOWN(('Diseño estructura &CP'!$AZ$5/FI17),0),"") | FN17: Lado 2 | FO17: =IF(FL11="SI",MAX(FI16:FI224),0) -> 0 | FP17: metros | FQ17: =IFERROR(1/(FR17+0.01),0) -> 100 | FR17: =IFERROR(IF(FO17="",0,ROUNDDOWN(('Diseño estructura &CP'!$AZ$6/FO17),0)),0) -> 0 | FT17: T2 | FU17: =IF(FL$11="SI",FF$14,"") | FV17: =IF(FU17="","",FU17*$R$15) | FW17: =1/(FX17+0.01) -> 100 | FX17: =IFERROR(ROUNDDOWN(('Diseño estructura &CP'!$AZ$8/FV17),0),0) -> 0 | FZ17: =+IF(GA17=0,"",FZ16+1) | GA17: =+GC17/$H$9 -> 0 | GB17: =ROUNDDOWN(GC17/$C$13,0) -> 0 | GD17: =IF(GB17=0,0,GB17+1) -> 0 | GE17: =IF(GF17="","",1/(GF17+0.01)) | GF17: =IF(GC17>0,ROUNDDOWN(('Diseño estructura &CP'!$AZ$5/GC17),0),"") | GH17: Lado 2 | GI17: =IF(GF11="SI",MAX(GC16:GC224),0) -> 0 | GJ17: metros | GK17: =IFERROR(1/(GL17+0.01),0) -> 100 | GL17: =IFERROR(IF(GI17="",0,ROUNDDOWN(('Diseño estructura &CP'!$AZ$6/GI17),0)),0) -> 0 | GN17: T2 | GO17: =IF(GF$11="SI",FZ$14,"") | GP17: =IF(GO17="","",GO17*$R$15) | GQ17: =1/(GR17+0.01) -> 100 | GR17: =IFERROR(ROUNDDOWN(('Diseño estructura &CP'!$AZ$8/GP17),0),0) -> 0
B18: =+IF(C18=0,"",B17+1) -> 3 | C18: =+E18/$H$9 -> 7.5 | D18: =ROUNDDOWN(E18/$C$13,0) -> 1 | E18: 15 | F18: =IF(D18=0,0,D18+1) -> 2 | G18: =IF(H18="","",1/(H18+0.01)) -> 0.01514922 | H18: =IF(E18>0,ROUNDDOWN(('Diseño estructura &CP'!$AZ$5/E18),0),"") -> 66 | J18: Lado 3 | K18: =IF(H11="SI",B14*F8,0) -> 424 | L18: metros | M18: =IFERROR(1/(N18+0.01),0) -> 0.99009901 | N18: =IFERROR(IF(K18="",0,ROUNDDOWN(('Diseño estructura &CP'!$AZ$6/K18),0)),0) -> 1 | P18: T3 | Q18: =IF(H$11="SI",B$14,"") -> 106 | R18: =IF(Q18="","",Q18*$R$15) -> 424 | S18: =1/(T18+0.01) -> 0.99009901 | T18: =IFERROR(ROUNDDOWN(('Diseño estructura &CP'!$AZ$8/R18),0),0) -> 1 | V18: =+IF(W18=0,"",V17+1) -> 3 | W18: =+Y18/$H$9 -> 76.5 | X18: =ROUNDDOWN(Y18/$C$13,0) -> 12 | Y18: 153 | Z18: =IF(X18=0,0,X18+1) -> 13 | AA18: =IF(AB18="","",1/(AB18+0.01)) -> 0.16638935 | AB18: =IF(Y18>0,ROUNDDOWN(('Diseño estructura &CP'!$AZ$5/Y18),0),"") -> 6 | AD18: Lado 3 | AE18: =IF(AB11="SI",V14*Z8,0) -> 220 | AF18: metros | AG18: =IFERROR(1/(AH18+0.01),0) -> 0.49751244 | AH18: =IFERROR(IF(AE18="",0,ROUNDDOWN(('Diseño estructura &CP'!$AZ$6/AE18),0)),0) -> 2 | AJ18: T3 | AK18: =IF(AB$11="SI",V$14,"") -> 55 | AL18: =IF(AK18="","",AK18*$R$15) -> 220 | AM18: =1/(AN18+0.01) -> 0.49751244 | AN18: =IFERROR(ROUNDDOWN(('Diseño estructura &CP'!$AZ$8/AL18),0),0) -> 2 | AP18: =+IF(AQ18=0,"",AP17+1) -> 3 | AQ18: =+AS18/$H$9 -> 81 | AR18: =ROUNDDOWN(AS18/$C$13,0) -> 13 | AS18: 162 | AT18: =IF(AR18=0,0,AR18+1) -> 14 | AU18: =IF(AV18="","",1/(AV18+0.01)) -> 0.16638935 | AV18: =IF(AS18>0,ROUNDDOWN(('Diseño estructura &CP'!$AZ$5/AS18),0),"") -> 6 | AX18: Lado 3 | AY18: =IF(AV11="SI",AP14*AT8,0) -> 304 | AZ18: metros | BA18: =IFERROR(1/(BB18+0.01),0) -> 0.99009901 | BB18: =IFERROR(IF(AY18="",0,ROUNDDOWN(('Diseño estructura &CP'!$AZ$6/AY18),0)),0) -> 1 | BD18: T3 | BE18: =IF(AV$11="SI",AP$14,"") -> 76 | BF18: =IF(BE18="","",BE18*$R$15) -> 304 | BG18: =1/(BH18+0.01) -> 0.99009901 | BH18: =IFERROR(ROUNDDOWN(('Diseño estructura &CP'!$AZ$8/BF18),0),0) -> 1 | BJ18: =+IF(BK18=0,"",BJ17+1) -> 3 | BK18: =+BM18/$H$9 -> 99.25 | BL18: =ROUNDDOWN(BM18/$BK$13,0) -> 18 | BM18: 198.5 | BN18: =IF(BL18=0,0,BL18+1) -> 19 | BO18: =IF(BP18="","",1/(BP18+0.01)) -> 0.1996008 | BP18: =IF(BM18>0,ROUNDDOWN(('Diseño estructura &CP'!$AZ$5/BM18),0),"") -> 5 | BR18: Lado 3 | BS18: =IF(BP11="SI",BJ14*BN8,0) -> 135 | BT18: metros | BU18: =IFERROR(1/(BV18+0.01),0) -> 0.33222591 | BV18: =IFERROR(IF(BS18="",0,ROUNDDOWN(('Diseño estructura &CP'!$AZ$6/BS18),0)),0) -> 3 | BX18: T3 | BY18: =IF(BP$11="SI",BJ$14,"") -> 30 | BZ18: =IF(BY18="","",BY18*$R$15) -> 120 | CA18: =1/(CB18+0.01) -> 0.24937656 | CB18: =IFERROR(ROUNDDOWN(('Diseño estructura &CP'!$AZ$8/BZ18),0),0) -> 4 | CD18: =+IF(CE18=0,"",CD17+1) | CE18: =+CG18/$H$9 -> 0 | CF18: =ROUNDDOWN(CG18/$C$13,0) -> 0 | CH18: =IF(CF18=0,0,CF18+1) -> 0 | CI18: =IF(CJ18="","",1/(CJ18+0.01)) | CJ18: =IF(CG18>0,ROUNDDOWN(('Diseño estructura &CP'!$AZ$5/CG18),0),"") | CL18: Lado 3 | CM18: =IF(CJ11="SI",CD14*CH8,0) -> 0 | CN18: metros | CO18: =IFERROR(1/(CP18+0.01),0) -> 100 | CP18: =IFERROR(IF(CM18="",0,ROUNDDOWN(('Diseño estructura &CP'!$AZ$6/CM18),0)),0) -> 0 | CR18: T3 | CS18: =IF(CJ$11="SI",CD$14,"") | CT18: =IF(CS18="","",CS18*$R$15) | CU18: =1/(CV18+0.01) -> 100 | CV18: =IFERROR(ROUNDDOWN(('Diseño estructura &CP'!$AZ$8/CT18),0),0) -> 0 | CX18: =+IF(CY18=0,"",CX17+1) | CY18: =+DA18/$H$9 -> 0 | CZ18: =ROUNDDOWN(DA18/$C$13,0) -> 0 | DB18: =IF(CZ18=0,0,CZ18+1) -> 0 | DC18: =IF(DD18="","",1/(DD18+0.01)) | DD18: =IF(DA18>0,ROUNDDOWN(('Diseño estructura &CP'!$AZ$5/DA18),0),"") | DF18: Lado 3 | DG18: =IF(DD11="SI",CX14*DB8,0) -> 0 | DH18: metros | DI18: =IFERROR(1/(DJ18+0.01),0) -> 100 | DJ18: =IFERROR(IF(DG18="",0,ROUNDDOWN(('Diseño estructura &CP'!$AZ$6/DG18),0)),0) -> 0 | DL18: T3 | DM18: =IF(DD$11="SI",CX$14,"") | DN18: =IF(DM18="","",DM18*$R$15) | DO18: =1/(DP18+0.01) -> 100 | DP18: =IFERROR(ROUNDDOWN(('Diseño estructura &CP'!$AZ$8/DN18),0),0) -> 0 | DR18: =+IF(DS18=0,"",DR17+1) | DS18: =+DU18/$H$9 -> 0 | DT18: =ROUNDDOWN(DU18/$C$13,0) -> 0 | DV18: =IF(DT18=0,0,DT18+1) -> 0 | DW18: =IF(DX18="","",1/(DX18+0.01)) | DX18: =IF(DU18>0,ROUNDDOWN(('Diseño estructura &CP'!$AZ$5/DU18),0),"") | DZ18: Lado 3 | EA18: =IF(DX11="SI",DR14*DV8,0) -> 0 | EB18: metros | EC18: =IFERROR(1/(ED18+0.01),0) -> 100 | ED18: =IFERROR(IF(EA18="",0,ROUNDDOWN(('Diseño estructura &CP'!$AZ$6/EA18),0)),0) -> 0 | EF18: T3 | EG18: =IF(DX$11="SI",DR$14,"") | EH18: =IF(EG18="","",EG18*$R$15) | EI18: =1/(EJ18+0.01) -> 100 | EJ18: =IFERROR(ROUNDDOWN(('Diseño estructura &CP'!$AZ$8/EH18),0),0) -> 0 | EL18: =+IF(EM18=0,"",EL17+1) | EM18: =+EO18/$H$9 -> 0 | EN18: =ROUNDDOWN(EO18/$C$13,0) -> 0 | EP18: =IF(EN18=0,0,EN18+1) -> 0 | EQ18: =IF(ER18="","",1/(ER18+0.01)) | ER18: =IF(EO18>0,ROUNDDOWN(('Diseño estructura &CP'!$AZ$5/EO18),0),"") | ET18: Lado 3 | EU18: =IF(ER11="SI",EL14*EP8,0) -> 0 | EV18: metros | EW18: =IFERROR(1/(EX18+0.01),0) -> 100 | EX18: =IFERROR(IF(EU18="",0,ROUNDDOWN(('Diseño estructura &CP'!$AZ$6/EU18),0)),0) -> 0 | EZ18: T3 | FA18: =IF(ER$11="SI",EL$14,"") | FB18: =IF(FA18="","",FA18*$R$15) | FC18: =1/(FD18+0.01) -> 100 | FD18: =IFERROR(ROUNDDOWN(('Diseño estructura &CP'!$AZ$8/FB18),0),0) -> 0 | FF18: =+IF(FG18=0,"",FF17+1) | FG18: =+FI18/$H$9 -> 0 | FH18: =ROUNDDOWN(FI18/$C$13,0) -> 0 | FJ18: =IF(FH18=0,0,FH18+1) -> 0 | FK18: =IF(FL18="","",1/(FL18+0.01)) | FL18: =IF(FI18>0,ROUNDDOWN(('Diseño estructura &CP'!$AZ$5/FI18),0),"") | FN18: Lado 3 | FO18: =IF(FL11="SI",FF14*FJ8,0) -> 0 | FP18: metros | FQ18: =IFERROR(1/(FR18+0.01),0) -> 100 | FR18: =IFERROR(IF(FO18="",0,ROUNDDOWN(('Diseño estructura &CP'!$AZ$6/FO18),0)),0) -> 0 | FT18: T3 | FU18: =IF(FL$11="SI",FF$14,"") | FV18: =IF(FU18="","",FU18*$R$15) | FW18: =1/(FX18+0.01) -> 100 | FX18: =IFERROR(ROUNDDOWN(('Diseño estructura &CP'!$AZ$8/FV18),0),0) -> 0 | FZ18: =+IF(GA18=0,"",FZ17+1) | GA18: =+GC18/$H$9 -> 0 | GB18: =ROUNDDOWN(GC18/$C$13,0) -> 0 | GD18: =IF(GB18=0,0,GB18+1) -> 0 | GE18: =IF(GF18="","",1/(GF18+0.01)) | GF18: =IF(GC18>0,ROUNDDOWN(('Diseño estructura &CP'!$AZ$5/GC18),0),"") | GH18: Lado 3 | GI18: =IF(GF11="SI",FZ14*GD8,0) -> 0 | GJ18: metros | GK18: =IFERROR(1/(GL18+0.01),0) -> 100 | GL18: =IFERROR(IF(GI18="",0,ROUNDDOWN(('Diseño estructura &CP'!$AZ$6/GI18),0)),0) -> 0 | GN18: T3 | GO18: =IF(GF$11="SI",FZ$14,"") | GP18: =IF(GO18="","",GO18*$R$15) | GQ18: =1/(GR18+0.01) -> 100 | GR18: =IFERROR(ROUNDDOWN(('Diseño estructura &CP'!$AZ$8/GP18),0),0) -> 0
B19: =+IF(C19=0,"",B18+1) -> 4 | C19: =+E19/$H$9 -> 9.5 | D19: =ROUNDDOWN(E19/$C$13,0) -> 1 | E19: 19 | F19: =IF(D19=0,0,D19+1) -> 2 | G19: =IF(H19="","",1/(H19+0.01)) -> 0.019227072 | H19: =IF(E19>0,ROUNDDOWN(('Diseño estructura &CP'!$AZ$5/E19),0),"") -> 52 | J19: Lado 4 | K19: =IF(H11="SI",B14*F8,0) -> 424 | L19: metros | M19: =IFERROR(1/(N19+0.01),0) -> 0.99009901 | N19: =IFERROR(IF(K19="",0,ROUNDDOWN(('Diseño estructura &CP'!$AZ$6/K19),0)),0) -> 1 | P19: T4 | Q19: =IF(H$11="SI",B$14,"") -> 106 | R19: =IF(Q19="","",Q19*$R$15) -> 424 | S19: =1/(T19+0.01) -> 0.99009901 | T19: =IFERROR(ROUNDDOWN(('Diseño estructura &CP'!$AZ$8/R19),0),0) -> 1 | V19: =+IF(W19=0,"",V18+1) -> 4 | W19: =+Y19/$H$9 -> 77.75 | X19: =ROUNDDOWN(Y19/$C$13,0) -> 12 | Y19: 155.5 | Z19: =IF(X19=0,0,X19+1) -> 13 | AA19: =IF(AB19="","",1/(AB19+0.01)) -> 0.16638935 | AB19: =IF(Y19>0,ROUNDDOWN(('Diseño estructura &CP'!$AZ$5/Y19),0),"") -> 6 | AD19: Lado 4 | AE19: =IF(AB11="SI",V14*Z8,0) -> 220 | AF19: metros | AG19: =IFERROR(1/(AH19+0.01),0) -> 0.49751244 | AH19: =IFERROR(IF(AE19="",0,ROUNDDOWN(('Diseño estructura &CP'!$AZ$6/AE19),0)),0) -> 2 | AJ19: T4 | AK19: =IF(AB$11="SI",V$14,"") -> 55 | AL19: =IF(AK19="","",AK19*$R$15) -> 220 | AM19: =1/(AN19+0.01) -> 0.49751244 | AN19: =IFERROR(ROUNDDOWN(('Diseño estructura &CP'!$AZ$8/AL19),0),0) -> 2 | AP19: =+IF(AQ19=0,"",AP18+1) -> 4 | AQ19: =+AS19/$H$9 -> 81.5 | AR19: =ROUNDDOWN(AS19/$C$13,0) -> 13 | AS19: 163 | AT19: =IF(AR19=0,0,AR19+1) -> 14 | AU19: =IF(AV19="","",1/(AV19+0.01)) -> 0.16638935 | AV19: =IF(AS19>0,ROUNDDOWN(('Diseño estructura &CP'!$AZ$5/AS19),0),"") -> 6 | AX19: Lado 4 | AY19: =IF(AV11="SI",AP14*AT8,0) -> 304 | AZ19: metros | BA19: =IFERROR(1/(BB19+0.01),0) -> 0.99009901 | BB19: =IFERROR(IF(AY19="",0,ROUNDDOWN(('Diseño estructura &CP'!$AZ$6/AY19),0)),0) -> 1 | BD19: T4 | BE19: =IF(AV$11="SI",AP$14,"") -> 76 | BF19: =IF(BE19="","",BE19*$R$15) -> 304 | BG19: =1/(BH19+0.01) -> 0.99009901 | BH19: =IFERROR(ROUNDDOWN(('Diseño estructura &CP'!$AZ$8/BF19),0),0) -> 1 | BJ19: =+IF(BK19=0,"",BJ18+1) -> 4 | BK19: =+BM19/$H$9 -> 98.75 | BL19: =ROUNDDOWN(BM19/$BK$13,0) -> 17 | BM19: 197.5 | BN19: =IF(BL19=0,0,BL19+1) -> 18 | BO19: =IF(BP19="","",1/(BP19+0.01)) -> 0.1996008 | BP19: =IF(BM19>0,ROUNDDOWN(('Diseño estructura &CP'!$AZ$5/BM19),0),"") -> 5 | BR19: Lado 4 | BS19: =IF(BP11="SI",BJ14*BN8,0) -> 135 | BT19: metros | BU19: =IFERROR(1/(BV19+0.01),0) -> 0.33222591 | BV19: =IFERROR(IF(BS19="",0,ROUNDDOWN(('Diseño estructura &CP'!$AZ$6/BS19),0)),0) -> 3 | BX19: T4 | BY19: =IF(BP$11="SI",BJ$14,"") -> 30 | BZ19: =IF(BY19="","",BY19*$R$15) -> 120 | CA19: =1/(CB19+0.01) -> 0.24937656 | CB19: =IFERROR(ROUNDDOWN(('Diseño estructura &CP'!$AZ$8/BZ19),0),0) -> 4 | CD19: =+IF(CE19=0,"",CD18+1) | CE19: =+CG19/$H$9 -> 0 | CF19: =ROUNDDOWN(CG19/$C$13,0) -> 0 | CH19: =IF(CF19=0,0,CF19+1) -> 0 | CI19: =IF(CJ19="","",1/(CJ19+0.01)) | CJ19: =IF(CG19>0,ROUNDDOWN(('Diseño estructura &CP'!$AZ$5/CG19),0),"") | CL19: Lado 4 | CM19: =IF(CJ11="SI",CD14*CH8,0) -> 0 | CN19: metros | CO19: =IFERROR(1/(CP19+0.01),0) -> 100 | CP19: =IFERROR(IF(CM19="",0,ROUNDDOWN(('Diseño estructura &CP'!$AZ$6/CM19),0)),0) -> 0 | CR19: T4 | CS19: =IF(CJ$11="SI",CD$14,"") | CT19: =IF(CS19="","",CS19*$R$15) | CU19: =1/(CV19+0.01) -> 100 | CV19: =IFERROR(ROUNDDOWN(('Diseño estructura &CP'!$AZ$8/CT19),0),0) -> 0 | CX19: =+IF(CY19=0,"",CX18+1) | CY19: =+DA19/$H$9 -> 0 | CZ19: =ROUNDDOWN(DA19/$C$13,0) -> 0 | DB19: =IF(CZ19=0,0,CZ19+1) -> 0 | DC19: =IF(DD19="","",1/(DD19+0.01)) | DD19: =IF(DA19>0,ROUNDDOWN(('Diseño estructura &CP'!$AZ$5/DA19),0),"") | DF19: Lado 4 | DG19: =IF(DD11="SI",CX14*DB8,0) -> 0 | DH19: metros | DI19: =IFERROR(1/(DJ19+0.01),0) -> 100 | DJ19: =IFERROR(IF(DG19="",0,ROUNDDOWN(('Diseño estructura &CP'!$AZ$6/DG19),0)),0) -> 0 | DL19: T4 | DM19: =IF(DD$11="SI",CX$14,"") | DN19: =IF(DM19="","",DM19*$R$15) | DO19: =1/(DP19+0.01) -> 100 | DP19: =IFERROR(ROUNDDOWN(('Diseño estructura &CP'!$AZ$8/DN19),0),0) -> 0 | DR19: =+IF(DS19=0,"",DR18+1) | DS19: =+DU19/$H$9 -> 0 | DT19: =ROUNDDOWN(DU19/$C$13,0) -> 0 | DV19: =IF(DT19=0,0,DT19+1) -> 0 | DW19: =IF(DX19="","",1/(DX19+0.01)) | DX19: =IF(DU19>0,ROUNDDOWN(('Diseño estructura &CP'!$AZ$5/DU19),0),"") | DZ19: Lado 4 | EA19: =IF(DX11="SI",DR14*DV8,0) -> 0 | EB19: metros | EC19: =IFERROR(1/(ED19+0.01),0) -> 100 | ED19: =IFERROR(IF(EA19="",0,ROUNDDOWN(('Diseño estructura &CP'!$AZ$6/EA19),0)),0) -> 0 | EF19: T4 | EG19: =IF(DX$11="SI",DR$14,"") | EH19: =IF(EG19="","",EG19*$R$15) | EI19: =1/(EJ19+0.01) -> 100 | EJ19: =IFERROR(ROUNDDOWN(('Diseño estructura &CP'!$AZ$8/EH19),0),0) -> 0 | EL19: =+IF(EM19=0,"",EL18+1) | EM19: =+EO19/$H$9 -> 0 | EN19: =ROUNDDOWN(EO19/$C$13,0) -> 0 | EP19: =IF(EN19=0,0,EN19+1) -> 0 | EQ19: =IF(ER19="","",1/(ER19+0.01)) | ER19: =IF(EO19>0,ROUNDDOWN(('Diseño estructura &CP'!$AZ$5/EO19),0),"") | ET19: Lado 4 | EU19: =IF(ER11="SI",EL14*EP8,0) -> 0 | EV19: metros | EW19: =IFERROR(1/(EX19+0.01),0) -> 100 | EX19: =IFERROR(IF(EU19="",0,ROUNDDOWN(('Diseño estructura &CP'!$AZ$6/EU19),0)),0) -> 0 | EZ19: T4 | FA19: =IF(ER$11="SI",EL$14,"") | FB19: =IF(FA19="","",FA19*$R$15) | FC19: =1/(FD19+0.01) -> 100 | FD19: =IFERROR(ROUNDDOWN(('Diseño estructura &CP'!$AZ$8/FB19),0),0) -> 0 | FF19: =+IF(FG19=0,"",FF18+1) | FG19: =+FI19/$H$9 -> 0 | FH19: =ROUNDDOWN(FI19/$C$13,0) -> 0 | FJ19: =IF(FH19=0,0,FH19+1) -> 0 | FK19: =IF(FL19="","",1/(FL19+0.01)) | FL19: =IF(FI19>0,ROUNDDOWN(('Diseño estructura &CP'!$AZ$5/FI19),0),"") | FN19: Lado 4 | FO19: =IF(FL11="SI",FF14*FJ8,0) -> 0 | FP19: metros | FQ19: =IFERROR(1/(FR19+0.01),0) -> 100 | FR19: =IFERROR(IF(FO19="",0,ROUNDDOWN(('Diseño estructura &CP'!$AZ$6/FO19),0)),0) -> 0 | FT19: T4 | FU19: =IF(FL$11="SI",FF$14,"") | FV19: =IF(FU19="","",FU19*$R$15) | FW19: =1/(FX19+0.01) -> 100 | FX19: =IFERROR(ROUNDDOWN(('Diseño estructura &CP'!$AZ$8/FV19),0),0) -> 0 | FZ19: =+IF(GA19=0,"",FZ18+1) | GA19: =+GC19/$H$9 -> 0 | GB19: =ROUNDDOWN(GC19/$C$13,0) -> 0 | GD19: =IF(GB19=0,0,GB19+1) -> 0 | GE19: =IF(GF19="","",1/(GF19+0.01)) | GF19: =IF(GC19>0,ROUNDDOWN(('Diseño estructura &CP'!$AZ$5/GC19),0),"") | GH19: Lado 4 | GI19: =IF(GF11="SI",FZ14*GD8,0) -> 0 | GJ19: metros | GK19: =IFERROR(1/(GL19+0.01),0) -> 100 | GL19: =IFERROR(IF(GI19="",0,ROUNDDOWN(('Diseño estructura &CP'!$AZ$6/GI19),0)),0) -> 0 | GN19: T4 | GO19: =IF(GF$11="SI",FZ$14,"") | GP19: =IF(GO19="","",GO19*$R$15) | GQ19: =1/(GR19+0.01) -> 100 | GR19: =IFERROR(ROUNDDOWN(('Diseño estructura &CP'!$AZ$8/GP19),0),0) -> 0
B20: =+IF(C20=0,"",B19+1) -> 5 | C20: =+E20/$H$9 -> 12 | D20: =ROUNDDOWN(E20/$C$13,0) -> 2 | E20: 24 | F20: =IF(D20=0,0,D20+1) -> 3 | G20: =IF(H20="","",1/(H20+0.01)) -> 0.024384297 | H20: =IF(E20>0,ROUNDDOWN(('Diseño estructura &CP'!$AZ$5/E20),0),"") -> 41 | J20: Lado 5 | L20: metros | N20: =IFERROR(IF(K20="",0,ROUNDDOWN(('Diseño estructura &CP'!$AZ$6/K20),0)),0) -> 0 | P20: T5 | Q20: =IF(H$11="SI",B$14,"") -> 106 | R20: =IF(Q20="","",Q20*$R$15) -> 424 | S20: =1/(T20+0.01) -> 0.99009901 | T20: =IFERROR(ROUNDDOWN(('Diseño estructura &CP'!$AZ$8/R20),0),0) -> 1 | V20: =+IF(W20=0,"",V19+1) -> 5 | W20: =+Y20/$H$9 -> 78.5 | X20: =ROUNDDOWN(Y20/$C$13,0) -> 13 | Y20: 157 | Z20: =IF(X20=0,0,X20+1) -> 14 | AA20: =IF(AB20="","",1/(AB20+0.01)) -> 0.16638935 | AB20: =IF(Y20>0,ROUNDDOWN(('Diseño estructura &CP'!$AZ$5/Y20),0),"") -> 6 | AD20: Lado 5 | AF20: metros | AH20: =IFERROR(IF(AE20="",0,ROUNDDOWN(('Diseño estructura &CP'!$AZ$6/AE20),0)),0) -> 0 | AJ20: T5 | AK20: =IF(AB$11="SI",V$14,"") -> 55 | AL20: =IF(AK20="","",AK20*$R$15) -> 220 | AM20: =1/(AN20+0.01) -> 0.49751244 | AN20: =IFERROR(ROUNDDOWN(('Diseño estructura &CP'!$AZ$8/AL20),0),0) -> 2 | AP20: =+IF(AQ20=0,"",AP19+1) -> 5 | AQ20: =+AS20/$H$9 -> 81.5 | AR20: =ROUNDDOWN(AS20/$C$13,0) -> 13 | AS20: 163 | AT20: =IF(AR20=0,0,AR20+1) -> 14 | AU20: =IF(AV20="","",1/(AV20+0.01)) -> 0.16638935 | AV20: =IF(AS20>0,ROUNDDOWN(('Diseño estructura &CP'!$AZ$5/AS20),0),"") -> 6 | AX20: Lado 5 | AZ20: metros | BB20: =IFERROR(IF(AY20="",0,ROUNDDOWN(('Diseño estructura &CP'!$AZ$6/AY20),0)),0) -> 0 | BD20: T5 | BE20: =IF(AV$11="SI",AP$14,"") -> 76 | BF20: =IF(BE20="","",BE20*$R$15) -> 304 | BG20: =1/(BH20+0.01) -> 0.99009901 | BH20: =IFERROR(ROUNDDOWN(('Diseño estructura &CP'!$AZ$8/BF20),0),0) -> 1 | BJ20: =+IF(BK20=0,"",BJ19+1) -> 5 | BK20: =+BM20/$H$9 -> 98.5 | BL20: =ROUNDDOWN(BM20/$BK$13,0) -> 17 | BM20: 197 | BN20: =IF(BL20=0,0,BL20+1) -> 18 | BO20: =IF(BP20="","",1/(BP20+0.01)) -> 0.1996008 | BP20: =IF(BM20>0,ROUNDDOWN(('Diseño estructura &CP'!$AZ$5/BM20),0),"") -> 5 | BR20: Lado 5 | BT20: metros | BV20: =IFERROR(IF(BS20="",0,ROUNDDOWN(('Diseño estructura &CP'!$AZ$6/BS20),0)),0) -> 0 | BX20: T5 | BY20: =IF(BP$11="SI",BJ$14,"") -> 30 | BZ20: =IF(BY20="","",BY20*$R$15) -> 120 | CA20: =1/(CB20+0.01) -> 0.24937656 | CB20: =IFERROR(ROUNDDOWN(('Diseño estructura &CP'!$AZ$8/BZ20),0),0) -> 4 | CD20: =+IF(CE20=0,"",CD19+1) | CE20: =+CG20/$H$9 -> 0 | CF20: =ROUNDDOWN(CG20/$C$13,0) -> 0 | CH20: =IF(CF20=0,0,CF20+1) -> 0 | CI20: =IF(CJ20="","",1/(CJ20+0.01)) | CJ20: =IF(CG20>0,ROUNDDOWN(('Diseño estructura &CP'!$AZ$5/CG20),0),"") | CL20: Lado 5 | CN20: metros | CP20: =IFERROR(IF(CM20="",0,ROUNDDOWN(('Diseño estructura &CP'!$AZ$6/CM20),0)),0) -> 0 | CR20: T5 | CS20: =IF(CJ$11="SI",CD$14,"") | CT20: =IF(CS20="","",CS20*$R$15) | CU20: =1/(CV20+0.01) -> 100 | CV20: =IFERROR(ROUNDDOWN(('Diseño estructura &CP'!$AZ$8/CT20),0),0) -> 0 | CX20: =+IF(CY20=0,"",CX19+1) | CY20: =+DA20/$H$9 -> 0 | CZ20: =ROUNDDOWN(DA20/$C$13,0) -> 0 | DB20: =IF(CZ20=0,0,CZ20+1) -> 0 | DC20: =IF(DD20="","",1/(DD20+0.01)) | DD20: =IF(DA20>0,ROUNDDOWN(('Diseño estructura &CP'!$AZ$5/DA20),0),"") | DF20: Lado 5 | DH20: metros | DJ20: =IFERROR(IF(DG20="",0,ROUNDDOWN(('Diseño estructura &CP'!$AZ$6/DG20),0)),0) -> 0 | DL20: T5 | DM20: =IF(DD$11="SI",CX$14,"") | DN20: =IF(DM20="","",DM20*$R$15) | DO20: =1/(DP20+0.01) -> 100 | DP20: =IFERROR(ROUNDDOWN(('Diseño estructura &CP'!$AZ$8/DN20),0),0) -> 0 | DR20: =+IF(DS20=0,"",DR19+1) | DS20: =+DU20/$H$9 -> 0 | DT20: =ROUNDDOWN(DU20/$C$13,0) -> 0 | DV20: =IF(DT20=0,0,DT20+1) -> 0 | DW20: =IF(DX20="","",1/(DX20+0.01)) | DX20: =IF(DU20>0,ROUNDDOWN(('Diseño estructura &CP'!$AZ$5/DU20),0),"") | DZ20: Lado 5 | EB20: metros | ED20: =IFERROR(IF(EA20="",0,ROUNDDOWN(('Diseño estructura &CP'!$AZ$6/EA20),0)),0) -> 0 | EF20: T5 | EG20: =IF(DX$11="SI",DR$14,"") | EH20: =IF(EG20="","",EG20*$R$15) | EI20: =1/(EJ20+0.01) -> 100 | EJ20: =IFERROR(ROUNDDOWN(('Diseño estructura &CP'!$AZ$8/EH20),0),0) -> 0 | EL20: =+IF(EM20=0,"",EL19+1) | EM20: =+EO20/$H$9 -> 0 | EN20: =ROUNDDOWN(EO20/$C$13,0) -> 0 | EP20: =IF(EN20=0,0,EN20+1) -> 0 | EQ20: =IF(ER20="","",1/(ER20+0.01)) | ER20: =IF(EO20>0,ROUNDDOWN(('Diseño estructura &CP'!$AZ$5/EO20),0),"") | ET20: Lado 5 | EV20: metros | EX20: =IFERROR(IF(EU20="",0,ROUNDDOWN(('Diseño estructura &CP'!$AZ$6/EU20),0)),0) -> 0 | EZ20: T5 | FA20: =IF(ER$11="SI",EL$14,"") | FB20: =IF(FA20="","",FA20*$R$15) | FC20: =1/(FD20+0.01) -> 100 | FD20: =IFERROR(ROUNDDOWN(('Diseño estructura &CP'!$AZ$8/FB20),0),0) -> 0 | FF20: =+IF(FG20=0,"",FF19+1) | FG20: =+FI20/$H$9 -> 0 | FH20: =ROUNDDOWN(FI20/$C$13,0) -> 0 | FJ20: =IF(FH20=0,0,FH20+1) -> 0 | FK20: =IF(FL20="","",1/(FL20+0.01)) | FL20: =IF(FI20>0,ROUNDDOWN(('Diseño estructura &CP'!$AZ$5/FI20),0),"") | FN20: Lado 5 | FP20: metros | FR20: =IFERROR(IF(FO20="",0,ROUNDDOWN(('Diseño estructura &CP'!$AZ$6/FO20),0)),0) -> 0 | FT20: T5 | FU20: =IF(FL$11="SI",FF$14,"") | FV20: =IF(FU20="","",FU20*$R$15) | FW20: =1/(FX20+0.01) -> 100 | FX20: =IFERROR(ROUNDDOWN(('Diseño estructura &CP'!$AZ$8/FV20),0),0) -> 0 | FZ20: =+IF(GA20=0,"",FZ19+1) | GA20: =+GC20/$H$9 -> 0 | GB20: =ROUNDDOWN(GC20/$C$13,0) -> 0 | GD20: =IF(GB20=0,0,GB20+1) -> 0 | GE20: =IF(GF20="","",1/(GF20+0.01)) | GF20: =IF(GC20>0,ROUNDDOWN(('Diseño estructura &CP'!$AZ$5/GC20),0),"") | GH20: Lado 5 | GJ20: metros | GL20: =IFERROR(IF(GI20="",0,ROUNDDOWN(('Diseño estructura &CP'!$AZ$6/GI20),0)),0) -> 0 | GN20: T5 | GO20: =IF(GF$11="SI",FZ$14,"") | GP20: =IF(GO20="","",GO20*$R$15) | GQ20: =1/(GR20+0.01) -> 100 | GR20: =IFERROR(ROUNDDOWN(('Diseño estructura &CP'!$AZ$8/GP20),0),0) -> 0
B21: =+IF(C21=0,"",B20+1) -> 6 | C21: =+E21/$H$9 -> 15 | D21: =ROUNDDOWN(E21/$C$13,0) -> 2 | E21: 30 | F21: =IF(D21=0,0,D21+1) -> 3 | G21: =IF(H21="","",1/(H21+0.01)) -> 0.03029385 | H21: =IF(E21>0,ROUNDDOWN(('Diseño estructura &CP'!$AZ$5/E21),0),"") -> 33 | J21: Lado 6 | L21: metros | N21: =IFERROR(IF(K21="",0,ROUNDDOWN(('Diseño estructura &CP'!$AZ$6/K21),0)),0) -> 0 | P21: T6 | Q21: =IF(H$11="SI",B$14,"") -> 106 | R21: =IF(Q21="","",Q21*$R$15) -> 424 | S21: =1/(T21+0.01) -> 0.99009901 | T21: =IFERROR(ROUNDDOWN(('Diseño estructura &CP'!$AZ$8/R21),0),0) -> 1 | V21: =+IF(W21=0,"",V20+1) -> 6 | W21: =+Y21/$H$9 -> 79.5 | X21: =ROUNDDOWN(Y21/$C$13,0) -> 13 | Y21: 159 | Z21: =IF(X21=0,0,X21+1) -> 14 | AA21: =IF(AB21="","",1/(AB21+0.01)) -> 0.16638935 | AB21: =IF(Y21>0,ROUNDDOWN(('Diseño estructura &CP'!$AZ$5/Y21),0),"") -> 6 | AD21: Lado 6 | AF21: metros | AH21: =IFERROR(IF(AE21="",0,ROUNDDOWN(('Diseño estructura &CP'!$AZ$6/AE21),0)),0) -> 0 | AJ21: T6 | AK21: =IF(AB$11="SI",V$14,"") -> 55 | AL21: =IF(AK21="","",AK21*$R$15) -> 220 | AM21: =1/(AN21+0.01) -> 0.49751244 | AN21: =IFERROR(ROUNDDOWN(('Diseño estructura &CP'!$AZ$8/AL21),0),0) -> 2 | AP21: =+IF(AQ21=0,"",AP20+1) -> 6 | AQ21: =+AS21/$H$9 -> 81.75 | AR21: =ROUNDDOWN(AS21/$C$13,0) -> 13 | AS21: 163.5 | AT21: =IF(AR21=0,0,AR21+1) -> 14 | AU21: =IF(AV21="","",1/(AV21+0.01)) -> 0.16638935 | AV21: =IF(AS21>0,ROUNDDOWN(('Diseño estructura &CP'!$AZ$5/AS21),0),"") -> 6 | AX21: Lado 6 | AZ21: metros | BB21: =IFERROR(IF(AY21="",0,ROUNDDOWN(('Diseño estructura &CP'!$AZ$6/AY21),0)),0) -> 0 | BD21: T6 | BE21: =IF(AV$11="SI",AP$14,"") -> 76 | BF21: =IF(BE21="","",BE21*$R$15) -> 304 | BG21: =1/(BH21+0.01) -> 0.99009901 | BH21: =IFERROR(ROUNDDOWN(('Diseño estructura &CP'!$AZ$8/BF21),0),0) -> 1 | BJ21: =+IF(BK21=0,"",BJ20+1) -> 6 | BK21: =+BM21/$H$9 -> 98.5 | BL21: =ROUNDDOWN(BM21/$BK$13,0) -> 17 | BM21: 197 | BN21: =IF(BL21=0,0,BL21+1) -> 18 | BO21: =IF(BP21="","",1/(BP21+0.01)) -> 0.1996008 | BP21: =IF(BM21>0,ROUNDDOWN(('Diseño estructura &CP'!$AZ$5/BM21),0),"") -> 5 | BR21: Lado 6 | BT21: metros | BV21: =IFERROR(IF(BS21="",0,ROUNDDOWN(('Diseño estructura &CP'!$AZ$6/BS21),0)),0) -> 0 | BX21: T6 | BY21: =IF(BP$11="SI",BJ$14,"") -> 30 | BZ21: =IF(BY21="","",BY21*$R$15) -> 120 | CA21: =1/(CB21+0.01) -> 0.24937656 | CB21: =IFERROR(ROUNDDOWN(('Diseño estructura &CP'!$AZ$8/BZ21),0),0) -> 4 | CD21: =+IF(CE21=0,"",CD20+1) | CE21: =+CG21/$H$9 -> 0 | CF21: =ROUNDDOWN(CG21/$C$13,0) -> 0 | CH21: =IF(CF21=0,0,CF21+1) -> 0 | CI21: =IF(CJ21="","",1/(CJ21+0.01)) | CJ21: =IF(CG21>0,ROUNDDOWN(('Diseño estructura &CP'!$AZ$5/CG21),0),"") | CL21: Lado 6 | CN21: metros | CP21: =IFERROR(IF(CM21="",0,ROUNDDOWN(('Diseño estructura &CP'!$AZ$6/CM21),0)),0) -> 0 | CR21: T6 | CS21: =IF(CJ$11="SI",CD$14,"") | CT21: =IF(CS21="","",CS21*$R$15) | CU21: =1/(CV21+0.01) -> 100 | CV21: =IFERROR(ROUNDDOWN(('Diseño estructura &CP'!$AZ$8/CT21),0),0) -> 0 | CX21: =+IF(CY21=0,"",CX20+1) | CY21: =+DA21/$H$9 -> 0 | CZ21: =ROUNDDOWN(DA21/$C$13,0) -> 0 | DB21: =IF(CZ21=0,0,CZ21+1) -> 0 | DC21: =IF(DD21="","",1/(DD21+0.01)) | DD21: =IF(DA21>0,ROUNDDOWN(('Diseño estructura &CP'!$AZ$5/DA21),0),"") | DF21: Lado 6 | DH21: metros | DJ21: =IFERROR(IF(DG21="",0,ROUNDDOWN(('Diseño estructura &CP'!$AZ$6/DG21),0)),0) -> 0 | DL21: T6 | DM21: =IF(DD$11="SI",CX$14,"") | DN21: =IF(DM21="","",DM21*$R$15) | DO21: =1/(DP21+0.01) -> 100 | DP21: =IFERROR(ROUNDDOWN(('Diseño estructura &CP'!$AZ$8/DN21),0),0) -> 0 | DR21: =+IF(DS21=0,"",DR20+1) | DS21: =+DU21/$H$9 -> 0 | DT21: =ROUNDDOWN(DU21/$C$13,0) -> 0 | DV21: =IF(DT21=0,0,DT21+1) -> 0 | DW21: =IF(DX21="","",1/(DX21+0.01)) | DX21: =IF(DU21>0,ROUNDDOWN(('Diseño estructura &CP'!$AZ$5/DU21),0),"") | DZ21: Lado 6 | EB21: metros | ED21: =IFERROR(IF(EA21="",0,ROUNDDOWN(('Diseño estructura &CP'!$AZ$6/EA21),0)),0) -> 0 | EF21: T6 | EG21: =IF(DX$11="SI",DR$14,"") | EH21: =IF(EG21="","",EG21*$R$15) | EI21: =1/(EJ21+0.01) -> 100 | EJ21: =IFERROR(ROUNDDOWN(('Diseño estructura &CP'!$AZ$8/EH21),0),0) -> 0 | EL21: =+IF(EM21=0,"",EL20+1) | EM21: =+EO21/$H$9 -> 0 | EN21: =ROUNDDOWN(EO21/$C$13,0) -> 0 | EP21: =IF(EN21=0,0,EN21+1) -> 0 | EQ21: =IF(ER21="","",1/(ER21+0.01)) | ER21: =IF(EO21>0,ROUNDDOWN(('Diseño estructura &CP'!$AZ$5/EO21),0),"") | ET21: Lado 6 | EV21: metros | EX21: =IFERROR(IF(EU21="",0,ROUNDDOWN(('Diseño estructura &CP'!$AZ$6/EU21),0)),0) -> 0 | EZ21: T6 | FA21: =IF(ER$11="SI",EL$14,"") | FB21: =IF(FA21="","",FA21*$R$15) | FC21: =1/(FD21+0.01) -> 100 | FD21: =IFERROR(ROUNDDOWN(('Diseño estructura &CP'!$AZ$8/FB21),0),0) -> 0 | FF21: =+IF(FG21=0,"",FF20+1) | FG21: =+FI21/$H$9 -> 0 | FH21: =ROUNDDOWN(FI21/$C$13,0) -> 0 | FJ21: =IF(FH21=0,0,FH21+1) -> 0 | FK21: =IF(FL21="","",1/(FL21+0.01)) | FL21: =IF(FI21>0,ROUNDDOWN(('Diseño estructura &CP'!$AZ$5/FI21),0),"") | FN21: Lado 6 | FP21: metros | FR21: =IFERROR(IF(FO21="",0,ROUNDDOWN(('Diseño estructura &CP'!$AZ$6/FO21),0)),0) -> 0 | FT21: T6 | FU21: =IF(FL$11="SI",FF$14,"") | FV21: =IF(FU21="","",FU21*$R$15) | FW21: =1/(FX21+0.01) -> 100 | FX21: =IFERROR(ROUNDDOWN(('Diseño estructura &CP'!$AZ$8/FV21),0),0) -> 0 | FZ21: =+IF(GA21=0,"",FZ20+1) | GA21: =+GC21/$H$9 -> 0 | GB21: =ROUNDDOWN(GC21/$C$13,0) -> 0 | GD21: =IF(GB21=0,0,GB21+1) -> 0 | GE21: =IF(GF21="","",1/(GF21+0.01)) | GF21: =IF(GC21>0,ROUNDDOWN(('Diseño estructura &CP'!$AZ$5/GC21),0),"") | GH21: Lado 6 | GJ21: metros | GL21: =IFERROR(IF(GI21="",0,ROUNDDOWN(('Diseño estructura &CP'!$AZ$6/GI21),0)),0) -> 0 | GN21: T6 | GO21: =IF(GF$11="SI",FZ$14,"") | GP21: =IF(GO21="","",GO21*$R$15) | GQ21: =1/(GR21+0.01) -> 100 | GR21: =IFERROR(ROUNDDOWN(('Diseño estructura &CP'!$AZ$8/GP21),0),0) -> 0
B22: =+IF(C22=0,"",B21+1) -> 7 | C22: =+E22/$H$9 -> 17.75 | D22: =ROUNDDOWN(E22/$C$13,0) -> 2 | E22: 35.5 | F22: =IF(D22=0,0,D22+1) -> 3 | G22: =IF(H22="","",1/(H22+0.01)) -> 0.035701535 | H22: =IF(E22>0,ROUNDDOWN(('Diseño estructura &CP'!$AZ$5/E22),0),"") -> 28 | J22: Lado 7 | L22: metros | N22: =IFERROR(IF(K22="",0,ROUNDDOWN(('Diseño estructura &CP'!$AZ$6/K22),0)),0) -> 0 | P22: T7 | Q22: =IF(H$11="SI",B$14,"") -> 106 | R22: =IF(Q22="","",Q22*$R$15) -> 424 | S22: =1/(T22+0.01) -> 0.99009901 | T22: =IFERROR(ROUNDDOWN(('Diseño estructura &CP'!$AZ$8/R22),0),0) -> 1 | V22: =+IF(W22=0,"",V21+1) -> 7 | W22: =+Y22/$H$9 -> 81 | X22: =ROUNDDOWN(Y22/$C$13,0) -> 13 | Y22: 162 | Z22: =IF(X22=0,0,X22+1) -> 14 | AA22: =IF(AB22="","",1/(AB22+0.01)) -> 0.16638935 | AB22: =IF(Y22>0,ROUNDDOWN(('Diseño estructura &CP'!$AZ$5/Y22),0),"") -> 6 | AD22: Lado 7 | AF22: metros | AH22: =IFERROR(IF(AE22="",0,ROUNDDOWN(('Diseño estructura &CP'!$AZ$6/AE22),0)),0) -> 0 | AJ22: T7 | AK22: =IF(AB$11="SI",V$14,"") -> 55 | AL22: =IF(AK22="","",AK22*$R$15) -> 220 | AM22: =1/(AN22+0.01) -> 0.49751244 | AN22: =IFERROR(ROUNDDOWN(('Diseño estructura &CP'!$AZ$8/AL22),0),0) -> 2 | AP22: =+IF(AQ22=0,"",AP21+1) -> 7 | AQ22: =+AS22/$H$9 -> 81 | AR22: =ROUNDDOWN(AS22/$C$13,0) -> 13 | AS22: 162 | AT22: =IF(AR22=0,0,AR22+1) -> 14 | AU22: =IF(AV22="","",1/(AV22+0.01)) -> 0.16638935 | AV22: =IF(AS22>0,ROUNDDOWN(('Diseño estructura &CP'!$AZ$5/AS22),0),"") -> 6 | AX22: Lado 7 | AZ22: metros | BB22: =IFERROR(IF(AY22="",0,ROUNDDOWN(('Diseño estructura &CP'!$AZ$6/AY22),0)),0) -> 0 | BD22: T7 | BE22: =IF(AV$11="SI",AP$14,"") -> 76 | BF22: =IF(BE22="","",BE22*$R$15) -> 304 | BG22: =1/(BH22+0.01) -> 0.99009901 | BH22: =IFERROR(ROUNDDOWN(('Diseño estructura &CP'!$AZ$8/BF22),0),0) -> 1 | BJ22: =+IF(BK22=0,"",BJ21+1) -> 7 | BK22: =+BM22/$H$9 -> 98.5 | BL22: =ROUNDDOWN(BM22/$BK$13,0) -> 17 | BM22: 197 | BN22: =IF(BL22=0,0,BL22+1) -> 18 | BO22: =IF(BP22="","",1/(BP22+0.01)) -> 0.1996008 | BP22: =IF(BM22>0,ROUNDDOWN(('Diseño estructura &CP'!$AZ$5/BM22),0),"") -> 5 | BR22: Lado 7 | BT22: metros | BV22: =IFERROR(IF(BS22="",0,ROUNDDOWN(('Diseño estructura &CP'!$AZ$6/BS22),0)),0) -> 0 | BX22: T7 | BY22: =IF(BP$11="SI",BJ$14,"") -> 30 | BZ22: =IF(BY22="","",BY22*$R$15) -> 120 | CA22: =1/(CB22+0.01) -> 0.24937656 | CB22: =IFERROR(ROUNDDOWN(('Diseño estructura &CP'!$AZ$8/BZ22),0),0) -> 4 | CD22: =+IF(CE22=0,"",CD21+1) | CE22: =+CG22/$H$9 -> 0 | CF22: =ROUNDDOWN(CG22/$C$13,0) -> 0 | CH22: =IF(CF22=0,0,CF22+1) -> 0 | CI22: =IF(CJ22="","",1/(CJ22+0.01)) | CJ22: =IF(CG22>0,ROUNDDOWN(('Diseño estructura &CP'!$AZ$5/CG22),0),"") | CL22: Lado 7 | CN22: metros | CP22: =IFERROR(IF(CM22="",0,ROUNDDOWN(('Diseño estructura &CP'!$AZ$6/CM22),0)),0) -> 0 | CR22: T7 | CS22: =IF(CJ$11="SI",CD$14,"") | CT22: =IF(CS22="","",CS22*$R$15) | CU22: =1/(CV22+0.01) -> 100 | CV22: =IFERROR(ROUNDDOWN(('Diseño estructura &CP'!$AZ$8/CT22),0),0) -> 0 | CX22: =+IF(CY22=0,"",CX21+1) | CY22: =+DA22/$H$9 -> 0 | CZ22: =ROUNDDOWN(DA22/$C$13,0) -> 0 | DB22: =IF(CZ22=0,0,CZ22+1) -> 0 | DC22: =IF(DD22="","",1/(DD22+0.01)) | DD22: =IF(DA22>0,ROUNDDOWN(('Diseño estructura &CP'!$AZ$5/DA22),0),"") | DF22: Lado 7 | DH22: metros | DJ22: =IFERROR(IF(DG22="",0,ROUNDDOWN(('Diseño estructura &CP'!$AZ$6/DG22),0)),0) -> 0 | DL22: T7 | DM22: =IF(DD$11="SI",CX$14,"") | DN22: =IF(DM22="","",DM22*$R$15) | DO22: =1/(DP22+0.01) -> 100 | DP22: =IFERROR(ROUNDDOWN(('Diseño estructura &CP'!$AZ$8/DN22),0),0) -> 0 | DR22: =+IF(DS22=0,"",DR21+1) | DS22: =+DU22/$H$9 -> 0 | DT22: =ROUNDDOWN(DU22/$C$13,0) -> 0 | DV22: =IF(DT22=0,0,DT22+1) -> 0 | DW22: =IF(DX22="","",1/(DX22+0.01)) | DX22: =IF(DU22>0,ROUNDDOWN(('Diseño estructura &CP'!$AZ$5/DU22),0),"") | DZ22: Lado 7 | EB22: metros | ED22: =IFERROR(IF(EA22="",0,ROUNDDOWN(('Diseño estructura &CP'!$AZ$6/EA22),0)),0) -> 0 | EF22: T7 | EG22: =IF(DX$11="SI",DR$14,"") | EH22: =IF(EG22="","",EG22*$R$15) | EI22: =1/(EJ22+0.01) -> 100 | EJ22: =IFERROR(ROUNDDOWN(('Diseño estructura &CP'!$AZ$8/EH22),0),0) -> 0 | EL22: =+IF(EM22=0,"",EL21+1) | EM22: =+EO22/$H$9 -> 0 | EN22: =ROUNDDOWN(EO22/$C$13,0) -> 0 | EP22: =IF(EN22=0,0,EN22+1) -> 0 | EQ22: =IF(ER22="","",1/(ER22+0.01)) | ER22: =IF(EO22>0,ROUNDDOWN(('Diseño estructura &CP'!$AZ$5/EO22),0),"") | ET22: Lado 7 | EV22: metros | EX22: =IFERROR(IF(EU22="",0,ROUNDDOWN(('Diseño estructura &CP'!$AZ$6/EU22),0)),0) -> 0 | EZ22: T7 | FA22: =IF(ER$11="SI",EL$14,"") | FB22: =IF(FA22="","",FA22*$R$15) | FC22: =1/(FD22+0.01) -> 100 | FD22: =IFERROR(ROUNDDOWN(('Diseño estructura &CP'!$AZ$8/FB22),0),0) -> 0 | FF22: =+IF(FG22=0,"",FF21+1) | FG22: =+FI22/$H$9 -> 0 | FH22: =ROUNDDOWN(FI22/$C$13,0) -> 0 | FJ22: =IF(FH22=0,0,FH22+1) -> 0 | FK22: =IF(FL22="","",1/(FL22+0.01)) | FL22: =IF(FI22>0,ROUNDDOWN(('Diseño estructura &CP'!$AZ$5/FI22),0),"") | FN22: Lado 7 | FP22: metros | FR22: =IFERROR(IF(FO22="",0,ROUNDDOWN(('Diseño estructura &CP'!$AZ$6/FO22),0)),0) -> 0 | FT22: T7 | FU22: =IF(FL$11="SI",FF$14,"") | FV22: =IF(FU22="","",FU22*$R$15) | FW22: =1/(FX22+0.01) -> 100 | FX22: =IFERROR(ROUNDDOWN(('Diseño estructura &CP'!$AZ$8/FV22),0),0) -> 0 | FZ22: =+IF(GA22=0,"",FZ21+1) | GA22: =+GC22/$H$9 -> 0 | GB22: =ROUNDDOWN(GC22/$C$13,0) -> 0 | GD22: =IF(GB22=0,0,GB22+1) -> 0 | GE22: =IF(GF22="","",1/(GF22+0.01)) | GF22: =IF(GC22>0,ROUNDDOWN(('Diseño estructura &CP'!$AZ$5/GC22),0),"") | GH22: Lado 7 | GJ22: metros | GL22: =IFERROR(IF(GI22="",0,ROUNDDOWN(('Diseño estructura &CP'!$AZ$6/GI22),0)),0) -> 0 | GN22: T7 | GO22: =IF(GF$11="SI",FZ$14,"") | GP22: =IF(GO22="","",GO22*$R$15) | GQ22: =1/(GR22+0.01) -> 100 | GR22: =IFERROR(ROUNDDOWN(('Diseño estructura &CP'!$AZ$8/GP22),0),0) -> 0
B23: =+IF(C23=0,"",B22+1) -> 8 | C23: =+E23/$H$9 -> 20 | D23: =ROUNDDOWN(E23/$C$13,0) -> 3 | E23: 40 | F23: =IF(D23=0,0,D23+1) -> 4 | G23: =IF(H23="","",1/(H23+0.01)) -> 0.039984006 | H23: =IF(E23>0,ROUNDDOWN(('Diseño estructura &CP'!$AZ$5/E23),0),"") -> 25 | J23: Lado 8 | L23: metros | N23: =IFERROR(IF(K23="",0,ROUNDDOWN(('Diseño estructura &CP'!$AZ$6/K23),0)),0) -> 0 | P23: T8 | Q23: =IF(H$11="SI",B$14,"") -> 106 | R23: =IF(Q23="","",Q23*$R$15) -> 424 | S23: =1/(T23+0.01) -> 0.99009901 | T23: =IFERROR(ROUNDDOWN(('Diseño estructura &CP'!$AZ$8/R23),0),0) -> 1 | V23: =+IF(W23=0,"",V22+1) -> 8 | W23: =+Y23/$H$9 -> 82.5 | X23: =ROUNDDOWN(Y23/$C$13,0) -> 13 | Y23: 165 | Z23: =IF(X23=0,0,X23+1) -> 14 | AA23: =IF(AB23="","",1/(AB23+0.01)) -> 0.16638935 | AB23: =IF(Y23>0,ROUNDDOWN(('Diseño estructura &CP'!$AZ$5/Y23),0),"") -> 6 | AD23: Lado 8 | AF23: metros | AH23: =IFERROR(IF(AE23="",0,ROUNDDOWN(('Diseño estructura &CP'!$AZ$6/AE23),0)),0) -> 0 | AJ23: T8 | AK23: =IF(AB$11="SI",V$14,"") -> 55 | AL23: =IF(AK23="","",AK23*$R$15) -> 220 | AM23: =1/(AN23+0.01) -> 0.49751244 | AN23: =IFERROR(ROUNDDOWN(('Diseño estructura &CP'!$AZ$8/AL23),0),0) -> 2 | AP23: =+IF(AQ23=0,"",AP22+1) -> 8 | AQ23: =+AS23/$H$9 -> 81.5 | AR23: =ROUNDDOWN(AS23/$C$13,0) -> 13 | AS23: 163 | AT23: =IF(AR23=0,0,AR23+1) -> 14 | AU23: =IF(AV23="","",1/(AV23+0.01)) -> 0.16638935 | AV23: =IF(AS23>0,ROUNDDOWN(('Diseño estructura &CP'!$AZ$5/AS23),0),"") -> 6 | AX23: Lado 8 | AZ23: metros | BB23: =IFERROR(IF(AY23="",0,ROUNDDOWN(('Diseño estructura &CP'!$AZ$6/AY23),0)),0) -> 0 | BD23: T8 | BE23: =IF(AV$11="SI",AP$14,"") -> 76 | BF23: =IF(BE23="","",BE23*$R$15) -> 304 | BG23: =1/(BH23+0.01) -> 0.99009901 | BH23: =IFERROR(ROUNDDOWN(('Diseño estructura &CP'!$AZ$8/BF23),0),0) -> 1 | BJ23: =+IF(BK23=0,"",BJ22+1) -> 8 | BK23: =+BM23/$H$9 -> 97.75 | BL23: =ROUNDDOWN(BM23/$BK$13,0) -> 17 | BM23: 195.5 | BN23: =IF(BL23=0,0,BL23+1) -> 18 | BO23: =IF(BP23="","",1/(BP23+0.01)) -> 0.1996008 | BP23: =IF(BM23>0,ROUNDDOWN(('Diseño estructura &CP'!$AZ$5/BM23),0),"") -> 5 | BR23: Lado 8 | BT23: metros | BV23: =IFERROR(IF(BS23="",0,ROUNDDOWN(('Diseño estructura &CP'!$AZ$6/BS23),0)),0) -> 0 | BX23: T8 | BY23: =IF(BP$11="SI",BJ$14,"") -> 30 | BZ23: =IF(BY23="","",BY23*$R$15) -> 120 | CA23: =1/(CB23+0.01) -> 0.24937656 | CB23: =IFERROR(ROUNDDOWN(('Diseño estructura &CP'!$AZ$8/BZ23),0),0) -> 4 | CD23: =+IF(CE23=0,"",CD22+1) | CE23: =+CG23/$H$9 -> 0 | CF23: =ROUNDDOWN(CG23/$C$13,0) -> 0 | CH23: =IF(CF23=0,0,CF23+1) -> 0 | CI23: =IF(CJ23="","",1/(CJ23+0.01)) | CJ23: =IF(CG23>0,ROUNDDOWN(('Diseño estructura &CP'!$AZ$5/CG23),0),"") | CL23: Lado 8 | CN23: metros | CP23: =IFERROR(IF(CM23="",0,ROUNDDOWN(('Diseño estructura &CP'!$AZ$6/CM23),0)),0) -> 0 | CR23: T8 | CS23: =IF(CJ$11="SI",CD$14,"") | CT23: =IF(CS23="","",CS23*$R$15) | CU23: =1/(CV23+0.01) -> 100 | CV23: =IFERROR(ROUNDDOWN(('Diseño estructura &CP'!$AZ$8/CT23),0),0) -> 0 | CX23: =+IF(CY23=0,"",CX22+1) | CY23: =+DA23/$H$9 -> 0 | CZ23: =ROUNDDOWN(DA23/$C$13,0) -> 0 | DB23: =IF(CZ23=0,0,CZ23+1) -> 0 | DC23: =IF(DD23="","",1/(DD23+0.01)) | DD23: =IF(DA23>0,ROUNDDOWN(('Diseño estructura &CP'!$AZ$5/DA23),0),"") | DF23: Lado 8 | DH23: metros | DJ23: =IFERROR(IF(DG23="",0,ROUNDDOWN(('Diseño estructura &CP'!$AZ$6/DG23),0)),0) -> 0 | DL23: T8 | DM23: =IF(DD$11="SI",CX$14,"") | DN23: =IF(DM23="","",DM23*$R$15) | DO23: =1/(DP23+0.01) -> 100 | DP23: =IFERROR(ROUNDDOWN(('Diseño estructura &CP'!$AZ$8/DN23),0),0) -> 0 | DR23: =+IF(DS23=0,"",DR22+1) | DS23: =+DU23/$H$9 -> 0 | DT23: =ROUNDDOWN(DU23/$C$13,0) -> 0 | DV23: =IF(DT23=0,0,DT23+1) -> 0 | DW23: =IF(DX23="","",1/(DX23+0.01)) | DX23: =IF(DU23>0,ROUNDDOWN(('Diseño estructura &CP'!$AZ$5/DU23),0),"") | DZ23: Lado 8 | EB23: metros | ED23: =IFERROR(IF(EA23="",0,ROUNDDOWN(('Diseño estructura &CP'!$AZ$6/EA23),0)),0) -> 0 | EF23: T8 | EG23: =IF(DX$11="SI",DR$14,"") | EH23: =IF(EG23="","",EG23*$R$15) | EI23: =1/(EJ23+0.01) -> 100 | EJ23: =IFERROR(ROUNDDOWN(('Diseño estructura &CP'!$AZ$8/EH23),0),0) -> 0 | EL23: =+IF(EM23=0,"",EL22+1) | EM23: =+EO23/$H$9 -> 0 | EN23: =ROUNDDOWN(EO23/$C$13,0) -> 0 | EP23: =IF(EN23=0,0,EN23+1) -> 0 | EQ23: =IF(ER23="","",1/(ER23+0.01)) | ER23: =IF(EO23>0,ROUNDDOWN(('Diseño estructura &CP'!$AZ$5/EO23),0),"") | ET23: Lado 8 | EV23: metros | EX23: =IFERROR(IF(EU23="",0,ROUNDDOWN(('Diseño estructura &CP'!$AZ$6/EU23),0)),0) -> 0 | EZ23: T8 | FA23: =IF(ER$11="SI",EL$14,"") | FB23: =IF(FA23="","",FA23*$R$15) | FC23: =1/(FD23+0.01) -> 100 | FD23: =IFERROR(ROUNDDOWN(('Diseño estructura &CP'!$AZ$8/FB23),0),0) -> 0 | FF23: =+IF(FG23=0,"",FF22+1) | FG23: =+FI23/$H$9 -> 0 | FH23: =ROUNDDOWN(FI23/$C$13,0) -> 0 | FJ23: =IF(FH23=0,0,FH23+1) -> 0 | FK23: =IF(FL23="","",1/(FL23+0.01)) | FL23: =IF(FI23>0,ROUNDDOWN(('Diseño estructura &CP'!$AZ$5/FI23),0),"") | FN23: Lado 8 | FP23: metros | FR23: =IFERROR(IF(FO23="",0,ROUNDDOWN(('Diseño estructura &CP'!$AZ$6/FO23),0)),0) -> 0 | FT23: T8 | FU23: =IF(FL$11="SI",FF$14,"") | FV23: =IF(FU23="","",FU23*$R$15) | FW23: =1/(FX23+0.01) -> 100 | FX23: =IFERROR(ROUNDDOWN(('Diseño estructura &CP'!$AZ$8/FV23),0),0) -> 0 | FZ23: =+IF(GA23=0,"",FZ22+1) | GA23: =+GC23/$H$9 -> 0 | GB23: =ROUNDDOWN(GC23/$C$13,0) -> 0 | GD23: =IF(GB23=0,0,GB23+1) -> 0 | GE23: =IF(GF23="","",1/(GF23+0.01)) | GF23: =IF(GC23>0,ROUNDDOWN(('Diseño estructura &CP'!$AZ$5/GC23),0),"") | GH23: Lado 8 | GJ23: metros | GL23: =IFERROR(IF(GI23="",0,ROUNDDOWN(('Diseño estructura &CP'!$AZ$6/GI23),0)),0) -> 0 | GN23: T8 | GO23: =IF(GF$11="SI",FZ$14,"") | GP23: =IF(GO23="","",GO23*$R$15) | GQ23: =1/(GR23+0.01) -> 100 | GR23: =IFERROR(ROUNDDOWN(('Diseño estructura &CP'!$AZ$8/GP23),0),0) -> 0
B24: =+IF(C24=0,"",B23+1) -> 9 | C24: =+E24/$H$9 -> 23 | D24: =ROUNDDOWN(E24/$C$13,0) -> 3 | E24: 46 | F24: =IF(D24=0,0,D24+1) -> 4 | G24: =IF(H24="","",1/(H24+0.01)) -> 0.047596383 | H24: =IF(E24>0,ROUNDDOWN(('Diseño estructura &CP'!$AZ$5/E24),0),"") -> 21 | J24: Lado 9 | L24: metros | N24: =IFERROR(IF(K24="",0,ROUNDDOWN(('Diseño estructura &CP'!$AZ$6/K24),0)),0) -> 0 | P24: T9 | Q24: =IF(H$11="SI",B$14,"") -> 106 | R24: =IF(Q24="","",Q24*$R$15) -> 424 | S24: =1/(T24+0.01) -> 0.99009901 | T24: =IFERROR(ROUNDDOWN(('Diseño estructura &CP'!$AZ$8/R24),0),0) -> 1 | V24: =+IF(W24=0,"",V23+1) -> 9 | W24: =+Y24/$H$9 -> 83.75 | X24: =ROUNDDOWN(Y24/$C$13,0) -> 13 | Y24: 167.5 | Z24: =IF(X24=0,0,X24+1) -> 14 | AA24: =IF(AB24="","",1/(AB24+0.01)) -> 0.1996008 | AB24: =IF(Y24>0,ROUNDDOWN(('Diseño estructura &CP'!$AZ$5/Y24),0),"") -> 5 | AD24: Lado 9 | AF24: metros | AH24: =IFERROR(IF(AE24="",0,ROUNDDOWN(('Diseño estructura &CP'!$AZ$6/AE24),0)),0) -> 0 | AJ24: T9 | AK24: =IF(AB$11="SI",V$14,"") -> 55 | AL24: =IF(AK24="","",AK24*$R$15) -> 220 | AM24: =1/(AN24+0.01) -> 0.49751244 | AN24: =IFERROR(ROUNDDOWN(('Diseño estructura &CP'!$AZ$8/AL24),0),0) -> 2 | AP24: =+IF(AQ24=0,"",AP23+1) -> 9 | AQ24: =+AS24/$H$9 -> 81.5 | AR24: =ROUNDDOWN(AS24/$C$13,0) -> 13 | AS24: 163 | AT24: =IF(AR24=0,0,AR24+1) -> 14 | AU24: =IF(AV24="","",1/(AV24+0.01)) -> 0.16638935 | AV24: =IF(AS24>0,ROUNDDOWN(('Diseño estructura &CP'!$AZ$5/AS24),0),"") -> 6 | AX24: Lado 9 | AZ24: metros | BB24: =IFERROR(IF(AY24="",0,ROUNDDOWN(('Diseño estructura &CP'!$AZ$6/AY24),0)),0) -> 0 | BD24: T9 | BE24: =IF(AV$11="SI",AP$14,"") -> 76 | BF24: =IF(BE24="","",BE24*$R$15) -> 304 | BG24: =1/(BH24+0.01) -> 0.99009901 | BH24: =IFERROR(ROUNDDOWN(('Diseño estructura &CP'!$AZ$8/BF24),0),0) -> 1 | BJ24: =+IF(BK24=0,"",BJ23+1) -> 9 | BK24: =+BM24/$H$9 -> 97 | BL24: =ROUNDDOWN(BM24/$BK$13,0) -> 17 | BM24: 194 | BN24: =IF(BL24=0,0,BL24+1) -> 18 | BO24: =IF(BP24="","",1/(BP24+0.01)) -> 0.1996008 | BP24: =IF(BM24>0,ROUNDDOWN(('Diseño estructura &CP'!$AZ$5/BM24),0),"") -> 5 | BR24: Lado 9 | BT24: metros | BV24: =IFERROR(IF(BS24="",0,ROUNDDOWN(('Diseño estructura &CP'!$AZ$6/BS24),0)),0) -> 0 | BX24: T9 | BY24: =IF(BP$11="SI",BJ$14,"") -> 30 | BZ24: =IF(BY24="","",BY24*$R$15) -> 120 | CA24: =1/(CB24+0.01) -> 0.24937656 | CB24: =IFERROR(ROUNDDOWN(('Diseño estructura &CP'!$AZ$8/BZ24),0),0) -> 4 | CD24: =+IF(CE24=0,"",CD23+1) | CE24: =+CG24/$H$9 -> 0 | CF24: =ROUNDDOWN(CG24/$C$13,0) -> 0 | CH24: =IF(CF24=0,0,CF24+1) -> 0 | CI24: =IF(CJ24="","",1/(CJ24+0.01)) | CJ24: =IF(CG24>0,ROUNDDOWN(('Diseño estructura &CP'!$AZ$5/CG24),0),"") | CL24: Lado 9 | CN24: metros | CP24: =IFERROR(IF(CM24="",0,ROUNDDOWN(('Diseño estructura &CP'!$AZ$6/CM24),0)),0) -> 0 | CR24: T9 | CS24: =IF(CJ$11="SI",CD$14,"") | CT24: =IF(CS24="","",CS24*$R$15) | CU24: =1/(CV24+0.01) -> 100 | CV24: =IFERROR(ROUNDDOWN(('Diseño estructura &CP'!$AZ$8/CT24),0),0) -> 0 | CX24: =+IF(CY24=0,"",CX23+1) | CY24: =+DA24/$H$9 -> 0 | CZ24: =ROUNDDOWN(DA24/$C$13,0) -> 0 | DB24: =IF(CZ24=0,0,CZ24+1) -> 0 | DC24: =IF(DD24="","",1/(DD24+0.01)) | DD24: =IF(DA24>0,ROUNDDOWN(('Diseño estructura &CP'!$AZ$5/DA24),0),"") | DF24: Lado 9 | DH24: metros | DJ24: =IFERROR(IF(DG24="",0,ROUNDDOWN(('Diseño estructura &CP'!$AZ$6/DG24),0)),0) -> 0 | DL24: T9 | DM24: =IF(DD$11="SI",CX$14,"") | DN24: =IF(DM24="","",DM24*$R$15) | DO24: =1/(DP24+0.01) -> 100 | DP24: =IFERROR(ROUNDDOWN(('Diseño estructura &CP'!$AZ$8/DN24),0),0) -> 0 | DR24: =+IF(DS24=0,"",DR23+1) | DS24: =+DU24/$H$9 -> 0 | DT24: =ROUNDDOWN(DU24/$C$13,0) -> 0 | DV24: =IF(DT24=0,0,DT24+1) -> 0 | DW24: =IF(DX24="","",1/(DX24+0.01)) | DX24: =IF(DU24>0,ROUNDDOWN(('Diseño estructura &CP'!$AZ$5/DU24),0),"") | DZ24: Lado 9 | EB24: metros | ED24: =IFERROR(IF(EA24="",0,ROUNDDOWN(('Diseño estructura &CP'!$AZ$6/EA24),0)),0) -> 0 | EF24: T9 | EG24: =IF(DX$11="SI",DR$14,"") | EH24: =IF(EG24="","",EG24*$R$15) | EI24: =1/(EJ24+0.01) -> 100 | EJ24: =IFERROR(ROUNDDOWN(('Diseño estructura &CP'!$AZ$8/EH24),0),0) -> 0 | EL24: =+IF(EM24=0,"",EL23+1) | EM24: =+EO24/$H$9 -> 0 | EN24: =ROUNDDOWN(EO24/$C$13,0) -> 0 | EP24: =IF(EN24=0,0,EN24+1) -> 0 | EQ24: =IF(ER24="","",1/(ER24+0.01)) | ER24: =IF(EO24>0,ROUNDDOWN(('Diseño estructura &CP'!$AZ$5/EO24),0),"") | ET24: Lado 9 | EV24: metros | EX24: =IFERROR(IF(EU24="",0,ROUNDDOWN(('Diseño estructura &CP'!$AZ$6/EU24),0)),0) -> 0 | EZ24: T9 | FA24: =IF(ER$11="SI",EL$14,"") | FB24: =IF(FA24="","",FA24*$R$15) | FC24: =1/(FD24+0.01) -> 100 | FD24: =IFERROR(ROUNDDOWN(('Diseño estructura &CP'!$AZ$8/FB24),0),0) -> 0 | FF24: =+IF(FG24=0,"",FF23+1) | FG24: =+FI24/$H$9 -> 0 | FH24: =ROUNDDOWN(FI24/$C$13,0) -> 0 | FJ24: =IF(FH24=0,0,FH24+1) -> 0 | FK24: =IF(FL24="","",1/(FL24+0.01)) | FL24: =IF(FI24>0,ROUNDDOWN(('Diseño estructura &CP'!$AZ$5/FI24),0),"") | FN24: Lado 9 | FP24: metros | FR24: =IFERROR(IF(FO24="",0,ROUNDDOWN(('Diseño estructura &CP'!$AZ$6/FO24),0)),0) -> 0 | FT24: T9 | FU24: =IF(FL$11="SI",FF$14,"") | FV24: =IF(FU24="","",FU24*$R$15) | FW24: =1/(FX24+0.01) -> 100 | FX24: =IFERROR(ROUNDDOWN(('Diseño estructura &CP'!$AZ$8/FV24),0),0) -> 0 | FZ24: =+IF(GA24=0,"",FZ23+1) | GA24: =+GC24/$H$9 -> 0 | GB24: =ROUNDDOWN(GC24/$C$13,0) -> 0 | GD24: =IF(GB24=0,0,GB24+1) -> 0 | GE24: =IF(GF24="","",1/(GF24+0.01)) | GF24: =IF(GC24>0,ROUNDDOWN(('Diseño estructura &CP'!$AZ$5/GC24),0),"") | GH24: Lado 9 | GJ24: metros | GL24: =IFERROR(IF(GI24="",0,ROUNDDOWN(('Diseño estructura &CP'!$AZ$6/GI24),0)),0) -> 0 | GN24: T9 | GO24: =IF(GF$11="SI",FZ$14,"") | GP24: =IF(GO24="","",GO24*$R$15) | GQ24: =1/(GR24+0.01) -> 100 | GR24: =IFERROR(ROUNDDOWN(('Diseño estructura &CP'!$AZ$8/GP24),0),0) -> 0
B25: =+IF(C25=0,"",B24+1) -> 10 | C25: =+E25/$H$9 -> 23.75 | D25: =ROUNDDOWN(E25/$C$13,0) -> 3 | E25: 47.5 | F25: =IF(D25=0,0,D25+1) -> 4 | G25: =IF(H25="","",1/(H25+0.01)) -> 0.047596383 | H25: =IF(E25>0,ROUNDDOWN(('Diseño estructura &CP'!$AZ$5/E25),0),"") -> 21 | J25: Lado 10 | L25: metros | N25: =IFERROR(IF(K25="",0,ROUNDDOWN(('Diseño estructura &CP'!$AZ$6/K25),0)),0) -> 0 | P25: T10 | Q25: =IF(H$11="SI",B$14,"") -> 106 | R25: =IF(Q25="","",Q25*$R$15) -> 424 | S25: =1/(T25+0.01) -> 0.99009901 | T25: =IFERROR(ROUNDDOWN(('Diseño estructura &CP'!$AZ$8/R25),0),0) -> 1 | V25: =+IF(W25=0,"",V24+1) -> 10 | W25: =+Y25/$H$9 -> 84.75 | X25: =ROUNDDOWN(Y25/$C$13,0) -> 14 | Y25: 169.5 | Z25: =IF(X25=0,0,X25+1) -> 15 | AA25: =IF(AB25="","",1/(AB25+0.01)) -> 0.1996008 | AB25: =IF(Y25>0,ROUNDDOWN(('Diseño estructura &CP'!$AZ$5/Y25),0),"") -> 5 | AD25: Lado 10 | AF25: metros | AH25: =IFERROR(IF(AE25="",0,ROUNDDOWN(('Diseño estructura &CP'!$AZ$6/AE25),0)),0) -> 0 | AJ25: T10 | AK25: =IF(AB$11="SI",V$14,"") -> 55 | AL25: =IF(AK25="","",AK25*$R$15) -> 220 | AM25: =1/(AN25+0.01) -> 0.49751244 | AN25: =IFERROR(ROUNDDOWN(('Diseño estructura &CP'!$AZ$8/AL25),0),0) -> 2 | AP25: =+IF(AQ25=0,"",AP24+1) -> 10 | AQ25: =+AS25/$H$9 -> 81 | AR25: =ROUNDDOWN(AS25/$C$13,0) -> 13 | AS25: 162 | AT25: =IF(AR25=0,0,AR25+1) -> 14 | AU25: =IF(AV25="","",1/(AV25+0.01)) -> 0.16638935 | AV25: =IF(AS25>0,ROUNDDOWN(('Diseño estructura &CP'!$AZ$5/AS25),0),"") -> 6 | AX25: Lado 10 | AZ25: metros | BB25: =IFERROR(IF(AY25="",0,ROUNDDOWN(('Diseño estructura &CP'!$AZ$6/AY25),0)),0) -> 0 | BD25: T10 | BE25: =IF(AV$11="SI",AP$14,"") -> 76 | BF25: =IF(BE25="","",BE25*$R$15) -> 304 | BG25: =1/(BH25+0.01) -> 0.99009901 | BH25: =IFERROR(ROUNDDOWN(('Diseño estructura &CP'!$AZ$8/BF25),0),0) -> 1 | BJ25: =+IF(BK25=0,"",BJ24+1) -> 10 | BK25: =+BM25/$H$9 -> 97 | BL25: =ROUNDDOWN(BM25/$BK$13,0) -> 17 | BM25: 194 | BN25: =IF(BL25=0,0,BL25+1) -> 18 | BO25: =IF(BP25="","",1/(BP25+0.01)) -> 0.1996008 | BP25: =IF(BM25>0,ROUNDDOWN(('Diseño estructura &CP'!$AZ$5/BM25),0),"") -> 5 | BR25: Lado 10 | BT25: metros | BV25: =IFERROR(IF(BS25="",0,ROUNDDOWN(('Diseño estructura &CP'!$AZ$6/BS25),0)),0) -> 0 | BX25: T10 | BY25: =IF(BP$11="SI",BJ$14,"") -> 30 | BZ25: =IF(BY25="","",BY25*$R$15) -> 120 | CA25: =1/(CB25+0.01) -> 0.24937656 | CB25: =IFERROR(ROUNDDOWN(('Diseño estructura &CP'!$AZ$8/BZ25),0),0) -> 4 | CD25: =+IF(CE25=0,"",CD24+1) | CE25: =+CG25/$H$9 -> 0 | CF25: =ROUNDDOWN(CG25/$C$13,0) -> 0 | CH25: =IF(CF25=0,0,CF25+1) -> 0 | CI25: =IF(CJ25="","",1/(CJ25+0.01)) | CJ25: =IF(CG25>0,ROUNDDOWN(('Diseño estructura &CP'!$AZ$5/CG25),0),"") | CL25: Lado 10 | CN25: metros | CP25: =IFERROR(IF(CM25="",0,ROUNDDOWN(('Diseño estructura &CP'!$AZ$6/CM25),0)),0) -> 0 | CR25: T10 | CS25: =IF(CJ$11="SI",CD$14,"") | CT25: =IF(CS25="","",CS25*$R$15) | CU25: =1/(CV25+0.01) -> 100 | CV25: =IFERROR(ROUNDDOWN(('Diseño estructura &CP'!$AZ$8/CT25),0),0) -> 0 | CX25: =+IF(CY25=0,"",CX24+1) | CY25: =+DA25/$H$9 -> 0 | CZ25: =ROUNDDOWN(DA25/$C$13,0) -> 0 | DB25: =IF(CZ25=0,0,CZ25+1) -> 0 | DC25: =IF(DD25="","",1/(DD25+0.01)) | DD25: =IF(DA25>0,ROUNDDOWN(('Diseño estructura &CP'!$AZ$5/DA25),0),"") | DF25: Lado 10 | DH25: metros | DJ25: =IFERROR(IF(DG25="",0,ROUNDDOWN(('Diseño estructura &CP'!$AZ$6/DG25),0)),0) -> 0 | DL25: T10 | DM25: =IF(DD$11="SI",CX$14,"") | DN25: =IF(DM25="","",DM25*$R$15) | DO25: =1/(DP25+0.01) -> 100 | DP25: =IFERROR(ROUNDDOWN(('Diseño estructura &CP'!$AZ$8/DN25),0),0) -> 0 | DR25: =+IF(DS25=0,"",DR24+1) | DS25: =+DU25/$H$9 -> 0 | DT25: =ROUNDDOWN(DU25/$C$13,0) -> 0 | DV25: =IF(DT25=0,0,DT25+1) -> 0 | DW25: =IF(DX25="","",1/(DX25+0.01)) | DX25: =IF(DU25>0,ROUNDDOWN(('Diseño estructura &CP'!$AZ$5/DU25),0),"") | DZ25: Lado 10 | EB25: metros | ED25: =IFERROR(IF(EA25="",0,ROUNDDOWN(('Diseño estructura &CP'!$AZ$6/EA25),0)),0) -> 0 | EF25: T10 | EG25: =IF(DX$11="SI",DR$14,"") | EH25: =IF(EG25="","",EG25*$R$15) | EI25: =1/(EJ25+0.01) -> 100 | EJ25: =IFERROR(ROUNDDOWN(('Diseño estructura &CP'!$AZ$8/EH25),0),0) -> 0 | EL25: =+IF(EM25=0,"",EL24+1) | EM25: =+EO25/$H$9 -> 0 | EN25: =ROUNDDOWN(EO25/$C$13,0) -> 0 | EP25: =IF(EN25=0,0,EN25+1) -> 0 | EQ25: =IF(ER25="","",1/(ER25+0.01)) | ER25: =IF(EO25>0,ROUNDDOWN(('Diseño estructura &CP'!$AZ$5/EO25),0),"") | ET25: Lado 10 | EV25: metros | EX25: =IFERROR(IF(EU25="",0,ROUNDDOWN(('Diseño estructura &CP'!$AZ$6/EU25),0)),0) -> 0 | EZ25: T10 | FA25: =IF(ER$11="SI",EL$14,"") | FB25: =IF(FA25="","",FA25*$R$15) | FC25: =1/(FD25+0.01) -> 100 | FD25: =IFERROR(ROUNDDOWN(('Diseño estructura &CP'!$AZ$8/FB25),0),0) -> 0 | FF25: =+IF(FG25=0,"",FF24+1) | FG25: =+FI25/$H$9 -> 0 | FH25: =ROUNDDOWN(FI25/$C$13,0) -> 0 | FJ25: =IF(FH25=0,0,FH25+1) -> 0 | FK25: =IF(FL25="","",1/(FL25+0.01)) | FL25: =IF(FI25>0,ROUNDDOWN(('Diseño estructura &CP'!$AZ$5/FI25),0),"") | FN25: Lado 10 | FP25: metros | FR25: =IFERROR(IF(FO25="",0,ROUNDDOWN(('Diseño estructura &CP'!$AZ$6/FO25),0)),0) -> 0 | FT25: T10 | FU25: =IF(FL$11="SI",FF$14,"") | FV25: =IF(FU25="","",FU25*$R$15) | FW25: =1/(FX25+0.01) -> 100 | FX25: =IFERROR(ROUNDDOWN(('Diseño estructura &CP'!$AZ$8/FV25),0),0) -> 0 | FZ25: =+IF(GA25=0,"",FZ24+1) | GA25: =+GC25/$H$9 -> 0 | GB25: =ROUNDDOWN(GC25/$C$13,0) -> 0 | GD25: =IF(GB25=0,0,GB25+1) -> 0 | GE25: =IF(GF25="","",1/(GF25+0.01)) | GF25: =IF(GC25>0,ROUNDDOWN(('Diseño estructura &CP'!$AZ$5/GC25),0),"") | GH25: Lado 10 | GJ25: metros | GL25: =IFERROR(IF(GI25="",0,ROUNDDOWN(('Diseño estructura &CP'!$AZ$6/GI25),0)),0) -> 0 | GN25: T10 | GO25: =IF(GF$11="SI",FZ$14,"") | GP25: =IF(GO25="","",GO25*$R$15) | GQ25: =1/(GR25+0.01) -> 100 | GR25: =IFERROR(ROUNDDOWN(('Diseño estructura &CP'!$AZ$8/GP25),0),0) -> 0
B26: =+IF(C26=0,"",B25+1) -> 11 | C26: =+E26/$H$9 -> 25.75 | D26: =ROUNDDOWN(E26/$C$13,0) -> 4 | E26: 51.5 | F26: =IF(D26=0,0,D26+1) -> 5 | G26: =IF(H26="","",1/(H26+0.01)) -> 0.052603893 | H26: =IF(E26>0,ROUNDDOWN(('Diseño estructura &CP'!$AZ$5/E26),0),"") -> 19 | J26: Lado 11 | L26: metros | N26: =IFERROR(IF(K26="",0,ROUNDDOWN(('Diseño estructura &CP'!$AZ$6/K26),0)),0) -> 0 | P26: T11 | Q26: =IF(H$11="SI",B$14,"") -> 106 | R26: =IF(Q26="","",Q26*$R$15) -> 424 | S26: =1/(T26+0.01) -> 0.99009901 | T26: =IFERROR(ROUNDDOWN(('Diseño estructura &CP'!$AZ$8/R26),0),0) -> 1 | V26: =+IF(W26=0,"",V25+1) -> 11 | W26: =+Y26/$H$9 -> 86 | X26: =ROUNDDOWN(Y26/$C$13,0) -> 14 | Y26: 172 | Z26: =IF(X26=0,0,X26+1) -> 15 | AA26: =IF(AB26="","",1/(AB26+0.01)) -> 0.1996008 | AB26: =IF(Y26>0,ROUNDDOWN(('Diseño estructura &CP'!$AZ$5/Y26),0),"") -> 5 | AD26: Lado 11 | AF26: metros | AH26: =IFERROR(IF(AE26="",0,ROUNDDOWN(('Diseño estructura &CP'!$AZ$6/AE26),0)),0) -> 0 | AJ26: T11 | AK26: =IF(AB$11="SI",V$14,"") -> 55 | AL26: =IF(AK26="","",AK26*$R$15) -> 220 | AM26: =1/(AN26+0.01) -> 0.49751244 | AN26: =IFERROR(ROUNDDOWN(('Diseño estructura &CP'!$AZ$8/AL26),0),0) -> 2 | AP26: =+IF(AQ26=0,"",AP25+1) -> 11 | AQ26: =+AS26/$H$9 -> 81.5 | AR26: =ROUNDDOWN(AS26/$C$13,0) -> 13 | AS26: 163 | AT26: =IF(AR26=0,0,AR26+1) -> 14 | AU26: =IF(AV26="","",1/(AV26+0.01)) -> 0.16638935 | AV26: =IF(AS26>0,ROUNDDOWN(('Diseño estructura &CP'!$AZ$5/AS26),0),"") -> 6 | AX26: Lado 11 | AZ26: metros | BB26: =IFERROR(IF(AY26="",0,ROUNDDOWN(('Diseño estructura &CP'!$AZ$6/AY26),0)),0) -> 0 | BD26: T11 | BE26: =IF(AV$11="SI",AP$14,"") -> 76 | BF26: =IF(BE26="","",BE26*$R$15) -> 304 | BG26: =1/(BH26+0.01) -> 0.99009901 | BH26: =IFERROR(ROUNDDOWN(('Diseño estructura &CP'!$AZ$8/BF26),0),0) -> 1 | BJ26: =+IF(BK26=0,"",BJ25+1) -> 11 | BK26: =+BM26/$H$9 -> 96.5 | BL26: =ROUNDDOWN(BM26/$BK$13,0) -> 17 | BM26: 193 | BN26: =IF(BL26=0,0,BL26+1) -> 18 | BO26: =IF(BP26="","",1/(BP26+0.01)) -> 0.1996008 | BP26: =IF(BM26>0,ROUNDDOWN(('Diseño estructura &CP'!$AZ$5/BM26),0),"") -> 5 | BR26: Lado 11 | BT26: metros | BV26: =IFERROR(IF(BS26="",0,ROUNDDOWN(('Diseño estructura &CP'!$AZ$6/BS26),0)),0) -> 0 | BX26: T11 | BY26: =IF(BP$11="SI",BJ$14,"") -> 30 | BZ26: =IF(BY26="","",BY26*$R$15) -> 120 | CA26: =1/(CB26+0.01) -> 0.24937656 | CB26: =IFERROR(ROUNDDOWN(('Diseño estructura &CP'!$AZ$8/BZ26),0),0) -> 4 | CD26: =+IF(CE26=0,"",CD25+1) | CE26: =+CG26/$H$9 -> 0 | CF26: =ROUNDDOWN(CG26/$C$13,0) -> 0 | CH26: =IF(CF26=0,0,CF26+1) -> 0 | CI26: =IF(CJ26="","",1/(CJ26+0.01)) | CJ26: =IF(CG26>0,ROUNDDOWN(('Diseño estructura &CP'!$AZ$5/CG26),0),"") | CL26: Lado 11 | CN26: metros | CP26: =IFERROR(IF(CM26="",0,ROUNDDOWN(('Diseño estructura &CP'!$AZ$6/CM26),0)),0) -> 0 | CR26: T11 | CS26: =IF(CJ$11="SI",CD$14,"") | CT26: =IF(CS26="","",CS26*$R$15) | CU26: =1/(CV26+0.01) -> 100 | CV26: =IFERROR(ROUNDDOWN(('Diseño estructura &CP'!$AZ$8/CT26),0),0) -> 0 | CX26: =+IF(CY26=0,"",CX25+1) | CY26: =+DA26/$H$9 -> 0 | CZ26: =ROUNDDOWN(DA26/$C$13,0) -> 0 | DB26: =IF(CZ26=0,0,CZ26+1) -> 0 | DC26: =IF(DD26="","",1/(DD26+0.01)) | DD26: =IF(DA26>0,ROUNDDOWN(('Diseño estructura &CP'!$AZ$5/DA26),0),"") | DF26: Lado 11 | DH26: metros | DJ26: =IFERROR(IF(DG26="",0,ROUNDDOWN(('Diseño estructura &CP'!$AZ$6/DG26),0)),0) -> 0 | DL26: T11 | DM26: =IF(DD$11="SI",CX$14,"") | DN26: =IF(DM26="","",DM26*$R$15) | DO26: =1/(DP26+0.01) -> 100 | DP26: =IFERROR(ROUNDDOWN(('Diseño estructura &CP'!$AZ$8/DN26),0),0) -> 0 | DR26: =+IF(DS26=0,"",DR25+1) | DS26: =+DU26/$H$9 -> 0 | DT26: =ROUNDDOWN(DU26/$C$13,0) -> 0 | DV26: =IF(DT26=0,0,DT26+1) -> 0 | DW26: =IF(DX26="","",1/(DX26+0.01)) | DX26: =IF(DU26>0,ROUNDDOWN(('Diseño estructura &CP'!$AZ$5/DU26),0),"") | DZ26: Lado 11 | EB26: metros | ED26: =IFERROR(IF(EA26="",0,ROUNDDOWN(('Diseño estructura &CP'!$AZ$6/EA26),0)),0) -> 0 | EF26: T11 | EG26: =IF(DX$11="SI",DR$14,"") | EH26: =IF(EG26="","",EG26*$R$15) | EI26: =1/(EJ26+0.01) -> 100 | EJ26: =IFERROR(ROUNDDOWN(('Diseño estructura &CP'!$AZ$8/EH26),0),0) -> 0 | EL26: =+IF(EM26=0,"",EL25+1) | EM26: =+EO26/$H$9 -> 0 | EN26: =ROUNDDOWN(EO26/$C$13,0) -> 0 | EP26: =IF(EN26=0,0,EN26+1) -> 0 | EQ26: =IF(ER26="","",1/(ER26+0.01)) | ER26: =IF(EO26>0,ROUNDDOWN(('Diseño estructura &CP'!$AZ$5/EO26),0),"") | ET26: Lado 11 | EV26: metros | EX26: =IFERROR(IF(EU26="",0,ROUNDDOWN(('Diseño estructura &CP'!$AZ$6/EU26),0)),0) -> 0 | EZ26: T11 | FA26: =IF(ER$11="SI",EL$14,"") | FB26: =IF(FA26="","",FA26*$R$15) | FC26: =1/(FD26+0.01) -> 100 | FD26: =IFERROR(ROUNDDOWN(('Diseño estructura &CP'!$AZ$8/FB26),0),0) -> 0 | FF26: =+IF(FG26=0,"",FF25+1) | FG26: =+FI26/$H$9 -> 0 | FH26: =ROUNDDOWN(FI26/$C$13,0) -> 0 | FJ26: =IF(FH26=0,0,FH26+1) -> 0 | FK26: =IF(FL26="","",1/(FL26+0.01)) | FL26: =IF(FI26>0,ROUNDDOWN(('Diseño estructura &CP'!$AZ$5/FI26),0),"") | FN26: Lado 11 | FP26: metros | FR26: =IFERROR(IF(FO26="",0,ROUNDDOWN(('Diseño estructura &CP'!$AZ$6/FO26),0)),0) -> 0 | FT26: T11 | FU26: =IF(FL$11="SI",FF$14,"") | FV26: =IF(FU26="","",FU26*$R$15) | FW26: =1/(FX26+0.01) -> 100 | FX26: =IFERROR(ROUNDDOWN(('Diseño estructura &CP'!$AZ$8/FV26),0),0) -> 0 | FZ26: =+IF(GA26=0,"",FZ25+1) | GA26: =+GC26/$H$9 -> 0 | GB26: =ROUNDDOWN(GC26/$C$13,0) -> 0 | GD26: =IF(GB26=0,0,GB26+1) -> 0 | GE26: =IF(GF26="","",1/(GF26+0.01)) | GF26: =IF(GC26>0,ROUNDDOWN(('Diseño estructura &CP'!$AZ$5/GC26),0),"") | GH26: Lado 11 | GJ26: metros | GL26: =IFERROR(IF(GI26="",0,ROUNDDOWN(('Diseño estructura &CP'!$AZ$6/GI26),0)),0) -> 0 | GN26: T11 | GO26: =IF(GF$11="SI",FZ$14,"") | GP26: =IF(GO26="","",GO26*$R$15) | GQ26: =1/(GR26+0.01) -> 100 | GR26: =IFERROR(ROUNDDOWN(('Diseño estructura &CP'!$AZ$8/GP26),0),0) -> 0
B27: =+IF(C27=0,"",B26+1) -> 12 | C27: =+E27/$H$9 -> 27 | D27: =ROUNDDOWN(E27/$C$13,0) -> 4 | E27: 54 | F27: =IF(D27=0,0,D27+1) -> 5 | G27: =IF(H27="","",1/(H27+0.01)) -> 0.055524708 | H27: =IF(E27>0,ROUNDDOWN(('Diseño estructura &CP'!$AZ$5/E27),0),"") -> 18 | J27: Lado 12 | L27: metros | N27: =IFERROR(IF(K27="",0,ROUNDDOWN(('Diseño estructura &CP'!$AZ$6/K27),0)),0) -> 0 | P27: T12 | Q27: =IF(H$11="SI",B$14,"") -> 106 | R27: =IF(Q27="","",Q27*$R$15) -> 424 | S27: =1/(T27+0.01) -> 0.99009901 | T27: =IFERROR(ROUNDDOWN(('Diseño estructura &CP'!$AZ$8/R27),0),0) -> 1 | V27: =+IF(W27=0,"",V26+1) -> 12 | W27: =+Y27/$H$9 -> 86.5 | X27: =ROUNDDOWN(Y27/$C$13,0) -> 14 | Y27: 173 | Z27: =IF(X27=0,0,X27+1) -> 15 | AA27: =IF(AB27="","",1/(AB27+0.01)) -> 0.1996008 | AB27: =IF(Y27>0,ROUNDDOWN(('Diseño estructura &CP'!$AZ$5/Y27),0),"") -> 5 | AD27: Lado 12 | AF27: metros | AH27: =IFERROR(IF(AE27="",0,ROUNDDOWN(('Diseño estructura &CP'!$AZ$6/AE27),0)),0) -> 0 | AJ27: T12 | AK27: =IF(AB$11="SI",V$14,"") -> 55 | AL27: =IF(AK27="","",AK27*$R$15) -> 220 | AM27: =1/(AN27+0.01) -> 0.49751244 | AN27: =IFERROR(ROUNDDOWN(('Diseño estructura &CP'!$AZ$8/AL27),0),0) -> 2 | AP27: =+IF(AQ27=0,"",AP26+1) -> 12 | AQ27: =+AS27/$H$9 -> 81 | AR27: =ROUNDDOWN(AS27/$C$13,0) -> 13 | AS27: 162 | AT27: =IF(AR27=0,0,AR27+1) -> 14 | AU27: =IF(AV27="","",1/(AV27+0.01)) -> 0.16638935 | AV27: =IF(AS27>0,ROUNDDOWN(('Diseño estructura &CP'!$AZ$5/AS27),0),"") -> 6 | AX27: Lado 12 | AZ27: metros | BB27: =IFERROR(IF(AY27="",0,ROUNDDOWN(('Diseño estructura &CP'!$AZ$6/AY27),0)),0) -> 0 | BD27: T12 | BE27: =IF(AV$11="SI",AP$14,"") -> 76 | BF27: =IF(BE27="","",BE27*$R$15) -> 304 | BG27: =1/(BH27+0.01) -> 0.99009901 | BH27: =IFERROR(ROUNDDOWN(('Diseño estructura &CP'!$AZ$8/BF27),0),0) -> 1 | BJ27: =+IF(BK27=0,"",BJ26+1) -> 12 | BK27: =+BM27/$H$9 -> 94.75 | BL27: =ROUNDDOWN(BM27/$BK$13,0) -> 17 | BM27: 189.5 | BN27: =IF(BL27=0,0,BL27+1) -> 18 | BO27: =IF(BP27="","",1/(BP27+0.01)) -> 0.1996008 | BP27: =IF(BM27>0,ROUNDDOWN(('Diseño estructura &CP'!$AZ$5/BM27),0),"") -> 5 | BR27: Lado 12 | BT27: metros | BV27: =IFERROR(IF(BS27="",0,ROUNDDOWN(('Diseño estructura &CP'!$AZ$6/BS27),0)),0) -> 0 | BX27: T12 | BY27: =IF(BP$11="SI",BJ$14,"") -> 30 | BZ27: =IF(BY27="","",BY27*$R$15) -> 120 | CA27: =1/(CB27+0.01) -> 0.24937656 | CB27: =IFERROR(ROUNDDOWN(('Diseño estructura &CP'!$AZ$8/BZ27),0),0) -> 4 | CD27: =+IF(CE27=0,"",CD26+1) | CE27: =+CG27/$H$9 -> 0 | CF27: =ROUNDDOWN(CG27/$C$13,0) -> 0 | CH27: =IF(CF27=0,0,CF27+1) -> 0 | CI27: =IF(CJ27="","",1/(CJ27+0.01)) | CJ27: =IF(CG27>0,ROUNDDOWN(('Diseño estructura &CP'!$AZ$5/CG27),0),"") | CL27: Lado 12 | CN27: metros | CP27: =IFERROR(IF(CM27="",0,ROUNDDOWN(('Diseño estructura &CP'!$AZ$6/CM27),0)),0) -> 0 | CR27: T12 | CS27: =IF(CJ$11="SI",CD$14,"") | CT27: =IF(CS27="","",CS27*$R$15) | CU27: =1/(CV27+0.01) -> 100 | CV27: =IFERROR(ROUNDDOWN(('Diseño estructura &CP'!$AZ$8/CT27),0),0) -> 0 | CX27: =+IF(CY27=0,"",CX26+1) | CY27: =+DA27/$H$9 -> 0 | CZ27: =ROUNDDOWN(DA27/$C$13,0) -> 0 | DB27: =IF(CZ27=0,0,CZ27+1) -> 0 | DC27: =IF(DD27="","",1/(DD27+0.01)) | DD27: =IF(DA27>0,ROUNDDOWN(('Diseño estructura &CP'!$AZ$5/DA27),0),"") | DF27: Lado 12 | DH27: metros | DJ27: =IFERROR(IF(DG27="",0,ROUNDDOWN(('Diseño estructura &CP'!$AZ$6/DG27),0)),0) -> 0 | DL27: T12 | DM27: =IF(DD$11="SI",CX$14,"") | DN27: =IF(DM27="","",DM27*$R$15) | DO27: =1/(DP27+0.01) -> 100 | DP27: =IFERROR(ROUNDDOWN(('Diseño estructura &CP'!$AZ$8/DN27),0),0) -> 0 | DR27: =+IF(DS27=0,"",DR26+1) | DS27: =+DU27/$H$9 -> 0 | DT27: =ROUNDDOWN(DU27/$C$13,0) -> 0 | DV27: =IF(DT27=0,0,DT27+1) -> 0 | DW27: =IF(DX27="","",1/(DX27+0.01)) | DX27: =IF(DU27>0,ROUNDDOWN(('Diseño estructura &CP'!$AZ$5/DU27),0),"") | DZ27: Lado 12 | EB27: metros | ED27: =IFERROR(IF(EA27="",0,ROUNDDOWN(('Diseño estructura &CP'!$AZ$6/EA27),0)),0) -> 0 | EF27: T12 | EG27: =IF(DX$11="SI",DR$14,"") | EH27: =IF(EG27="","",EG27*$R$15) | EI27: =1/(EJ27+0.01) -> 100 | EJ27: =IFERROR(ROUNDDOWN(('Diseño estructura &CP'!$AZ$8/EH27),0),0) -> 0 | EL27: =+IF(EM27=0,"",EL26+1) | EM27: =+EO27/$H$9 -> 0 | EN27: =ROUNDDOWN(EO27/$C$13,0) -> 0 | EP27: =IF(EN27=0,0,EN27+1) -> 0 | EQ27: =IF(ER27="","",1/(ER27+0.01)) | ER27: =IF(EO27>0,ROUNDDOWN(('Diseño estructura &CP'!$AZ$5/EO27),0),"") | ET27: Lado 12 | EV27: metros | EX27: =IFERROR(IF(EU27="",0,ROUNDDOWN(('Diseño estructura &CP'!$AZ$6/EU27),0)),0) -> 0 | EZ27: T12 | FA27: =IF(ER$11="SI",EL$14,"") | FB27: =IF(FA27="","",FA27*$R$15) | FC27: =1/(FD27+0.01) -> 100 | FD27: =IFERROR(ROUNDDOWN(('Diseño estructura &CP'!$AZ$8/FB27),0),0) -> 0 | FF27: =+IF(FG27=0,"",FF26+1) | FG27: =+FI27/$H$9 -> 0 | FH27: =ROUNDDOWN(FI27/$C$13,0) -> 0 | FJ27: =IF(FH27=0,0,FH27+1) -> 0 | FK27: =IF(FL27="","",1/(FL27+0.01)) | FL27: =IF(FI27>0,ROUNDDOWN(('Diseño estructura &CP'!$AZ$5/FI27),0),"") | FN27: Lado 12 | FP27: metros | FR27: =IFERROR(IF(FO27="",0,ROUNDDOWN(('Diseño estructura &CP'!$AZ$6/FO27),0)),0) -> 0 | FT27: T12 | FU27: =IF(FL$11="SI",FF$14,"") | FV27: =IF(FU27="","",FU27*$R$15) | FW27: =1/(FX27+0.01) -> 100 | FX27: =IFERROR(ROUNDDOWN(('Diseño estructura &CP'!$AZ$8/FV27),0),0) -> 0 | FZ27: =+IF(GA27=0,"",FZ26+1) | GA27: =+GC27/$H$9 -> 0 | GB27: =ROUNDDOWN(GC27/$C$13,0) -> 0 | GD27: =IF(GB27=0,0,GB27+1) -> 0 | GE27: =IF(GF27="","",1/(GF27+0.01)) | GF27: =IF(GC27>0,ROUNDDOWN(('Diseño estructura &CP'!$AZ$5/GC27),0),"") | GH27: Lado 12 | GJ27: metros | GL27: =IFERROR(IF(GI27="",0,ROUNDDOWN(('Diseño estructura &CP'!$AZ$6/GI27),0)),0) -> 0 | GN27: T12 | GO27: =IF(GF$11="SI",FZ$14,"") | GP27: =IF(GO27="","",GO27*$R$15) | GQ27: =1/(GR27+0.01) -> 100 | GR27: =IFERROR(ROUNDDOWN(('Diseño estructura &CP'!$AZ$8/GP27),0),0) -> 0
B28: =+IF(C28=0,"",B27+1) -> 13 | C28: =+E28/$H$9 -> 28 | D28: =ROUNDDOWN(E28/$C$13,0) -> 4 | E28: 56 | F28: =IF(D28=0,0,D28+1) -> 5 | G28: =IF(H28="","",1/(H28+0.01)) -> 0.058788948 | H28: =IF(E28>0,ROUNDDOWN(('Diseño estructura &CP'!$AZ$5/E28),0),"") -> 17 | J28: Lado 13 | L28: metros | N28: =IFERROR(IF(K28="",0,ROUNDDOWN(('Diseño estructura &CP'!$AZ$6/K28),0)),0) -> 0 | P28: T13 | Q28: =IF(H$11="SI",B$14,"") -> 106 | R28: =IF(Q28="","",Q28*$R$15) -> 424 | S28: =1/(T28+0.01) -> 0.99009901 | T28: =IFERROR(ROUNDDOWN(('Diseño estructura &CP'!$AZ$8/R28),0),0) -> 1 | V28: =+IF(W28=0,"",V27+1) -> 13 | W28: =+Y28/$H$9 -> 87.5 | X28: =ROUNDDOWN(Y28/$C$13,0) -> 14 | Y28: 175 | Z28: =IF(X28=0,0,X28+1) -> 15 | AA28: =IF(AB28="","",1/(AB28+0.01)) -> 0.1996008 | AB28: =IF(Y28>0,ROUNDDOWN(('Diseño estructura &CP'!$AZ$5/Y28),0),"") -> 5 | AD28: Lado 13 | AF28: metros | AH28: =IFERROR(IF(AE28="",0,ROUNDDOWN(('Diseño estructura &CP'!$AZ$6/AE28),0)),0) -> 0 | AJ28: T13 | AK28: =IF(AB$11="SI",V$14,"") -> 55 | AL28: =IF(AK28="","",AK28*$R$15) -> 220 | AM28: =1/(AN28+0.01) -> 0.49751244 | AN28: =IFERROR(ROUNDDOWN(('Diseño estructura &CP'!$AZ$8/AL28),0),0) -> 2 | AP28: =+IF(AQ28=0,"",AP27+1) -> 13 | AQ28: =+AS28/$H$9 -> 81 | AR28: =ROUNDDOWN(AS28/$C$13,0) -> 13 | AS28: 162 | AT28: =IF(AR28=0,0,AR28+1) -> 14 | AU28: =IF(AV28="","",1/(AV28+0.01)) -> 0.16638935 | AV28: =IF(AS28>0,ROUNDDOWN(('Diseño estructura &CP'!$AZ$5/AS28),0),"") -> 6 | AX28: Lado 13 | AZ28: metros | BB28: =IFERROR(IF(AY28="",0,ROUNDDOWN(('Diseño estructura &CP'!$AZ$6/AY28),0)),0) -> 0 | BD28: T13 | BE28: =IF(AV$11="SI",AP$14,"") -> 76 | BF28: =IF(BE28="","",BE28*$R$15) -> 304 | BG28: =1/(BH28+0.01) -> 0.99009901 | BH28: =IFERROR(ROUNDDOWN(('Diseño estructura &CP'!$AZ$8/BF28),0),0) -> 1 | BJ28: =+IF(BK28=0,"",BJ27+1) -> 13 | BK28: =+BM28/$H$9 -> 92 | BL28: =ROUNDDOWN(BM28/$BK$13,0) -> 16 | BM28: 184 | BN28: =IF(BL28=0,0,BL28+1) -> 17 | BO28: =IF(BP28="","",1/(BP28+0.01)) -> 0.1996008 | BP28: =IF(BM28>0,ROUNDDOWN(('Diseño estructura &CP'!$AZ$5/BM28),0),"") -> 5 | BR28: Lado 13 | BT28: metros | BV28: =IFERROR(IF(BS28="",0,ROUNDDOWN(('Diseño estructura &CP'!$AZ$6/BS28),0)),0) -> 0 | BX28: T13 | BY28: =IF(BP$11="SI",BJ$14,"") -> 30 | BZ28: =IF(BY28="","",BY28*$R$15) -> 120 | CA28: =1/(CB28+0.01) -> 0.24937656 | CB28: =IFERROR(ROUNDDOWN(('Diseño estructura &CP'!$AZ$8/BZ28),0),0) -> 4 | CD28: =+IF(CE28=0,"",CD27+1) | CE28: =+CG28/$H$9 -> 0 | CF28: =ROUNDDOWN(CG28/$C$13,0) -> 0 | CH28: =IF(CF28=0,0,CF28+1) -> 0 | CI28: =IF(CJ28="","",1/(CJ28+0.01)) | CJ28: =IF(CG28>0,ROUNDDOWN(('Diseño estructura &CP'!$AZ$5/CG28),0),"") | CL28: Lado 13 | CN28: metros | CP28: =IFERROR(IF(CM28="",0,ROUNDDOWN(('Diseño estructura &CP'!$AZ$6/CM28),0)),0) -> 0 | CR28: T13 | CS28: =IF(CJ$11="SI",CD$14,"") | CT28: =IF(CS28="","",CS28*$R$15) | CU28: =1/(CV28+0.01) -> 100 | CV28: =IFERROR(ROUNDDOWN(('Diseño estructura &CP'!$AZ$8/CT28),0),0) -> 0 | CX28: =+IF(CY28=0,"",CX27+1) | CY28: =+DA28/$H$9 -> 0 | CZ28: =ROUNDDOWN(DA28/$C$13,0) -> 0 | DB28: =IF(CZ28=0,0,CZ28+1) -> 0 | DC28: =IF(DD28="","",1/(DD28+0.01)) | DD28: =IF(DA28>0,ROUNDDOWN(('Diseño estructura &CP'!$AZ$5/DA28),0),"") | DF28: Lado 13 | DH28: metros | DJ28: =IFERROR(IF(DG28="",0,ROUNDDOWN(('Diseño estructura &CP'!$AZ$6/DG28),0)),0) -> 0 | DL28: T13 | DM28: =IF(DD$11="SI",CX$14,"") | DN28: =IF(DM28="","",DM28*$R$15) | DO28: =1/(DP28+0.01) -> 100 | DP28: =IFERROR(ROUNDDOWN(('Diseño estructura &CP'!$AZ$8/DN28),0),0) -> 0 | DR28: =+IF(DS28=0,"",DR27+1) | DS28: =+DU28/$H$9 -> 0 | DT28: =ROUNDDOWN(DU28/$C$13,0) -> 0 | DV28: =IF(DT28=0,0,DT28+1) -> 0 | DW28: =IF(DX28="","",1/(DX28+0.01)) | DX28: =IF(DU28>0,ROUNDDOWN(('Diseño estructura &CP'!$AZ$5/DU28),0),"") | DZ28: Lado 13 | EB28: metros | ED28: =IFERROR(IF(EA28="",0,ROUNDDOWN(('Diseño estructura &CP'!$AZ$6/EA28),0)),0) -> 0 | EF28: T13 | EG28: =IF(DX$11="SI",DR$14,"") | EH28: =IF(EG28="","",EG28*$R$15) | EI28: =1/(EJ28+0.01) -> 100 | EJ28: =IFERROR(ROUNDDOWN(('Diseño estructura &CP'!$AZ$8/EH28),0),0) -> 0 | EL28: =+IF(EM28=0,"",EL27+1) | EM28: =+EO28/$H$9 -> 0 | EN28: =ROUNDDOWN(EO28/$C$13,0) -> 0 | EP28: =IF(EN28=0,0,EN28+1) -> 0 | EQ28: =IF(ER28="","",1/(ER28+0.01)) | ER28: =IF(EO28>0,ROUNDDOWN(('Diseño estructura &CP'!$AZ$5/EO28),0),"") | ET28: Lado 13 | EV28: metros | EX28: =IFERROR(IF(EU28="",0,ROUNDDOWN(('Diseño estructura &CP'!$AZ$6/EU28),0)),0) -> 0 | EZ28: T13 | FA28: =IF(ER$11="SI",EL$14,"") | FB28: =IF(FA28="","",FA28*$R$15) | FC28: =1/(FD28+0.01) -> 100 | FD28: =IFERROR(ROUNDDOWN(('Diseño estructura &CP'!$AZ$8/FB28),0),0) -> 0 | FF28: =+IF(FG28=0,"",FF27+1) | FG28: =+FI28/$H$9 -> 0 | FH28: =ROUNDDOWN(FI28/$C$13,0) -> 0 | FJ28: =IF(FH28=0,0,FH28+1) -> 0 | FK28: =IF(FL28="","",1/(FL28+0.01)) | FL28: =IF(FI28>0,ROUNDDOWN(('Diseño estructura &CP'!$AZ$5/FI28),0),"") | FN28: Lado 13 | FP28: metros | FR28: =IFERROR(IF(FO28="",0,ROUNDDOWN(('Diseño estructura &CP'!$AZ$6/FO28),0)),0) -> 0 | FT28: T13 | FU28: =IF(FL$11="SI",FF$14,"") | FV28: =IF(FU28="","",FU28*$R$15) | FW28: =1/(FX28+0.01) -> 100 | FX28: =IFERROR(ROUNDDOWN(('Diseño estructura &CP'!$AZ$8/FV28),0),0) -> 0 | FZ28: =+IF(GA28=0,"",FZ27+1) | GA28: =+GC28/$H$9 -> 0 | GB28: =ROUNDDOWN(GC28/$C$13,0) -> 0 | GD28: =IF(GB28=0,0,GB28+1) -> 0 | GE28: =IF(GF28="","",1/(GF28+0.01)) | GF28: =IF(GC28>0,ROUNDDOWN(('Diseño estructura &CP'!$AZ$5/GC28),0),"") | GH28: Lado 13 | GJ28: metros | GL28: =IFERROR(IF(GI28="",0,ROUNDDOWN(('Diseño estructura &CP'!$AZ$6/GI28),0)),0) -> 0 | GN28: T13 | GO28: =IF(GF$11="SI",FZ$14,"") | GP28: =IF(GO28="","",GO28*$R$15) | GQ28: =1/(GR28+0.01) -> 100 | GR28: =IFERROR(ROUNDDOWN(('Diseño estructura &CP'!$AZ$8/GP28),0),0) -> 0
B29: =+IF(C29=0,"",B28+1) -> 14 | C29: =+E29/$H$9 -> 29.5 | D29: =ROUNDDOWN(E29/$C$13,0) -> 4 | E29: 59 | F29: =IF(D29=0,0,D29+1) -> 5 | G29: =IF(H29="","",1/(H29+0.01)) -> 0.062460962 | H29: =IF(E29>0,ROUNDDOWN(('Diseño estructura &CP'!$AZ$5/E29),0),"") -> 16 | J29: Lado 14 | L29: metros | N29: =IFERROR(IF(K29="",0,ROUNDDOWN(('Diseño estructura &CP'!$AZ$6/K29),0)),0) -> 0 | P29: T14 | Q29: =IF(H$11="SI",B$14,"") -> 106 | R29: =IF(Q29="","",Q29*$R$15) -> 424 | S29: =1/(T29+0.01) -> 0.99009901 | T29: =IFERROR(ROUNDDOWN(('Diseño estructura &CP'!$AZ$8/R29),0),0) -> 1 | V29: =+IF(W29=0,"",V28+1) -> 14 | W29: =+Y29/$H$9 -> 89 | X29: =ROUNDDOWN(Y29/$C$13,0) -> 14 | Y29: 178 | Z29: =IF(X29=0,0,X29+1) -> 15 | AA29: =IF(AB29="","",1/(AB29+0.01)) -> 0.1996008 | AB29: =IF(Y29>0,ROUNDDOWN(('Diseño estructura &CP'!$AZ$5/Y29),0),"") -> 5 | AD29: Lado 14 | AF29: metros | AH29: =IFERROR(IF(AE29="",0,ROUNDDOWN(('Diseño estructura &CP'!$AZ$6/AE29),0)),0) -> 0 | AJ29: T14 | AK29: =IF(AB$11="SI",V$14,"") -> 55 | AL29: =IF(AK29="","",AK29*$R$15) -> 220 | AM29: =1/(AN29+0.01) -> 0.49751244 | AN29: =IFERROR(ROUNDDOWN(('Diseño estructura &CP'!$AZ$8/AL29),0),0) -> 2 | AP29: =+IF(AQ29=0,"",AP28+1) -> 14 | AQ29: =+AS29/$H$9 -> 81.25 | AR29: =ROUNDDOWN(AS29/$C$13,0) -> 13 | AS29: 162.5 | AT29: =IF(AR29=0,0,AR29+1) -> 14 | AU29: =IF(AV29="","",1/(AV29+0.01)) -> 0.16638935 | AV29: =IF(AS29>0,ROUNDDOWN(('Diseño estructura &CP'!$AZ$5/AS29),0),"") -> 6 | AX29: Lado 14 | AZ29: metros | BB29: =IFERROR(IF(AY29="",0,ROUNDDOWN(('Diseño estructura &CP'!$AZ$6/AY29),0)),0) -> 0 | BD29: T14 | BE29: =IF(AV$11="SI",AP$14,"") -> 76 | BF29: =IF(BE29="","",BE29*$R$15) -> 304 | BG29: =1/(BH29+0.01) -> 0.99009901 | BH29: =IFERROR(ROUNDDOWN(('Diseño estructura &CP'!$AZ$8/BF29),0),0) -> 1 | BJ29: =+IF(BK29=0,"",BJ28+1) -> 14 | BK29: =+BM29/$H$9 -> 87.75 | BL29: =ROUNDDOWN(BM29/$BK$13,0) -> 15 | BM29: 175.5 | BN29: =IF(BL29=0,0,BL29+1) -> 16 | BO29: =IF(BP29="","",1/(BP29+0.01)) -> 0.1996008 | BP29: =IF(BM29>0,ROUNDDOWN(('Diseño estructura &CP'!$AZ$5/BM29),0),"") -> 5 | BR29: Lado 14 | BT29: metros | BV29: =IFERROR(IF(BS29="",0,ROUNDDOWN(('Diseño estructura &CP'!$AZ$6/BS29),0)),0) -> 0 | BX29: T14 | BY29: =IF(BP$11="SI",BJ$14,"") -> 30 | BZ29: =IF(BY29="","",BY29*$R$15) -> 120 | CA29: =1/(CB29+0.01) -> 0.24937656 | CB29: =IFERROR(ROUNDDOWN(('Diseño estructura &CP'!$AZ$8/BZ29),0),0) -> 4 | CD29: =+IF(CE29=0,"",CD28+1) | CE29: =+CG29/$H$9 -> 0 | CF29: =ROUNDDOWN(CG29/$C$13,0) -> 0 | CH29: =IF(CF29=0,0,CF29+1) -> 0 | CI29: =IF(CJ29="","",1/(CJ29+0.01)) | CJ29: =IF(CG29>0,ROUNDDOWN(('Diseño estructura &CP'!$AZ$5/CG29),0),"") | CL29: Lado 14 | CN29: metros | CP29: =IFERROR(IF(CM29="",0,ROUNDDOWN(('Diseño estructura &CP'!$AZ$6/CM29),0)),0) -> 0 | CR29: T14 | CS29: =IF(CJ$11="SI",CD$14,"") | CT29: =IF(CS29="","",CS29*$R$15) | CU29: =1/(CV29+0.01) -> 100 | CV29: =IFERROR(ROUNDDOWN(('Diseño estructura &CP'!$AZ$8/CT29),0),0) -> 0 | CX29: =+IF(CY29=0,"",CX28+1) | CY29: =+DA29/$H$9 -> 0 | CZ29: =ROUNDDOWN(DA29/$C$13,0) -> 0 | DB29: =IF(CZ29=0,0,CZ29+1) -> 0 | DC29: =IF(DD29="","",1/(DD29+0.01)) | DD29: =IF(DA29>0,ROUNDDOWN(('Diseño estructura &CP'!$AZ$5/DA29),0),"") | DF29: Lado 14 | DH29: metros | DJ29: =IFERROR(IF(DG29="",0,ROUNDDOWN(('Diseño estructura &CP'!$AZ$6/DG29),0)),0) -> 0 | DL29: T14 | DM29: =IF(DD$11="SI",CX$14,"") | DN29: =IF(DM29="","",DM29*$R$15) | DO29: =1/(DP29+0.01) -> 100 | DP29: =IFERROR(ROUNDDOWN(('Diseño estructura &CP'!$AZ$8/DN29),0),0) -> 0 | DR29: =+IF(DS29=0,"",DR28+1) | DS29: =+DU29/$H$9 -> 0 | DT29: =ROUNDDOWN(DU29/$C$13,0) -> 0 | DV29: =IF(DT29=0,0,DT29+1) -> 0 | DW29: =IF(DX29="","",1/(DX29+0.01)) | DX29: =IF(DU29>0,ROUNDDOWN(('Diseño estructura &CP'!$AZ$5/DU29),0),"") | DZ29: Lado 14 | EB29: metros | ED29: =IFERROR(IF(EA29="",0,ROUNDDOWN(('Diseño estructura &CP'!$AZ$6/EA29),0)),0) -> 0 | EF29: T14 | EG29: =IF(DX$11="SI",DR$14,"") | EH29: =IF(EG29="","",EG29*$R$15) | EI29: =1/(EJ29+0.01) -> 100 | EJ29: =IFERROR(ROUNDDOWN(('Diseño estructura &CP'!$AZ$8/EH29),0),0) -> 0 | EL29: =+IF(EM29=0,"",EL28+1) | EM29: =+EO29/$H$9 -> 0 | EN29: =ROUNDDOWN(EO29/$C$13,0) -> 0 | EP29: =IF(EN29=0,0,EN29+1) -> 0 | EQ29: =IF(ER29="","",1/(ER29+0.01)) | ER29: =IF(EO29>0,ROUNDDOWN(('Diseño estructura &CP'!$AZ$5/EO29),0),"") | ET29: Lado 14 | EV29: metros | EX29: =IFERROR(IF(EU29="",0,ROUNDDOWN(('Diseño estructura &CP'!$AZ$6/EU29),0)),0) -> 0 | EZ29: T14 | FA29: =IF(ER$11="SI",EL$14,"") | FB29: =IF(FA29="","",FA29*$R$15) | FC29: =1/(FD29+0.01) -> 100 | FD29: =IFERROR(ROUNDDOWN(('Diseño estructura &CP'!$AZ$8/FB29),0),0) -> 0 | FF29: =+IF(FG29=0,"",FF28+1) | FG29: =+FI29/$H$9 -> 0 | FH29: =ROUNDDOWN(FI29/$C$13,0) -> 0 | FJ29: =IF(FH29=0,0,FH29+1) -> 0 | FK29: =IF(FL29="","",1/(FL29+0.01)) | FL29: =IF(FI29>0,ROUNDDOWN(('Diseño estructura &CP'!$AZ$5/FI29),0),"") | FN29: Lado 14 | FP29: metros | FR29: =IFERROR(IF(FO29="",0,ROUNDDOWN(('Diseño estructura &CP'!$AZ$6/FO29),0)),0) -> 0 | FT29: T14 | FU29: =IF(FL$11="SI",FF$14,"") | FV29: =IF(FU29="","",FU29*$R$15) | FW29: =1/(FX29+0.01) -> 100 | FX29: =IFERROR(ROUNDDOWN(('Diseño estructura &CP'!$AZ$8/FV29),0),0) -> 0 | FZ29: =+IF(GA29=0,"",FZ28+1) | GA29: =+GC29/$H$9 -> 0 | GB29: =ROUNDDOWN(GC29/$C$13,0) -> 0 | GD29: =IF(GB29=0,0,GB29+1) -> 0 | GE29: =IF(GF29="","",1/(GF29+0.01)) | GF29: =IF(GC29>0,ROUNDDOWN(('Diseño estructura &CP'!$AZ$5/GC29),0),"") | GH29: Lado 14 | GJ29: metros | GL29: =IFERROR(IF(GI29="",0,ROUNDDOWN(('Diseño estructura &CP'!$AZ$6/GI29),0)),0) -> 0 | GN29: T14 | GO29: =IF(GF$11="SI",FZ$14,"") | GP29: =IF(GO29="","",GO29*$R$15) | GQ29: =1/(GR29+0.01) -> 100 | GR29: =IFERROR(ROUNDDOWN(('Diseño estructura &CP'!$AZ$8/GP29),0),0) -> 0
B30: =+IF(C30=0,"",B29+1) -> 15 | C30: =+E30/$H$9 -> 30.25 | D30: =ROUNDDOWN(E30/$C$13,0) -> 5 | E30: 60.5 | F30: =IF(D30=0,0,D30+1) -> 6 | G30: =IF(H30="","",1/(H30+0.01)) -> 0.062460962 | H30: =IF(E30>0,ROUNDDOWN(('Diseño estructura &CP'!$AZ$5/E30),0),"") -> 16 | J30: Lado 15 | L30: metros | N30: =IFERROR(IF(K30="",0,ROUNDDOWN(('Diseño estructura &CP'!$AZ$6/K30),0)),0) -> 0 | P30: T15 | Q30: =IF(H$11="SI",B$14,"") -> 106 | R30: =IF(Q30="","",Q30*$R$15) -> 424 | S30: =1/(T30+0.01) -> 0.99009901 | T30: =IFERROR(ROUNDDOWN(('Diseño estructura &CP'!$AZ$8/R30),0),0) -> 1 | V30: =+IF(W30=0,"",V29+1) -> 15 | W30: =+Y30/$H$9 -> 89.5 | X30: =ROUNDDOWN(Y30/$C$13,0) -> 14 | Y30: 179 | Z30: =IF(X30=0,0,X30+1) -> 15 | AA30: =IF(AB30="","",1/(AB30+0.01)) -> 0.1996008 | AB30: =IF(Y30>0,ROUNDDOWN(('Diseño estructura &CP'!$AZ$5/Y30),0),"") -> 5 | AD30: Lado 15 | AF30: metros | AH30: =IFERROR(IF(AE30="",0,ROUNDDOWN(('Diseño estructura &CP'!$AZ$6/AE30),0)),0) -> 0 | AJ30: T15 | AK30: =IF(AB$11="SI",V$14,"") -> 55 | AL30: =IF(AK30="","",AK30*$R$15) -> 220 | AM30: =1/(AN30+0.01) -> 0.49751244 | AN30: =IFERROR(ROUNDDOWN(('Diseño estructura &CP'!$AZ$8/AL30),0),0) -> 2 | AP30: =+IF(AQ30=0,"",AP29+1) -> 15 | AQ30: =+AS30/$H$9 -> 81.5 | AR30: =ROUNDDOWN(AS30/$C$13,0) -> 13 | AS30: 163 | AT30: =IF(AR30=0,0,AR30+1) -> 14 | AU30: =IF(AV30="","",1/(AV30+0.01)) -> 0.16638935 | AV30: =IF(AS30>0,ROUNDDOWN(('Diseño estructura &CP'!$AZ$5/AS30),0),"") -> 6 | AX30: Lado 15 | AZ30: metros | BB30: =IFERROR(IF(AY30="",0,ROUNDDOWN(('Diseño estructura &CP'!$AZ$6/AY30),0)),0) -> 0 | BJ30: =+IF(BK30=0,"",BJ29+1) -> 15 | BK30: =+BM30/$H$9 -> 84.25 | BL30: =ROUNDDOWN(BM30/$BK$13,0) -> 15 | BM30: 168.5 | BN30: =IF(BL30=0,0,BL30+1) -> 16 | BO30: =IF(BP30="","",1/(BP30+0.01)) -> 0.1996008 | BP30: =IF(BM30>0,ROUNDDOWN(('Diseño estructura &CP'!$AZ$5/BM30),0),"") -> 5 | BR30: Lado 15 | BT30: metros | BV30: =IFERROR(IF(BS30="",0,ROUNDDOWN(('Diseño estructura &CP'!$AZ$6/BS30),0)),0) -> 0 | BX30: T15 | BY30: =IF(BP$11="SI",BJ$14,"") -> 30 | BZ30: =IF(BY30="","",BY30*$R$15) -> 120 | CA30: =1/(CB30+0.01) -> 0.24937656 | CB30: =IFERROR(ROUNDDOWN(('Diseño estructura &CP'!$AZ$8/BZ30),0),0) -> 4 | CD30: =+IF(CE30=0,"",CD29+1) | CE30: =+CG30/$H$9 -> 0 | CF30: =ROUNDDOWN(CG30/$C$13,0) -> 0 | CH30: =IF(CF30=0,0,CF30+1) -> 0 | CI30: =IF(CJ30="","",1/(CJ30+0.01)) | CJ30: =IF(CG30>0,ROUNDDOWN(('Diseño estructura &CP'!$AZ$5/CG30),0),"") | CL30: Lado 15 | CN30: metros | CP30: =IFERROR(IF(CM30="",0,ROUNDDOWN(('Diseño estructura &CP'!$AZ$6/CM30),0)),0) -> 0 | CX30: =+IF(CY30=0,"",CX29+1) | CY30: =+DA30/$H$9 -> 0 | CZ30: =ROUNDDOWN(DA30/$C$13,0) -> 0 | DB30: =IF(CZ30=0,0,CZ30+1) -> 0 | DC30: =IF(DD30="","",1/(DD30+0.01)) | DD30: =IF(DA30>0,ROUNDDOWN(('Diseño estructura &CP'!$AZ$5/DA30),0),"") | DF30: Lado 15 | DH30: metros | DJ30: =IFERROR(IF(DG30="",0,ROUNDDOWN(('Diseño estructura &CP'!$AZ$6/DG30),0)),0) -> 0 | DR30: =+IF(DS30=0,"",DR29+1) | DS30: =+DU30/$H$9 -> 0 | DT30: =ROUNDDOWN(DU30/$C$13,0) -> 0 | DV30: =IF(DT30=0,0,DT30+1) -> 0 | DW30: =IF(DX30="","",1/(DX30+0.01)) | DX30: =IF(DU30>0,ROUNDDOWN(('Diseño estructura &CP'!$AZ$5/DU30),0),"") | DZ30: Lado 15 | EB30: metros | ED30: =IFERROR(IF(EA30="",0,ROUNDDOWN(('Diseño estructura &CP'!$AZ$6/EA30),0)),0) -> 0 | EL30: =+IF(EM30=0,"",EL29+1) | EM30: =+EO30/$H$9 -> 0 | EN30: =ROUNDDOWN(EO30/$C$13,0) -> 0 | EP30: =IF(EN30=0,0,EN30+1) -> 0 | EQ30: =IF(ER30="","",1/(ER30+0.01)) | ER30: =IF(EO30>0,ROUNDDOWN(('Diseño estructura &CP'!$AZ$5/EO30),0),"") | ET30: Lado 15 | EV30: metros | EX30: =IFERROR(IF(EU30="",0,ROUNDDOWN(('Diseño estructura &CP'!$AZ$6/EU30),0)),0) -> 0 | FF30: =+IF(FG30=0,"",FF29+1) | FG30: =+FI30/$H$9 -> 0 | FH30: =ROUNDDOWN(FI30/$C$13,0) -> 0 | FJ30: =IF(FH30=0,0,FH30+1) -> 0 | FK30: =IF(FL30="","",1/(FL30+0.01)) | FL30: =IF(FI30>0,ROUNDDOWN(('Diseño estructura &CP'!$AZ$5/FI30),0),"") | FN30: Lado 15 | FP30: metros | FR30: =IFERROR(IF(FO30="",0,ROUNDDOWN(('Diseño estructura &CP'!$AZ$6/FO30),0)),0) -> 0 | FZ30: =+IF(GA30=0,"",FZ29+1) | GA30: =+GC30/$H$9 -> 0 | GB30: =ROUNDDOWN(GC30/$C$13,0) -> 0 | GD30: =IF(GB30=0,0,GB30+1) -> 0 | GE30: =IF(GF30="","",1/(GF30+0.01)) | GF30: =IF(GC30>0,ROUNDDOWN(('Diseño estructura &CP'!$AZ$5/GC30),0),"") | GH30: Lado 15 | GJ30: metros | GL30: =IFERROR(IF(GI30="",0,ROUNDDOWN(('Diseño estructura &CP'!$AZ$6/GI30),0)),0) -> 0
B31: =+IF(C31=0,"",B30+1) -> 16 | C31: =+E31/$H$9 -> 32 | D31: =ROUNDDOWN(E31/$C$13,0) -> 5 | E31: 64 | F31: =IF(D31=0,0,D31+1) -> 6 | G31: =IF(H31="","",1/(H31+0.01)) -> 0.066622252 | H31: =IF(E31>0,ROUNDDOWN(('Diseño estructura &CP'!$AZ$5/E31),0),"") -> 15 | J31: Lado 16 | L31: metros | N31: =IFERROR(IF(K31="",0,ROUNDDOWN(('Diseño estructura &CP'!$AZ$6/K31),0)),0) -> 0 | P31: T16 | Q31: =IF(H$11="SI",B$14,"") -> 106 | R31: =IF(Q31="","",Q31*$R$15) -> 424 | S31: =1/(T31+0.01) -> 0.99009901 | T31: =IFERROR(ROUNDDOWN(('Diseño estructura &CP'!$AZ$8/R31),0),0) -> 1 | V31: =+IF(W31=0,"",V30+1) -> 16 | W31: =+Y31/$H$9 -> 90.5 | X31: =ROUNDDOWN(Y31/$C$13,0) -> 15 | Y31: 181 | Z31: =IF(X31=0,0,X31+1) -> 16 | AA31: =IF(AB31="","",1/(AB31+0.01)) -> 0.1996008 | AB31: =IF(Y31>0,ROUNDDOWN(('Diseño estructura &CP'!$AZ$5/Y31),0),"") -> 5 | AD31: Lado 16 | AF31: metros | AH31: =IFERROR(IF(AE31="",0,ROUNDDOWN(('Diseño estructura &CP'!$AZ$6/AE31),0)),0) -> 0 | AJ31: T16 | AK31: =IF(AB$11="SI",V$14,"") -> 55 | AL31: =IF(AK31="","",AK31*$R$15) -> 220 | AM31: =1/(AN31+0.01) -> 0.49751244 | AN31: =IFERROR(ROUNDDOWN(('Diseño estructura &CP'!$AZ$8/AL31),0),0) -> 2 | AP31: =+IF(AQ31=0,"",AP30+1) -> 16 | AQ31: =+AS31/$H$9 -> 81.5 | AR31: =ROUNDDOWN(AS31/$C$13,0) -> 13 | AS31: 163 | AT31: =IF(AR31=0,0,AR31+1) -> 14 | AU31: =IF(AV31="","",1/(AV31+0.01)) -> 0.16638935 | AV31: =IF(AS31>0,ROUNDDOWN(('Diseño estructura &CP'!$AZ$5/AS31),0),"") -> 6 | AX31: Lado 16 | AZ31: metros | BB31: =IFERROR(IF(AY31="",0,ROUNDDOWN(('Diseño estructura &CP'!$AZ$6/AY31),0)),0) -> 0 | BJ31: =+IF(BK31=0,"",BJ30+1) -> 16 | BK31: =+BM31/$H$9 -> 78.25 | BL31: =ROUNDDOWN(BM31/$BK$13,0) -> 14 | BM31: 156.5 | BN31: =IF(BL31=0,0,BL31+1) -> 15 | BO31: =IF(BP31="","",1/(BP31+0.01)) -> 0.16638935 | BP31: =IF(BM31>0,ROUNDDOWN(('Diseño estructura &CP'!$AZ$5/BM31),0),"") -> 6 | BR31: Lado 16 | BT31: metros | BV31: =IFERROR(IF(BS31="",0,ROUNDDOWN(('Diseño estructura &CP'!$AZ$6/BS31),0)),0) -> 0 | BX31: T16 | BY31: =IF(BP$11="SI",BJ$14,"") -> 30 | BZ31: =IF(BY31="","",BY31*$R$15) -> 120 | CA31: =1/(CB31+0.01) -> 0.24937656 | CB31: =IFERROR(ROUNDDOWN(('Diseño estructura &CP'!$AZ$8/BZ31),0),0) -> 4 | CD31: =+IF(CE31=0,"",CD30+1) | CE31: =+CG31/$H$9 -> 0 | CF31: =ROUNDDOWN(CG31/$C$13,0) -> 0 | CH31: =IF(CF31=0,0,CF31+1) -> 0 | CI31: =IF(CJ31="","",1/(CJ31+0.01)) | CJ31: =IF(CG31>0,ROUNDDOWN(('Diseño estructura &CP'!$AZ$5/CG31),0),"") | CL31: Lado 16 | CN31: metros | CP31: =IFERROR(IF(CM31="",0,ROUNDDOWN(('Diseño estructura &CP'!$AZ$6/CM31),0)),0) -> 0 | CX31: =+IF(CY31=0,"",CX30+1) | CY31: =+DA31/$H$9 -> 0 | CZ31: =ROUNDDOWN(DA31/$C$13,0) -> 0 | DB31: =IF(CZ31=0,0,CZ31+1) -> 0 | DC31: =IF(DD31="","",1/(DD31+0.01)) | DD31: =IF(DA31>0,ROUNDDOWN(('Diseño estructura &CP'!$AZ$5/DA31),0),"") | DF31: Lado 16 | DH31: metros | DJ31: =IFERROR(IF(DG31="",0,ROUNDDOWN(('Diseño estructura &CP'!$AZ$6/DG31),0)),0) -> 0 | DR31: =+IF(DS31=0,"",DR30+1) | DS31: =+DU31/$H$9 -> 0 | DT31: =ROUNDDOWN(DU31/$C$13,0) -> 0 | DV31: =IF(DT31=0,0,DT31+1) -> 0 | DW31: =IF(DX31="","",1/(DX31+0.01)) | DX31: =IF(DU31>0,ROUNDDOWN(('Diseño estructura &CP'!$AZ$5/DU31),0),"") | DZ31: Lado 16 | EB31: metros | ED31: =IFERROR(IF(EA31="",0,ROUNDDOWN(('Diseño estructura &CP'!$AZ$6/EA31),0)),0) -> 0 | EL31: =+IF(EM31=0,"",EL30+1) | EM31: =+EO31/$H$9 -> 0 | EN31: =ROUNDDOWN(EO31/$C$13,0) -> 0 | EP31: =IF(EN31=0,0,EN31+1) -> 0 | EQ31: =IF(ER31="","",1/(ER31+0.01)) | ER31: =IF(EO31>0,ROUNDDOWN(('Diseño estructura &CP'!$AZ$5/EO31),0),"") | ET31: Lado 16 | EV31: metros | EX31: =IFERROR(IF(EU31="",0,ROUNDDOWN(('Diseño estructura &CP'!$AZ$6/EU31),0)),0) -> 0 | FF31: =+IF(FG31=0,"",FF30+1) | FG31: =+FI31/$H$9 -> 0 | FH31: =ROUNDDOWN(FI31/$C$13,0) -> 0 | FJ31: =IF(FH31=0,0,FH31+1) -> 0 | FK31: =IF(FL31="","",1/(FL31+0.01)) | FL31: =IF(FI31>0,ROUNDDOWN(('Diseño estructura &CP'!$AZ$5/FI31),0),"") | FN31: Lado 16 | FP31: metros | FR31: =IFERROR(IF(FO31="",0,ROUNDDOWN(('Diseño estructura &CP'!$AZ$6/FO31),0)),0) -> 0 | FZ31: =+IF(GA31=0,"",FZ30+1) | GA31: =+GC31/$H$9 -> 0 | GB31: =ROUNDDOWN(GC31/$C$13,0) -> 0 | GD31: =IF(GB31=0,0,GB31+1) -> 0 | GE31: =IF(GF31="","",1/(GF31+0.01)) | GF31: =IF(GC31>0,ROUNDDOWN(('Diseño estructura &CP'!$AZ$5/GC31),0),"") | GH31: Lado 16 | GJ31: metros | GL31: =IFERROR(IF(GI31="",0,ROUNDDOWN(('Diseño estructura &CP'!$AZ$6/GI31),0)),0) -> 0
B32: =+IF(C32=0,"",B31+1) -> 17 | C32: =+E32/$H$9 -> 33.5 | D32: =ROUNDDOWN(E32/$C$13,0) -> 5 | E32: 67 | F32: =IF(D32=0,0,D32+1) -> 6 | G32: =IF(H32="","",1/(H32+0.01)) -> 0.071377587 | H32: =IF(E32>0,ROUNDDOWN(('Diseño estructura &CP'!$AZ$5/E32),0),"") -> 14 | J32: Lado 17 | L32: metros | N32: =IFERROR(IF(K32="",0,ROUNDDOWN(('Diseño estructura &CP'!$AZ$6/K32),0)),0) -> 0 | P32: T17 | Q32: =IF(H$11="SI",B$14,"") -> 106 | R32: =IF(Q32="","",Q32*$R$15) -> 424 | S32: =1/(T32+0.01) -> 0.99009901 | T32: =IFERROR(ROUNDDOWN(('Diseño estructura &CP'!$AZ$8/R32),0),0) -> 1 | V32: =+IF(W32=0,"",V31+1) -> 17 | W32: =+Y32/$H$9 -> 91 | X32: =ROUNDDOWN(Y32/$C$13,0) -> 15 | Y32: 182 | Z32: =IF(X32=0,0,X32+1) -> 16 | AA32: =IF(AB32="","",1/(AB32+0.01)) -> 0.1996008 | AB32: =IF(Y32>0,ROUNDDOWN(('Diseño estructura &CP'!$AZ$5/Y32),0),"") -> 5 | AD32: Lado 17 | AF32: metros | AH32: =IFERROR(IF(AE32="",0,ROUNDDOWN(('Diseño estructura &CP'!$AZ$6/AE32),0)),0) -> 0 | AP32: =+IF(AQ32=0,"",AP31+1) -> 17 | AQ32: =+AS32/$H$9 -> 81.5 | AR32: =ROUNDDOWN(AS32/$C$13,0) -> 13 | AS32: 163 | AT32: =IF(AR32=0,0,AR32+1) -> 14 | AU32: =IF(AV32="","",1/(AV32+0.01)) -> 0.16638935 | AV32: =IF(AS32>0,ROUNDDOWN(('Diseño estructura &CP'!$AZ$5/AS32),0),"") -> 6 | AX32: Lado 17 | AZ32: metros | BB32: =IFERROR(IF(AY32="",0,ROUNDDOWN(('Diseño estructura &CP'!$AZ$6/AY32),0)),0) -> 0 | BJ32: =+IF(BK32=0,"",BJ31+1) -> 17 | BK32: =+BM32/$H$9 -> 73.25 | BL32: =ROUNDDOWN(BM32/$BK$13,0) -> 13 | BM32: 146.5 | BN32: =IF(BL32=0,0,BL32+1) -> 14 | BO32: =IF(BP32="","",1/(BP32+0.01)) -> 0.16638935 | BP32: =IF(BM32>0,ROUNDDOWN(('Diseño estructura &CP'!$AZ$5/BM32),0),"") -> 6 | BR32: Lado 17 | BT32: metros | BV32: =IFERROR(IF(BS32="",0,ROUNDDOWN(('Diseño estructura &CP'!$AZ$6/BS32),0)),0) -> 0 | BX32: T17 | BY32: =IF(BP$11="SI",BJ$14,"") -> 30 | BZ32: =IF(BY32="","",BY32*$R$15) -> 120 | CA32: =1/(CB32+0.01) -> 0.24937656 | CB32: =IFERROR(ROUNDDOWN(('Diseño estructura &CP'!$AZ$8/BZ32),0),0) -> 4 | CD32: =+IF(CE32=0,"",CD31+1) | CE32: =+CG32/$H$9 -> 0 | CF32: =ROUNDDOWN(CG32/$C$13,0) -> 0 | CH32: =IF(CF32=0,0,CF32+1) -> 0 | CI32: =IF(CJ32="","",1/(CJ32+0.01)) | CJ32: =IF(CG32>0,ROUNDDOWN(('Diseño estructura &CP'!$AZ$5/CG32),0),"") | CL32: Lado 17 | CN32: metros | CP32: =IFERROR(IF(CM32="",0,ROUNDDOWN(('Diseño estructura &CP'!$AZ$6/CM32),0)),0) -> 0 | CX32: =+IF(CY32=0,"",CX31+1) | CY32: =+DA32/$H$9 -> 0 | CZ32: =ROUNDDOWN(DA32/$C$13,0) -> 0 | DB32: =IF(CZ32=0,0,CZ32+1) -> 0 | DC32: =IF(DD32="","",1/(DD32+0.01)) | DD32: =IF(DA32>0,ROUNDDOWN(('Diseño estructura &CP'!$AZ$5/DA32),0),"") | DF32: Lado 17 | DH32: metros | DJ32: =IFERROR(IF(DG32="",0,ROUNDDOWN(('Diseño estructura &CP'!$AZ$6/DG32),0)),0) -> 0 | DR32: =+IF(DS32=0,"",DR31+1) | DS32: =+DU32/$H$9 -> 0 | DT32: =ROUNDDOWN(DU32/$C$13,0) -> 0 | DV32: =IF(DT32=0,0,DT32+1) -> 0 | DW32: =IF(DX32="","",1/(DX32+0.01)) | DX32: =IF(DU32>0,ROUNDDOWN(('Diseño estructura &CP'!$AZ$5/DU32),0),"") | DZ32: Lado 17 | EB32: metros | ED32: =IFERROR(IF(EA32="",0,ROUNDDOWN(('Diseño estructura &CP'!$AZ$6/EA32),0)),0) -> 0 | EL32: =+IF(EM32=0,"",EL31+1) | EM32: =+EO32/$H$9 -> 0 | EN32: =ROUNDDOWN(EO32/$C$13,0) -> 0 | EP32: =IF(EN32=0,0,EN32+1) -> 0 | EQ32: =IF(ER32="","",1/(ER32+0.01)) | ER32: =IF(EO32>0,ROUNDDOWN(('Diseño estructura &CP'!$AZ$5/EO32),0),"") | ET32: Lado 17 | EV32: metros | EX32: =IFERROR(IF(EU32="",0,ROUNDDOWN(('Diseño estructura &CP'!$AZ$6/EU32),0)),0) -> 0 | FF32: =+IF(FG32=0,"",FF31+1) | FG32: =+FI32/$H$9 -> 0 | FH32: =ROUNDDOWN(FI32/$C$13,0) -> 0 | FJ32: =IF(FH32=0,0,FH32+1) -> 0 | FK32: =IF(FL32="","",1/(FL32+0.01)) | FL32: =IF(FI32>0,ROUNDDOWN(('Diseño estructura &CP'!$AZ$5/FI32),0),"") | FN32: Lado 17 | FP32: metros | FR32: =IFERROR(IF(FO32="",0,ROUNDDOWN(('Diseño estructura &CP'!$AZ$6/FO32),0)),0) -> 0 | FZ32: =+IF(GA32=0,"",FZ31+1) | GA32: =+GC32/$H$9 -> 0 | GB32: =ROUNDDOWN(GC32/$C$13,0) -> 0 | GD32: =IF(GB32=0,0,GB32+1) -> 0 | GE32: =IF(GF32="","",1/(GF32+0.01)) | GF32: =IF(GC32>0,ROUNDDOWN(('Diseño estructura &CP'!$AZ$5/GC32),0),"") | GH32: Lado 17 | GJ32: metros | GL32: =IFERROR(IF(GI32="",0,ROUNDDOWN(('Diseño estructura &CP'!$AZ$6/GI32),0)),0) -> 0
B33: =+IF(C33=0,"",B32+1) -> 18 | C33: =+E33/$H$9 -> 34 | D33: =ROUNDDOWN(E33/$C$13,0) -> 5 | E33: 68 | F33: =IF(D33=0,0,D33+1) -> 6 | G33: =IF(H33="","",1/(H33+0.01)) -> 0.071377587 | H33: =IF(E33>0,ROUNDDOWN(('Diseño estructura &CP'!$AZ$5/E33),0),"") -> 14 | J33: Lado 18 | L33: metros | N33: =IFERROR(IF(K33="",0,ROUNDDOWN(('Diseño estructura &CP'!$AZ$6/K33),0)),0) -> 0 | P33: T18 | Q33: =IF(H$11="SI",B$14,"") -> 106 | R33: =IF(Q33="","",Q33*$R$15) -> 424 | S33: =1/(T33+0.01) -> 0.99009901 | T33: =IFERROR(ROUNDDOWN(('Diseño estructura &CP'!$AZ$8/R33),0),0) -> 1 | V33: =+IF(W33=0,"",V32+1) -> 18 | W33: =+Y33/$H$9 -> 92 | X33: =ROUNDDOWN(Y33/$C$13,0) -> 15 | Y33: 184 | Z33: =IF(X33=0,0,X33+1) -> 16 | AA33: =IF(AB33="","",1/(AB33+0.01)) -> 0.1996008 | AB33: =IF(Y33>0,ROUNDDOWN(('Diseño estructura &CP'!$AZ$5/Y33),0),"") -> 5 | AD33: Lado 18 | AF33: metros | AH33: =IFERROR(IF(AE33="",0,ROUNDDOWN(('Diseño estructura &CP'!$AZ$6/AE33),0)),0) -> 0 | AP33: =+IF(AQ33=0,"",AP32+1) -> 18 | AQ33: =+AS33/$H$9 -> 81.5 | AR33: =ROUNDDOWN(AS33/$C$13,0) -> 13 | AS33: 163 | AT33: =IF(AR33=0,0,AR33+1) -> 14 | AU33: =IF(AV33="","",1/(AV33+0.01)) -> 0.16638935 | AV33: =IF(AS33>0,ROUNDDOWN(('Diseño estructura &CP'!$AZ$5/AS33),0),"") -> 6 | AX33: Lado 18 | AZ33: metros | BB33: =IFERROR(IF(AY33="",0,ROUNDDOWN(('Diseño estructura &CP'!$AZ$6/AY33),0)),0) -> 0 | BJ33: =+IF(BK33=0,"",BJ32+1) -> 18 | BK33: =+BM33/$H$9 -> 67 | BL33: =ROUNDDOWN(BM33/$BK$13,0) -> 12 | BM33: 134 | BN33: =IF(BL33=0,0,BL33+1) -> 13 | BO33: =IF(BP33="","",1/(BP33+0.01)) -> 0.14265335 | BP33: =IF(BM33>0,ROUNDDOWN(('Diseño estructura &CP'!$AZ$5/BM33),0),"") -> 7 | BR33: Lado 18 | BT33: metros | BV33: =IFERROR(IF(BS33="",0,ROUNDDOWN(('Diseño estructura &CP'!$AZ$6/BS33),0)),0) -> 0 | BX33: T18 | BY33: =IF(BP$11="SI",BJ$14,"") -> 30 | BZ33: =IF(BY33="","",BY33*$R$15) -> 120 | CA33: =1/(CB33+0.01) -> 0.24937656 | CB33: =IFERROR(ROUNDDOWN(('Diseño estructura &CP'!$AZ$8/BZ33),0),0) -> 4 | CD33: =+IF(CE33=0,"",CD32+1) | CE33: =+CG33/$H$9 -> 0 | CF33: =ROUNDDOWN(CG33/$C$13,0) -> 0 | CH33: =IF(CF33=0,0,CF33+1) -> 0 | CI33: =IF(CJ33="","",1/(CJ33+0.01)) | CJ33: =IF(CG33>0,ROUNDDOWN(('Diseño estructura &CP'!$AZ$5/CG33),0),"") | CL33: Lado 18 | CN33: metros | CP33: =IFERROR(IF(CM33="",0,ROUNDDOWN(('Diseño estructura &CP'!$AZ$6/CM33),0)),0) -> 0 | CX33: =+IF(CY33=0,"",CX32+1) | CY33: =+DA33/$H$9 -> 0 | CZ33: =ROUNDDOWN(DA33/$C$13,0) -> 0 | DB33: =IF(CZ33=0,0,CZ33+1) -> 0 | DC33: =IF(DD33="","",1/(DD33+0.01)) | DD33: =IF(DA33>0,ROUNDDOWN(('Diseño estructura &CP'!$AZ$5/DA33),0),"") | DF33: Lado 18 | DH33: metros | DJ33: =IFERROR(IF(DG33="",0,ROUNDDOWN(('Diseño estructura &CP'!$AZ$6/DG33),0)),0) -> 0 | DR33: =+IF(DS33=0,"",DR32+1) | DS33: =+DU33/$H$9 -> 0 | DT33: =ROUNDDOWN(DU33/$C$13,0) -> 0 | DV33: =IF(DT33=0,0,DT33+1) -> 0 | DW33: =IF(DX33="","",1/(DX33+0.01)) | DX33: =IF(DU33>0,ROUNDDOWN(('Diseño estructura &CP'!$AZ$5/DU33),0),"") | DZ33: Lado 18 | EB33: metros | ED33: =IFERROR(IF(EA33="",0,ROUNDDOWN(('Diseño estructura &CP'!$AZ$6/EA33),0)),0) -> 0 | EL33: =+IF(EM33=0,"",EL32+1) | EM33: =+EO33/$H$9 -> 0 | EN33: =ROUNDDOWN(EO33/$C$13,0) -> 0 | EP33: =IF(EN33=0,0,EN33+1) -> 0 | EQ33: =IF(ER33="","",1/(ER33+0.01)) | ER33: =IF(EO33>0,ROUNDDOWN(('Diseño estructura &CP'!$AZ$5/EO33),0),"") | ET33: Lado 18 | EV33: metros | EX33: =IFERROR(IF(EU33="",0,ROUNDDOWN(('Diseño estructura &CP'!$AZ$6/EU33),0)),0) -> 0 | FF33: =+IF(FG33=0,"",FF32+1) | FG33: =+FI33/$H$9 -> 0 | FH33: =ROUNDDOWN(FI33/$C$13,0) -> 0 | FJ33: =IF(FH33=0,0,FH33+1) -> 0 | FK33: =IF(FL33="","",1/(FL33+0.01)) | FL33: =IF(FI33>0,ROUNDDOWN(('Diseño estructura &CP'!$AZ$5/FI33),0),"") | FN33: Lado 18 | FP33: metros | FR33: =IFERROR(IF(FO33="",0,ROUNDDOWN(('Diseño estructura &CP'!$AZ$6/FO33),0)),0) -> 0 | FZ33: =+IF(GA33=0,"",FZ32+1) | GA33: =+GC33/$H$9 -> 0 | GB33: =ROUNDDOWN(GC33/$C$13,0) -> 0 | GD33: =IF(GB33=0,0,GB33+1) -> 0 | GE33: =IF(GF33="","",1/(GF33+0.01)) | GF33: =IF(GC33>0,ROUNDDOWN(('Diseño estructura &CP'!$AZ$5/GC33),0),"") | GH33: Lado 18 | GJ33: metros | GL33: =IFERROR(IF(GI33="",0,ROUNDDOWN(('Diseño estructura &CP'!$AZ$6/GI33),0)),0) -> 0
B34: =+IF(C34=0,"",B33+1) -> 19 | C34: =+E34/$H$9 -> 34.5 | D34: =ROUNDDOWN(E34/$C$13,0) -> 5 | E34: 69 | F34: =IF(D34=0,0,D34+1) -> 6 | G34: =IF(H34="","",1/(H34+0.01)) -> 0.071377587 | H34: =IF(E34>0,ROUNDDOWN(('Diseño estructura &CP'!$AZ$5/E34),0),"") -> 14 | J34: Lado 19 | L34: metros | N34: =IFERROR(IF(K34="",0,ROUNDDOWN(('Diseño estructura &CP'!$AZ$6/K34),0)),0) -> 0 | P34: T19 | Q34: =IF(H$11="SI",B$14,"") -> 106 | R34: =IF(Q34="","",Q34*$R$15) -> 424 | S34: =1/(T34+0.01) -> 0.99009901 | T34: =IFERROR(ROUNDDOWN(('Diseño estructura &CP'!$AZ$8/R34),0),0) -> 1 | V34: =+IF(W34=0,"",V33+1) -> 19 | W34: =+Y34/$H$9 -> 92.75 | X34: =ROUNDDOWN(Y34/$C$13,0) -> 15 | Y34: 185.5 | Z34: =IF(X34=0,0,X34+1) -> 16 | AA34: =IF(AB34="","",1/(AB34+0.01)) -> 0.1996008 | AB34: =IF(Y34>0,ROUNDDOWN(('Diseño estructura &CP'!$AZ$5/Y34),0),"") -> 5 | AD34: Lado 19 | AF34: metros | AH34: =IFERROR(IF(AE34="",0,ROUNDDOWN(('Diseño estructura &CP'!$AZ$6/AE34),0)),0) -> 0 | AP34: =+IF(AQ34=0,"",AP33+1) -> 19 | AQ34: =+AS34/$H$9 -> 81.5 | AR34: =ROUNDDOWN(AS34/$C$13,0) -> 13 | AS34: 163 | AT34: =IF(AR34=0,0,AR34+1) -> 14 | AU34: =IF(AV34="","",1/(AV34+0.01)) -> 0.16638935 | AV34: =IF(AS34>0,ROUNDDOWN(('Diseño estructura &CP'!$AZ$5/AS34),0),"") -> 6 | AX34: Lado 19 | AZ34: metros | BB34: =IFERROR(IF(AY34="",0,ROUNDDOWN(('Diseño estructura &CP'!$AZ$6/AY34),0)),0) -> 0 | BJ34: =+IF(BK34=0,"",BJ33+1) -> 19 | BK34: =+BM34/$H$9 -> 62.5 | BL34: =ROUNDDOWN(BM34/$BK$13,0) -> 11 | BM34: 125 | BN34: =IF(BL34=0,0,BL34+1) -> 12 | BO34: =IF(BP34="","",1/(BP34+0.01)) -> 0.12484395 | BP34: =IF(BM34>0,ROUNDDOWN(('Diseño estructura &CP'!$AZ$5/BM34),0),"") -> 8 | BR34: Lado 19 | BT34: metros | BV34: =IFERROR(IF(BS34="",0,ROUNDDOWN(('Diseño estructura &CP'!$AZ$6/BS34),0)),0) -> 0 | CD34: =+IF(CE34=0,"",CD33+1) | CE34: =+CG34/$H$9 -> 0 | CF34: =ROUNDDOWN(CG34/$C$13,0) -> 0 | CH34: =IF(CF34=0,0,CF34+1) -> 0 | CI34: =IF(CJ34="","",1/(CJ34+0.01)) | CJ34: =IF(CG34>0,ROUNDDOWN(('Diseño estructura &CP'!$AZ$5/CG34),0),"") | CL34: Lado 19 | CN34: metros | CP34: =IFERROR(IF(CM34="",0,ROUNDDOWN(('Diseño estructura &CP'!$AZ$6/CM34),0)),0) -> 0 | CX34: =+IF(CY34=0,"",CX33+1) | CY34: =+DA34/$H$9 -> 0 | CZ34: =ROUNDDOWN(DA34/$C$13,0) -> 0 | DB34: =IF(CZ34=0,0,CZ34+1) -> 0 | DC34: =IF(DD34="","",1/(DD34+0.01)) | DD34: =IF(DA34>0,ROUNDDOWN(('Diseño estructura &CP'!$AZ$5/DA34),0),"") | DF34: Lado 19 | DH34: metros | DJ34: =IFERROR(IF(DG34="",0,ROUNDDOWN(('Diseño estructura &CP'!$AZ$6/DG34),0)),0) -> 0 | DR34: =+IF(DS34=0,"",DR33+1) | DS34: =+DU34/$H$9 -> 0 | DT34: =ROUNDDOWN(DU34/$C$13,0) -> 0 | DV34: =IF(DT34=0,0,DT34+1) -> 0 | DW34: =IF(DX34="","",1/(DX34+0.01)) | DX34: =IF(DU34>0,ROUNDDOWN(('Diseño estructura &CP'!$AZ$5/DU34),0),"") | DZ34: Lado 19 | EB34: metros | ED34: =IFERROR(IF(EA34="",0,ROUNDDOWN(('Diseño estructura &CP'!$AZ$6/EA34),0)),0) -> 0 | EL34: =+IF(EM34=0,"",EL33+1) | EM34: =+EO34/$H$9 -> 0 | EN34: =ROUNDDOWN(EO34/$C$13,0) -> 0 | EP34: =IF(EN34=0,0,EN34+1) -> 0 | EQ34: =IF(ER34="","",1/(ER34+0.01)) | ER34: =IF(EO34>0,ROUNDDOWN(('Diseño estructura &CP'!$AZ$5/EO34),0),"") | ET34: Lado 19 | EV34: metros | EX34: =IFERROR(IF(EU34="",0,ROUNDDOWN(('Diseño estructura &CP'!$AZ$6/EU34),0)),0) -> 0 | FF34: =+IF(FG34=0,"",FF33+1) | FG34: =+FI34/$H$9 -> 0 | FH34: =ROUNDDOWN(FI34/$C$13,0) -> 0 | FJ34: =IF(FH34=0,0,FH34+1) -> 0 | FK34: =IF(FL34="","",1/(FL34+0.01)) | FL34: =IF(FI34>0,ROUNDDOWN(('Diseño estructura &CP'!$AZ$5/FI34),0),"") | FN34: Lado 19 | FP34: metros | FR34: =IFERROR(IF(FO34="",0,ROUNDDOWN(('Diseño estructura &CP'!$AZ$6/FO34),0)),0) -> 0 | FZ34: =+IF(GA34=0,"",FZ33+1) | GA34: =+GC34/$H$9 -> 0 | GB34: =ROUNDDOWN(GC34/$C$13,0) -> 0 | GD34: =IF(GB34=0,0,GB34+1) -> 0 | GE34: =IF(GF34="","",1/(GF34+0.01)) | GF34: =IF(GC34>0,ROUNDDOWN(('Diseño estructura &CP'!$AZ$5/GC34),0),"") | GH34: Lado 19 | GJ34: metros | GL34: =IFERROR(IF(GI34="",0,ROUNDDOWN(('Diseño estructura &CP'!$AZ$6/GI34),0)),0) -> 0
B35: =+IF(C35=0,"",B34+1) -> 20 | C35: =+E35/$H$9 -> 35.5 | D35: =ROUNDDOWN(E35/$C$13,0) -> 5 | E35: 71 | F35: =IF(D35=0,0,D35+1) -> 6 | G35: =IF(H35="","",1/(H35+0.01)) -> 0.071377587 | H35: =IF(E35>0,ROUNDDOWN(('Diseño estructura &CP'!$AZ$5/E35),0),"") -> 14 | J35: Lado 20 | L35: metros | N35: =IFERROR(IF(K35="",0,ROUNDDOWN(('Diseño estructura &CP'!$AZ$6/K35),0)),0) -> 0 | P35: T20 | Q35: =IF(H$11="SI",B$14,"") -> 106 | R35: =IF(Q35="","",Q35*$R$15) -> 424 | S35: =1/(T35+0.01) -> 0.99009901 | T35: =IFERROR(ROUNDDOWN(('Diseño estructura &CP'!$AZ$8/R35),0),0) -> 1 | V35: =+IF(W35=0,"",V34+1) -> 20 | W35: =+Y35/$H$9 -> 93.25 | X35: =ROUNDDOWN(Y35/$C$13,0) -> 15 | Y35: 186.5 | Z35: =IF(X35=0,0,X35+1) -> 16 | AA35: =IF(AB35="","",1/(AB35+0.01)) -> 0.1996008 | AB35: =IF(Y35>0,ROUNDDOWN(('Diseño estructura &CP'!$AZ$5/Y35),0),"") -> 5 | AD35: Lado 20 | AF35: metros | AH35: =IFERROR(IF(AE35="",0,ROUNDDOWN(('Diseño estructura &CP'!$AZ$6/AE35),0)),0) -> 0 | AP35: =+IF(AQ35=0,"",AP34+1) -> 20 | AQ35: =+AS35/$H$9 -> 81.5 | AR35: =ROUNDDOWN(AS35/$C$13,0) -> 13 | AS35: 163 | AT35: =IF(AR35=0,0,AR35+1) -> 14 | AU35: =IF(AV35="","",1/(AV35+0.01)) -> 0.16638935 | AV35: =IF(AS35>0,ROUNDDOWN(('Diseño estructura &CP'!$AZ$5/AS35),0),"") -> 6 | AX35: Lado 20 | AZ35: metros | BB35: =IFERROR(IF(AY35="",0,ROUNDDOWN(('Diseño estructura &CP'!$AZ$6/AY35),0)),0) -> 0 | BJ35: =+IF(BK35=0,"",BJ34+1) -> 20 | BK35: =+BM35/$H$9 -> 55.75 | BL35: =ROUNDDOWN(BM35/$BK$13,0) -> 10 | BM35: 111.5 | BN35: =IF(BL35=0,0,BL35+1) -> 11 | BO35: =IF(BP35="","",1/(BP35+0.01)) -> 0.12484395 | BP35: =IF(BM35>0,ROUNDDOWN(('Diseño estructura &CP'!$AZ$5/BM35),0),"") -> 8 | BR35: Lado 20 | BT35: metros | BV35: =IFERROR(IF(BS35="",0,ROUNDDOWN(('Diseño estructura &CP'!$AZ$6/BS35),0)),0) -> 0 | CD35: =+IF(CE35=0,"",CD34+1) | CE35: =+CG35/$H$9 -> 0 | CF35: =ROUNDDOWN(CG35/$C$13,0) -> 0 | CH35: =IF(CF35=0,0,CF35+1) -> 0 | CI35: =IF(CJ35="","",1/(CJ35+0.01)) | CJ35: =IF(CG35>0,ROUNDDOWN(('Diseño estructura &CP'!$AZ$5/CG35),0),"") | CL35: Lado 20 | CN35: metros | CP35: =IFERROR(IF(CM35="",0,ROUNDDOWN(('Diseño estructura &CP'!$AZ$6/CM35),0)),0) -> 0 | CX35: =+IF(CY35=0,"",CX34+1) | CY35: =+DA35/$H$9 -> 0 | CZ35: =ROUNDDOWN(DA35/$C$13,0) -> 0 | DB35: =IF(CZ35=0,0,CZ35+1) -> 0 | DC35: =IF(DD35="","",1/(DD35+0.01)) | DD35: =IF(DA35>0,ROUNDDOWN(('Diseño estructura &CP'!$AZ$5/DA35),0),"") | DF35: Lado 20 | DH35: metros | DJ35: =IFERROR(IF(DG35="",0,ROUNDDOWN(('Diseño estructura &CP'!$AZ$6/DG35),0)),0) -> 0 | DR35: =+IF(DS35=0,"",DR34+1) | DS35: =+DU35/$H$9 -> 0 | DT35: =ROUNDDOWN(DU35/$C$13,0) -> 0 | DV35: =IF(DT35=0,0,DT35+1) -> 0 | DW35: =IF(DX35="","",1/(DX35+0.01)) | DX35: =IF(DU35>0,ROUNDDOWN(('Diseño estructura &CP'!$AZ$5/DU35),0),"") | DZ35: Lado 20 | EB35: metros | ED35: =IFERROR(IF(EA35="",0,ROUNDDOWN(('Diseño estructura &CP'!$AZ$6/EA35),0)),0) -> 0 | EL35: =+IF(EM35=0,"",EL34+1) | EM35: =+EO35/$H$9 -> 0 | EN35: =ROUNDDOWN(EO35/$C$13,0) -> 0 | EP35: =IF(EN35=0,0,EN35+1) -> 0 | EQ35: =IF(ER35="","",1/(ER35+0.01)) | ER35: =IF(EO35>0,ROUNDDOWN(('Diseño estructura &CP'!$AZ$5/EO35),0),"") | ET35: Lado 20 | EV35: metros | EX35: =IFERROR(IF(EU35="",0,ROUNDDOWN(('Diseño estructura &CP'!$AZ$6/EU35),0)),0) -> 0 | FF35: =+IF(FG35=0,"",FF34+1) | FG35: =+FI35/$H$9 -> 0 | FH35: =ROUNDDOWN(FI35/$C$13,0) -> 0 | FJ35: =IF(FH35=0,0,FH35+1) -> 0 | FK35: =IF(FL35="","",1/(FL35+0.01)) | FL35: =IF(FI35>0,ROUNDDOWN(('Diseño estructura &CP'!$AZ$5/FI35),0),"") | FN35: Lado 20 | FP35: metros | FR35: =IFERROR(IF(FO35="",0,ROUNDDOWN(('Diseño estructura &CP'!$AZ$6/FO35),0)),0) -> 0 | FZ35: =+IF(GA35=0,"",FZ34+1) | GA35: =+GC35/$H$9 -> 0 | GB35: =ROUNDDOWN(GC35/$C$13,0) -> 0 | GD35: =IF(GB35=0,0,GB35+1) -> 0 | GE35: =IF(GF35="","",1/(GF35+0.01)) | GF35: =IF(GC35>0,ROUNDDOWN(('Diseño estructura &CP'!$AZ$5/GC35),0),"") | GH35: Lado 20 | GJ35: metros | GL35: =IFERROR(IF(GI35="",0,ROUNDDOWN(('Diseño estructura &CP'!$AZ$6/GI35),0)),0) -> 0
B36: =+IF(C36=0,"",B35+1) -> 21 | C36: =+E36/$H$9 -> 36.5 | D36: =ROUNDDOWN(E36/$C$13,0) -> 6 | E36: 73 | F36: =IF(D36=0,0,D36+1) -> 7 | G36: =IF(H36="","",1/(H36+0.01)) -> 0.076863951 | H36: =IF(E36>0,ROUNDDOWN(('Diseño estructura &CP'!$AZ$5/E36),0),"") -> 13 | J36: Lado 21 | L36: metros | N36: =IFERROR(IF(K36="",0,ROUNDDOWN(('Diseño estructura &CP'!$AZ$6/K36),0)),0) -> 0 | P36: T21 | Q36: =IF(H$11="SI",B$14,"") -> 106 | R36: =IF(Q36="","",Q36*$R$15) -> 424 | S36: =1/(T36+0.01) -> 0.99009901 | T36: =IFERROR(ROUNDDOWN(('Diseño estructura &CP'!$AZ$8/R36),0),0) -> 1 | V36: =+IF(W36=0,"",V35+1) -> 21 | W36: =+Y36/$H$9 -> 94 | X36: =ROUNDDOWN(Y36/$C$13,0) -> 15 | Y36: 188 | Z36: =IF(X36=0,0,X36+1) -> 16 | AA36: =IF(AB36="","",1/(AB36+0.01)) -> 0.1996008 | AB36: =IF(Y36>0,ROUNDDOWN(('Diseño estructura &CP'!$AZ$5/Y36),0),"") -> 5 | AD36: Lado 21 | AF36: metros | AH36: =IFERROR(IF(AE36="",0,ROUNDDOWN(('Diseño estructura &CP'!$AZ$6/AE36),0)),0) -> 0 | AP36: =+IF(AQ36=0,"",AP35+1) -> 21 | AQ36: =+AS36/$H$9 -> 81.5 | AR36: =ROUNDDOWN(AS36/$C$13,0) -> 13 | AS36: 163 | AT36: =IF(AR36=0,0,AR36+1) -> 14 | AU36: =IF(AV36="","",1/(AV36+0.01)) -> 0.16638935 | AV36: =IF(AS36>0,ROUNDDOWN(('Diseño estructura &CP'!$AZ$5/AS36),0),"") -> 6 | AX36: Lado 21 | AZ36: metros | BB36: =IFERROR(IF(AY36="",0,ROUNDDOWN(('Diseño estructura &CP'!$AZ$6/AY36),0)),0) -> 0 | BJ36: =+IF(BK36=0,"",BJ35+1) -> 21 | BK36: =+BM36/$H$9 -> 48.5 | BL36: =ROUNDDOWN(BM36/$BK$13,0) -> 8 | BM36: 97 | BN36: =IF(BL36=0,0,BL36+1) -> 9 | BO36: =IF(BP36="","",1/(BP36+0.01)) -> 0.0999001 | BP36: =IF(BM36>0,ROUNDDOWN(('Diseño estructura &CP'!$AZ$5/BM36),0),"") -> 10 | BR36: Lado 21 | BT36: metros | BV36: =IFERROR(IF(BS36="",0,ROUNDDOWN(('Diseño estructura &CP'!$AZ$6/BS36),0)),0) -> 0 | CD36: =+IF(CE36=0,"",CD35+1) | CE36: =+CG36/$H$9 -> 0 | CF36: =ROUNDDOWN(CG36/$C$13,0) -> 0 | CH36: =IF(CF36=0,0,CF36+1) -> 0 | CI36: =IF(CJ36="","",1/(CJ36+0.01)) | CJ36: =IF(CG36>0,ROUNDDOWN(('Diseño estructura &CP'!$AZ$5/CG36),0),"") | CL36: Lado 21 | CN36: metros | CP36: =IFERROR(IF(CM36="",0,ROUNDDOWN(('Diseño estructura &CP'!$AZ$6/CM36),0)),0) -> 0 | CX36: =+IF(CY36=0,"",CX35+1) | CY36: =+DA36/$H$9 -> 0 | CZ36: =ROUNDDOWN(DA36/$C$13,0) -> 0 | DB36: =IF(CZ36=0,0,CZ36+1) -> 0 | DC36: =IF(DD36="","",1/(DD36+0.01)) | DD36: =IF(DA36>0,ROUNDDOWN(('Diseño estructura &CP'!$AZ$5/DA36),0),"") | DF36: Lado 21 | DH36: metros | DJ36: =IFERROR(IF(DG36="",0,ROUNDDOWN(('Diseño estructura &CP'!$AZ$6/DG36),0)),0) -> 0 | DR36: =+IF(DS36=0,"",DR35+1) | DS36: =+DU36/$H$9 -> 0 | DT36: =ROUNDDOWN(DU36/$C$13,0) -> 0 | DV36: =IF(DT36=0,0,DT36+1) -> 0 | DW36: =IF(DX36="","",1/(DX36+0.01)) | DX36: =IF(DU36>0,ROUNDDOWN(('Diseño estructura &CP'!$AZ$5/DU36),0),"") | DZ36: Lado 21 | EB36: metros | ED36: =IFERROR(IF(EA36="",0,ROUNDDOWN(('Diseño estructura &CP'!$AZ$6/EA36),0)),0) -> 0 | EL36: =+IF(EM36=0,"",EL35+1) | EM36: =+EO36/$H$9 -> 0 | EN36: =ROUNDDOWN(EO36/$C$13,0) -> 0 | EP36: =IF(EN36=0,0,EN36+1) -> 0 | EQ36: =IF(ER36="","",1/(ER36+0.01)) | ER36: =IF(EO36>0,ROUNDDOWN(('Diseño estructura &CP'!$AZ$5/EO36),0),"") | ET36: Lado 21 | EV36: metros | EX36: =IFERROR(IF(EU36="",0,ROUNDDOWN(('Diseño estructura &CP'!$AZ$6/EU36),0)),0) -> 0 | FF36: =+IF(FG36=0,"",FF35+1) | FG36: =+FI36/$H$9 -> 0 | FH36: =ROUNDDOWN(FI36/$C$13,0) -> 0 | FJ36: =IF(FH36=0,0,FH36+1) -> 0 | FK36: =IF(FL36="","",1/(FL36+0.01)) | FL36: =IF(FI36>0,ROUNDDOWN(('Diseño estructura &CP'!$AZ$5/FI36),0),"") | FN36: Lado 21 | FP36: metros | FR36: =IFERROR(IF(FO36="",0,ROUNDDOWN(('Diseño estructura &CP'!$AZ$6/FO36),0)),0) -> 0 | FZ36: =+IF(GA36=0,"",FZ35+1) | GA36: =+GC36/$H$9 -> 0 | GB36: =ROUNDDOWN(GC36/$C$13,0) -> 0 | GD36: =IF(GB36=0,0,GB36+1) -> 0 | GE36: =IF(GF36="","",1/(GF36+0.01)) | GF36: =IF(GC36>0,ROUNDDOWN(('Diseño estructura &CP'!$AZ$5/GC36),0),"") | GH36: Lado 21 | GJ36: metros | GL36: =IFERROR(IF(GI36="",0,ROUNDDOWN(('Diseño estructura &CP'!$AZ$6/GI36),0)),0) -> 0
B37: =+IF(C37=0,"",B36+1) -> 22 | C37: =+E37/$H$9 -> 38.25 | D37: =ROUNDDOWN(E37/$C$13,0) -> 6 | E37: 76.5 | F37: =IF(D37=0,0,D37+1) -> 7 | G37: =IF(H37="","",1/(H37+0.01)) -> 0.076863951 | H37: =IF(E37>0,ROUNDDOWN(('Diseño estructura &CP'!$AZ$5/E37),0),"") -> 13 | J37: Lado 22 | L37: metros | N37: =IFERROR(IF(K37="",0,ROUNDDOWN(('Diseño estructura &CP'!$AZ$6/K37),0)),0) -> 0 | P37: T22 | Q37: =IF(H$11="SI",B$14,"") -> 106 | R37: =IF(Q37="","",Q37*$R$15) -> 424 | S37: =1/(T37+0.01) -> 0.99009901 | T37: =IFERROR(ROUNDDOWN(('Diseño estructura &CP'!$AZ$8/R37),0),0) -> 1 | V37: =+IF(W37=0,"",V36+1) -> 22 | W37: =+Y37/$H$9 -> 94.5 | X37: =ROUNDDOWN(Y37/$C$13,0) -> 15 | Y37: 189 | Z37: =IF(X37=0,0,X37+1) -> 16 | AA37: =IF(AB37="","",1/(AB37+0.01)) -> 0.1996008 | AB37: =IF(Y37>0,ROUNDDOWN(('Diseño estructura &CP'!$AZ$5/Y37),0),"") -> 5 | AD37: Lado 22 | AF37: metros | AH37: =IFERROR(IF(AE37="",0,ROUNDDOWN(('Diseño estructura &CP'!$AZ$6/AE37),0)),0) -> 0 | AP37: =+IF(AQ37=0,"",AP36+1) -> 22 | AQ37: =+AS37/$H$9 -> 81 | AR37: =ROUNDDOWN(AS37/$C$13,0) -> 13 | AS37: 162 | AT37: =IF(AR37=0,0,AR37+1) -> 14 | AU37: =IF(AV37="","",1/(AV37+0.01)) -> 0.16638935 | AV37: =IF(AS37>0,ROUNDDOWN(('Diseño estructura &CP'!$AZ$5/AS37),0),"") -> 6 | AX37: Lado 22 | AZ37: metros | BB37: =IFERROR(IF(AY37="",0,ROUNDDOWN(('Diseño estructura &CP'!$AZ$6/AY37),0)),0) -> 0 | BJ37: =+IF(BK37=0,"",BJ36+1) -> 22 | BK37: =+BM37/$H$9 -> 43.75 | BL37: =ROUNDDOWN(BM37/$BK$13,0) -> 7 | BM37: 87.5 | BN37: =IF(BL37=0,0,BL37+1) -> 8 | BO37: =IF(BP37="","",1/(BP37+0.01)) -> 0.090826521 | BP37: =IF(BM37>0,ROUNDDOWN(('Diseño estructura &CP'!$AZ$5/BM37),0),"") -> 11 | BR37: Lado 22 | BT37: metros | BV37: =IFERROR(IF(BS37="",0,ROUNDDOWN(('Diseño estructura &CP'!$AZ$6/BS37),0)),0) -> 0 | CD37: =+IF(CE37=0,"",CD36+1) | CE37: =+CG37/$H$9 -> 0 | CF37: =ROUNDDOWN(CG37/$C$13,0) -> 0 | CH37: =IF(CF37=0,0,CF37+1) -> 0 | CI37: =IF(CJ37="","",1/(CJ37+0.01)) | CJ37: =IF(CG37>0,ROUNDDOWN(('Diseño estructura &CP'!$AZ$5/CG37),0),"") | CL37: Lado 22 | CN37: metros | CP37: =IFERROR(IF(CM37="",0,ROUNDDOWN(('Diseño estructura &CP'!$AZ$6/CM37),0)),0) -> 0 | CX37: =+IF(CY37=0,"",CX36+1) | CY37: =+DA37/$H$9 -> 0 | CZ37: =ROUNDDOWN(DA37/$C$13,0) -> 0 | DB37: =IF(CZ37=0,0,CZ37+1) -> 0 | DC37: =IF(DD37="","",1/(DD37+0.01)) | DD37: =IF(DA37>0,ROUNDDOWN(('Diseño estructura &CP'!$AZ$5/DA37),0),"") | DF37: Lado 22 | DH37: metros | DJ37: =IFERROR(IF(DG37="",0,ROUNDDOWN(('Diseño estructura &CP'!$AZ$6/DG37),0)),0) -> 0 | DR37: =+IF(DS37=0,"",DR36+1) | DS37: =+DU37/$H$9 -> 0 | DT37: =ROUNDDOWN(DU37/$C$13,0) -> 0 | DV37: =IF(DT37=0,0,DT37+1) -> 0 | DW37: =IF(DX37="","",1/(DX37+0.01)) | DX37: =IF(DU37>0,ROUNDDOWN(('Diseño estructura &CP'!$AZ$5/DU37),0),"") | DZ37: Lado 22 | EB37: metros | ED37: =IFERROR(IF(EA37="",0,ROUNDDOWN(('Diseño estructura &CP'!$AZ$6/EA37),0)),0) -> 0 | EL37: =+IF(EM37=0,"",EL36+1) | EM37: =+EO37/$H$9 -> 0 | EN37: =ROUNDDOWN(EO37/$C$13,0) -> 0 | EP37: =IF(EN37=0,0,EN37+1) -> 0 | EQ37: =IF(ER37="","",1/(ER37+0.01)) | ER37: =IF(EO37>0,ROUNDDOWN(('Diseño estructura &CP'!$AZ$5/EO37),0),"") | ET37: Lado 22 | EV37: metros | EX37: =IFERROR(IF(EU37="",0,ROUNDDOWN(('Diseño estructura &CP'!$AZ$6/EU37),0)),0) -> 0 | FF37: =+IF(FG37=0,"",FF36+1) | FG37: =+FI37/$H$9 -> 0 | FH37: =ROUNDDOWN(FI37/$C$13,0) -> 0 | FJ37: =IF(FH37=0,0,FH37+1) -> 0 | FK37: =IF(FL37="","",1/(FL37+0.01)) | FL37: =IF(FI37>0,ROUNDDOWN(('Diseño estructura &CP'!$AZ$5/FI37),0),"") | FN37: Lado 22 | FP37: metros | FR37: =IFERROR(IF(FO37="",0,ROUNDDOWN(('Diseño estructura &CP'!$AZ$6/FO37),0)),0) -> 0 | FZ37: =+IF(GA37=0,"",FZ36+1) | GA37: =+GC37/$H$9 -> 0 | GB37: =ROUNDDOWN(GC37/$C$13,0) -> 0 | GD37: =IF(GB37=0,0,GB37+1) -> 0 | GE37: =IF(GF37="","",1/(GF37+0.01)) | GF37: =IF(GC37>0,ROUNDDOWN(('Diseño estructura &CP'!$AZ$5/GC37),0),"") | GH37: Lado 22 | GJ37: metros | GL37: =IFERROR(IF(GI37="",0,ROUNDDOWN(('Diseño estructura &CP'!$AZ$6/GI37),0)),0) -> 0
B38: =+IF(C38=0,"",B37+1) -> 23 | C38: =+E38/$H$9 -> 41 | D38: =ROUNDDOWN(E38/$C$13,0) -> 6 | E38: 82 | F38: =IF(D38=0,0,D38+1) -> 7 | G38: =IF(H38="","",1/(H38+0.01)) -> 0.083263947 | H38: =IF(E38>0,ROUNDDOWN(('Diseño estructura &CP'!$AZ$5/E38),0),"") -> 12 | J38: Lado 23 | L38: metros | N38: =IFERROR(IF(K38="",0,ROUNDDOWN(('Diseño estructura &CP'!$AZ$6/K38),0)),0) -> 0 | P38: T23 | Q38: =IF(H$11="SI",B$14,"") -> 106 | R38: =IF(Q38="","",Q38*$R$15) -> 424 | S38: =1/(T38+0.01) -> 0.99009901 | T38: =IFERROR(ROUNDDOWN(('Diseño estructura &CP'!$AZ$8/R38),0),0) -> 1 | V38: =+IF(W38=0,"",V37+1) -> 23 | W38: =+Y38/$H$9 -> 94.5 | X38: =ROUNDDOWN(Y38/$C$13,0) -> 15 | Y38: 189 | Z38: =IF(X38=0,0,X38+1) -> 16 | AA38: =IF(AB38="","",1/(AB38+0.01)) -> 0.1996008 | AB38: =IF(Y38>0,ROUNDDOWN(('Diseño estructura &CP'!$AZ$5/Y38),0),"") -> 5 | AD38: Lado 23 | AF38: metros | AH38: =IFERROR(IF(AE38="",0,ROUNDDOWN(('Diseño estructura &CP'!$AZ$6/AE38),0)),0) -> 0 | AP38: =+IF(AQ38=0,"",AP37+1) -> 23 | AQ38: =+AS38/$H$9 -> 81.5 | AR38: =ROUNDDOWN(AS38/$C$13,0) -> 13 | AS38: 163 | AT38: =IF(AR38=0,0,AR38+1) -> 14 | AU38: =IF(AV38="","",1/(AV38+0.01)) -> 0.16638935 | AV38: =IF(AS38>0,ROUNDDOWN(('Diseño estructura &CP'!$AZ$5/AS38),0),"") -> 6 | AX38: Lado 23 | AZ38: metros | BB38: =IFERROR(IF(AY38="",0,ROUNDDOWN(('Diseño estructura &CP'!$AZ$6/AY38),0)),0) -> 0 | BJ38: =+IF(BK38=0,"",BJ37+1) -> 23 | BK38: =+BM38/$H$9 -> 38.75 | BL38: =ROUNDDOWN(BM38/$BK$13,0) -> 7 | BM38: 77.5 | BN38: =IF(BL38=0,0,BL38+1) -> 8 | BO38: =IF(BP38="","",1/(BP38+0.01)) -> 0.083263947 | BP38: =IF(BM38>0,ROUNDDOWN(('Diseño estructura &CP'!$AZ$5/BM38),0),"") -> 12 | BR38: Lado 23 | BT38: metros | BV38: =IFERROR(IF(BS38="",0,ROUNDDOWN(('Diseño estructura &CP'!$AZ$6/BS38),0)),0) -> 0 | CD38: =+IF(CE38=0,"",CD37+1) | CE38: =+CG38/$H$9 -> 0 | CF38: =ROUNDDOWN(CG38/$C$13,0) -> 0 | CH38: =IF(CF38=0,0,CF38+1) -> 0 | CI38: =IF(CJ38="","",1/(CJ38+0.01)) | CJ38: =IF(CG38>0,ROUNDDOWN(('Diseño estructura &CP'!$AZ$5/CG38),0),"") | CL38: Lado 23 | CN38: metros | CP38: =IFERROR(IF(CM38="",0,ROUNDDOWN(('Diseño estructura &CP'!$AZ$6/CM38),0)),0) -> 0 | CX38: =+IF(CY38=0,"",CX37+1) | CY38: =+DA38/$H$9 -> 0 | CZ38: =ROUNDDOWN(DA38/$C$13,0) -> 0 | DB38: =IF(CZ38=0,0,CZ38+1) -> 0 | DC38: =IF(DD38="","",1/(DD38+0.01)) | DD38: =IF(DA38>0,ROUNDDOWN(('Diseño estructura &CP'!$AZ$5/DA38),0),"") | DF38: Lado 23 | DH38: metros | DJ38: =IFERROR(IF(DG38="",0,ROUNDDOWN(('Diseño estructura &CP'!$AZ$6/DG38),0)),0) -> 0 | DR38: =+IF(DS38=0,"",DR37+1) | DS38: =+DU38/$H$9 -> 0 | DT38: =ROUNDDOWN(DU38/$C$13,0) -> 0 | DV38: =IF(DT38=0,0,DT38+1) -> 0 | DW38: =IF(DX38="","",1/(DX38+0.01)) | DX38: =IF(DU38>0,ROUNDDOWN(('Diseño estructura &CP'!$AZ$5/DU38),0),"") | DZ38: Lado 23 | EB38: metros | ED38: =IFERROR(IF(EA38="",0,ROUNDDOWN(('Diseño estructura &CP'!$AZ$6/EA38),0)),0) -> 0 | EL38: =+IF(EM38=0,"",EL37+1) | EM38: =+EO38/$H$9 -> 0 | EN38: =ROUNDDOWN(EO38/$C$13,0) -> 0 | EP38: =IF(EN38=0,0,EN38+1) -> 0 | EQ38: =IF(ER38="","",1/(ER38+0.01)) | ER38: =IF(EO38>0,ROUNDDOWN(('Diseño estructura &CP'!$AZ$5/EO38),0),"") | ET38: Lado 23 | EV38: metros | EX38: =IFERROR(IF(EU38="",0,ROUNDDOWN(('Diseño estructura &CP'!$AZ$6/EU38),0)),0) -> 0 | FF38: =+IF(FG38=0,"",FF37+1) | FG38: =+FI38/$H$9 -> 0 | FH38: =ROUNDDOWN(FI38/$C$13,0) -> 0 | FJ38: =IF(FH38=0,0,FH38+1) -> 0 | FK38: =IF(FL38="","",1/(FL38+0.01)) | FL38: =IF(FI38>0,ROUNDDOWN(('Diseño estructura &CP'!$AZ$5/FI38),0),"") | FN38: Lado 23 | FP38: metros | FR38: =IFERROR(IF(FO38="",0,ROUNDDOWN(('Diseño estructura &CP'!$AZ$6/FO38),0)),0) -> 0 | FZ38: =+IF(GA38=0,"",FZ37+1) | GA38: =+GC38/$H$9 -> 0 | GB38: =ROUNDDOWN(GC38/$C$13,0) -> 0 | GD38: =IF(GB38=0,0,GB38+1) -> 0 | GE38: =IF(GF38="","",1/(GF38+0.01)) | GF38: =IF(GC38>0,ROUNDDOWN(('Diseño estructura &CP'!$AZ$5/GC38),0),"") | GH38: Lado 23 | GJ38: metros | GL38: =IFERROR(IF(GI38="",0,ROUNDDOWN(('Diseño estructura &CP'!$AZ$6/GI38),0)),0) -> 0
B39: =+IF(C39=0,"",B38+1) -> 24 | C39: =+E39/$H$9 -> 42.75 | D39: =ROUNDDOWN(E39/$C$13,0) -> 7 | E39: 85.5 | F39: =IF(D39=0,0,D39+1) -> 8 | G39: =IF(H39="","",1/(H39+0.01)) -> 0.090826521 | H39: =IF(E39>0,ROUNDDOWN(('Diseño estructura &CP'!$AZ$5/E39),0),"") -> 11 | J39: Lado 24 | L39: metros | N39: =IFERROR(IF(K39="",0,ROUNDDOWN(('Diseño estructura &CP'!$AZ$6/K39),0)),0) -> 0 | V39: =+IF(W39=0,"",V38+1) -> 24 | W39: =+Y39/$H$9 -> 94 | X39: =ROUNDDOWN(Y39/$C$13,0) -> 15 | Y39: 188 | Z39: =IF(X39=0,0,X39+1) -> 16 | AA39: =IF(AB39="","",1/(AB39+0.01)) -> 0.1996008 | AB39: =IF(Y39>0,ROUNDDOWN(('Diseño estructura &CP'!$AZ$5/Y39),0),"") -> 5 | AD39: Lado 24 | AF39: metros | AH39: =IFERROR(IF(AE39="",0,ROUNDDOWN(('Diseño estructura &CP'!$AZ$6/AE39),0)),0) -> 0 | AP39: =+IF(AQ39=0,"",AP38+1) -> 24 | AQ39: =+AS39/$H$9 -> 81 | AR39: =ROUNDDOWN(AS39/$C$13,0) -> 13 | AS39: 162 | AT39: =IF(AR39=0,0,AR39+1) -> 14 | AU39: =IF(AV39="","",1/(AV39+0.01)) -> 0.16638935 | AV39: =IF(AS39>0,ROUNDDOWN(('Diseño estructura &CP'!$AZ$5/AS39),0),"") -> 6 | AX39: Lado 24 | AZ39: metros | BB39: =IFERROR(IF(AY39="",0,ROUNDDOWN(('Diseño estructura &CP'!$AZ$6/AY39),0)),0) -> 0 | BJ39: =+IF(BK39=0,"",BJ38+1) -> 24 | BK39: =+BM39/$H$9 -> 30 | BL39: =ROUNDDOWN(BM39/$BK$13,0) -> 5 | BM39: 60 | BN39: =IF(BL39=0,0,BL39+1) -> 6 | BO39: =IF(BP39="","",1/(BP39+0.01)) -> 0.062460962 | BP39: =IF(BM39>0,ROUNDDOWN(('Diseño estructura &CP'!$AZ$5/BM39),0),"") -> 16 | BR39: Lado 24 | BT39: metros | BV39: =IFERROR(IF(BS39="",0,ROUNDDOWN(('Diseño estructura &CP'!$AZ$6/BS39),0)),0) -> 0 | CD39: =+IF(CE39=0,"",CD38+1) | CE39: =+CG39/$H$9 -> 0 | CF39: =ROUNDDOWN(CG39/$C$13,0) -> 0 | CH39: =IF(CF39=0,0,CF39+1) -> 0 | CI39: =IF(CJ39="","",1/(CJ39+0.01)) | CJ39: =IF(CG39>0,ROUNDDOWN(('Diseño estructura &CP'!$AZ$5/CG39),0),"") | CL39: Lado 24 | CN39: metros | CP39: =IFERROR(IF(CM39="",0,ROUNDDOWN(('Diseño estructura &CP'!$AZ$6/CM39),0)),0) -> 0 | CX39: =+IF(CY39=0,"",CX38+1) | CY39: =+DA39/$H$9 -> 0 | CZ39: =ROUNDDOWN(DA39/$C$13,0) -> 0 | DB39: =IF(CZ39=0,0,CZ39+1) -> 0 | DC39: =IF(DD39="","",1/(DD39+0.01)) | DD39: =IF(DA39>0,ROUNDDOWN(('Diseño estructura &CP'!$AZ$5/DA39),0),"") | DF39: Lado 24 | DH39: metros | DJ39: =IFERROR(IF(DG39="",0,ROUNDDOWN(('Diseño estructura &CP'!$AZ$6/DG39),0)),0) -> 0 | DR39: =+IF(DS39=0,"",DR38+1) | DS39: =+DU39/$H$9 -> 0 | DT39: =ROUNDDOWN(DU39/$C$13,0) -> 0 | DV39: =IF(DT39=0,0,DT39+1) -> 0 | DW39: =IF(DX39="","",1/(DX39+0.01)) | DX39: =IF(DU39>0,ROUNDDOWN(('Diseño estructura &CP'!$AZ$5/DU39),0),"") | DZ39: Lado 24 | EB39: metros | ED39: =IFERROR(IF(EA39="",0,ROUNDDOWN(('Diseño estructura &CP'!$AZ$6/EA39),0)),0) -> 0 | EL39: =+IF(EM39=0,"",EL38+1) | EM39: =+EO39/$H$9 -> 0 | EN39: =ROUNDDOWN(EO39/$C$13,0) -> 0 | EP39: =IF(EN39=0,0,EN39+1) -> 0 | EQ39: =IF(ER39="","",1/(ER39+0.01)) | ER39: =IF(EO39>0,ROUNDDOWN(('Diseño estructura &CP'!$AZ$5/EO39),0),"") | ET39: Lado 24 | EV39: metros | EX39: =IFERROR(IF(EU39="",0,ROUNDDOWN(('Diseño estructura &CP'!$AZ$6/EU39),0)),0) -> 0 | FF39: =+IF(FG39=0,"",FF38+1) | FG39: =+FI39/$H$9 -> 0 | FH39: =ROUNDDOWN(FI39/$C$13,0) -> 0 | FJ39: =IF(FH39=0,0,FH39+1) -> 0 | FK39: =IF(FL39="","",1/(FL39+0.01)) | FL39: =IF(FI39>0,ROUNDDOWN(('Diseño estructura &CP'!$AZ$5/FI39),0),"") | FN39: Lado 24 | FP39: metros | FR39: =IFERROR(IF(FO39="",0,ROUNDDOWN(('Diseño estructura &CP'!$AZ$6/FO39),0)),0) -> 0 | FZ39: =+IF(GA39=0,"",FZ38+1) | GA39: =+GC39/$H$9 -> 0 | GB39: =ROUNDDOWN(GC39/$C$13,0) -> 0 | GD39: =IF(GB39=0,0,GB39+1) -> 0 | GE39: =IF(GF39="","",1/(GF39+0.01)) | GF39: =IF(GC39>0,ROUNDDOWN(('Diseño estructura &CP'!$AZ$5/GC39),0),"") | GH39: Lado 24 | GJ39: metros | GL39: =IFERROR(IF(GI39="",0,ROUNDDOWN(('Diseño estructura &CP'!$AZ$6/GI39),0)),0) -> 0
B40: =+IF(C40=0,"",B39+1) -> 25 | C40: =+E40/$H$9 -> 44 | D40: =ROUNDDOWN(E40/$C$13,0) -> 7 | E40: 88 | F40: =IF(D40=0,0,D40+1) -> 8 | G40: =IF(H40="","",1/(H40+0.01)) -> 0.090826521 | H40: =IF(E40>0,ROUNDDOWN(('Diseño estructura &CP'!$AZ$5/E40),0),"") -> 11 | J40: Lado 25 | L40: metros | N40: =IFERROR(IF(K40="",0,ROUNDDOWN(('Diseño estructura &CP'!$AZ$6/K40),0)),0) -> 0 | V40: =+IF(W40=0,"",V39+1) -> 25 | W40: =+Y40/$H$9 -> 93.5 | X40: =ROUNDDOWN(Y40/$C$13,0) -> 15 | Y40: 187 | Z40: =IF(X40=0,0,X40+1) -> 16 | AA40: =IF(AB40="","",1/(AB40+0.01)) -> 0.1996008 | AB40: =IF(Y40>0,ROUNDDOWN(('Diseño estructura &CP'!$AZ$5/Y40),0),"") -> 5 | AD40: Lado 25 | AF40: metros | AH40: =IFERROR(IF(AE40="",0,ROUNDDOWN(('Diseño estructura &CP'!$AZ$6/AE40),0)),0) -> 0 | AP40: =+IF(AQ40=0,"",AP39+1) -> 25 | AQ40: =+AS40/$H$9 -> 81 | AR40: =ROUNDDOWN(AS40/$C$13,0) -> 13 | AS40: 162 | AT40: =IF(AR40=0,0,AR40+1) -> 14 | AU40: =IF(AV40="","",1/(AV40+0.01)) -> 0.16638935 | AV40: =IF(AS40>0,ROUNDDOWN(('Diseño estructura &CP'!$AZ$5/AS40),0),"") -> 6 | AX40: Lado 25 | AZ40: metros | BB40: =IFERROR(IF(AY40="",0,ROUNDDOWN(('Diseño estructura &CP'!$AZ$6/AY40),0)),0) -> 0 | BJ40: =+IF(BK40=0,"",BJ39+1) -> 25 | BK40: =+BM40/$H$9 -> 26.75 | BL40: =ROUNDDOWN(BM40/$BK$13,0) -> 4 | BM40: 53.5 | BN40: =IF(BL40=0,0,BL40+1) -> 5 | BO40: =IF(BP40="","",1/(BP40+0.01)) -> 0.055524708 | BP40: =IF(BM40>0,ROUNDDOWN(('Diseño estructura &CP'!$AZ$5/BM40),0),"") -> 18 | BR40: Lado 25 | BT40: metros | BV40: =IFERROR(IF(BS40="",0,ROUNDDOWN(('Diseño estructura &CP'!$AZ$6/BS40),0)),0) -> 0 | CD40: =+IF(CE40=0,"",CD39+1) | CE40: =+CG40/$H$9 -> 0 | CF40: =ROUNDDOWN(CG40/$C$13,0) -> 0 | CH40: =IF(CF40=0,0,CF40+1) -> 0 | CI40: =IF(CJ40="","",1/(CJ40+0.01)) | CJ40: =IF(CG40>0,ROUNDDOWN(('Diseño estructura &CP'!$AZ$5/CG40),0),"") | CL40: Lado 25 | CN40: metros | CP40: =IFERROR(IF(CM40="",0,ROUNDDOWN(('Diseño estructura &CP'!$AZ$6/CM40),0)),0) -> 0 | CX40: =+IF(CY40=0,"",CX39+1) | CY40: =+DA40/$H$9 -> 0 | CZ40: =ROUNDDOWN(DA40/$C$13,0) -> 0 | DB40: =IF(CZ40=0,0,CZ40+1) -> 0 | DC40: =IF(DD40="","",1/(DD40+0.01)) | DD40: =IF(DA40>0,ROUNDDOWN(('Diseño estructura &CP'!$AZ$5/DA40),0),"") | DF40: Lado 25 | DH40: metros | DJ40: =IFERROR(IF(DG40="",0,ROUNDDOWN(('Diseño estructura &CP'!$AZ$6/DG40),0)),0) -> 0 | DR40: =+IF(DS40=0,"",DR39+1) | DS40: =+DU40/$H$9 -> 0 | DT40: =ROUNDDOWN(DU40/$C$13,0) -> 0 | DV40: =IF(DT40=0,0,DT40+1) -> 0 | DW40: =IF(DX40="","",1/(DX40+0.01)) | DX40: =IF(DU40>0,ROUNDDOWN(('Diseño estructura &CP'!$AZ$5/DU40),0),"") | DZ40: Lado 25 | EB40: metros | ED40: =IFERROR(IF(EA40="",0,ROUNDDOWN(('Diseño estructura &CP'!$AZ$6/EA40),0)),0) -> 0 | EL40: =+IF(EM40=0,"",EL39+1) | EM40: =+EO40/$H$9 -> 0 | EN40: =ROUNDDOWN(EO40/$C$13,0) -> 0 | EP40: =IF(EN40=0,0,EN40+1) -> 0 | EQ40: =IF(ER40="","",1/(ER40+0.01)) | ER40: =IF(EO40>0,ROUNDDOWN(('Diseño estructura &CP'!$AZ$5/EO40),0),"") | ET40: Lado 25 | EV40: metros | EX40: =IFERROR(IF(EU40="",0,ROUNDDOWN(('Diseño estructura &CP'!$AZ$6/EU40),0)),0) -> 0 | FF40: =+IF(FG40=0,"",FF39+1) | FG40: =+FI40/$H$9 -> 0 | FH40: =ROUNDDOWN(FI40/$C$13,0) -> 0 | FJ40: =IF(FH40=0,0,FH40+1) -> 0 | FK40: =IF(FL40="","",1/(FL40+0.01)) | FL40: =IF(FI40>0,ROUNDDOWN(('Diseño estructura &CP'!$AZ$5/FI40),0),"") | FN40: Lado 25 | FP40: metros | FR40: =IFERROR(IF(FO40="",0,ROUNDDOWN(('Diseño estructura &CP'!$AZ$6/FO40),0)),0) -> 0 | FZ40: =+IF(GA40=0,"",FZ39+1) | GA40: =+GC40/$H$9 -> 0 | GB40: =ROUNDDOWN(GC40/$C$13,0) -> 0 | GD40: =IF(GB40=0,0,GB40+1) -> 0 | GE40: =IF(GF40="","",1/(GF40+0.01)) | GF40: =IF(GC40>0,ROUNDDOWN(('Diseño estructura &CP'!$AZ$5/GC40),0),"") | GH40: Lado 25 | GJ40: metros | GL40: =IFERROR(IF(GI40="",0,ROUNDDOWN(('Diseño estructura &CP'!$AZ$6/GI40),0)),0) -> 0
B41: =+IF(C41=0,"",B40+1) -> 26 | C41: =+E41/$H$9 -> 44.25 | D41: =ROUNDDOWN(E41/$C$13,0) -> 7 | E41: 88.5 | F41: =IF(D41=0,0,D41+1) -> 8 | G41: =IF(H41="","",1/(H41+0.01)) -> 0.090826521 | H41: =IF(E41>0,ROUNDDOWN(('Diseño estructura &CP'!$AZ$5/E41),0),"") -> 11 | J41: Lado 26 | L41: metros | N41: =IFERROR(IF(K41="",0,ROUNDDOWN(('Diseño estructura &CP'!$AZ$6/K41),0)),0) -> 0 | V41: =+IF(W41=0,"",V40+1) -> 26 | W41: =+Y41/$H$9 -> 92.5 | X41: =ROUNDDOWN(Y41/$C$13,0) -> 15 | Y41: 185 | Z41: =IF(X41=0,0,X41+1) -> 16 | AA41: =IF(AB41="","",1/(AB41+0.01)) -> 0.1996008 | AB41: =IF(Y41>0,ROUNDDOWN(('Diseño estructura &CP'!$AZ$5/Y41),0),"") -> 5 | AD41: Lado 26 | AF41: metros | AH41: =IFERROR(IF(AE41="",0,ROUNDDOWN(('Diseño estructura &CP'!$AZ$6/AE41),0)),0) -> 0 | AP41: =+IF(AQ41=0,"",AP40+1) -> 26 | AQ41: =+AS41/$H$9 -> 81.5 | AR41: =ROUNDDOWN(AS41/$C$13,0) -> 13 | AS41: 163 | AT41: =IF(AR41=0,0,AR41+1) -> 14 | AU41: =IF(AV41="","",1/(AV41+0.01)) -> 0.16638935 | AV41: =IF(AS41>0,ROUNDDOWN(('Diseño estructura &CP'!$AZ$5/AS41),0),"") -> 6 | AX41: Lado 26 | AZ41: metros | BB41: =IFERROR(IF(AY41="",0,ROUNDDOWN(('Diseño estructura &CP'!$AZ$6/AY41),0)),0) -> 0 | BJ41: =+IF(BK41=0,"",BJ40+1) -> 26 | BK41: =+BM41/$H$9 -> 22 | BL41: =ROUNDDOWN(BM41/$BK$13,0) -> 4 | BM41: 44 | BN41: =IF(BL41=0,0,BL41+1) -> 5 | BO41: =IF(BP41="","",1/(BP41+0.01)) -> 0.045433894 | BP41: =IF(BM41>0,ROUNDDOWN(('Diseño estructura &CP'!$AZ$5/BM41),0),"") -> 22 | BR41: Lado 26 | BT41: metros | BV41: =IFERROR(IF(BS41="",0,ROUNDDOWN(('Diseño estructura &CP'!$AZ$6/BS41),0)),0) -> 0 | CD41: =+IF(CE41=0,"",CD40+1) | CE41: =+CG41/$H$9 -> 0 | CF41: =ROUNDDOWN(CG41/$C$13,0) -> 0 | CH41: =IF(CF41=0,0,CF41+1) -> 0 | CI41: =IF(CJ41="","",1/(CJ41+0.01)) | CJ41: =IF(CG41>0,ROUNDDOWN(('Diseño estructura &CP'!$AZ$5/CG41),0),"") | CL41: Lado 26 | CN41: metros | CP41: =IFERROR(IF(CM41="",0,ROUNDDOWN(('Diseño estructura &CP'!$AZ$6/CM41),0)),0) -> 0 | CX41: =+IF(CY41=0,"",CX40+1) | CY41: =+DA41/$H$9 -> 0 | CZ41: =ROUNDDOWN(DA41/$C$13,0) -> 0 | DB41: =IF(CZ41=0,0,CZ41+1) -> 0 | DC41: =IF(DD41="","",1/(DD41+0.01)) | DD41: =IF(DA41>0,ROUNDDOWN(('Diseño estructura &CP'!$AZ$5/DA41),0),"") | DF41: Lado 26 | DH41: metros | DJ41: =IFERROR(IF(DG41="",0,ROUNDDOWN(('Diseño estructura &CP'!$AZ$6/DG41),0)),0) -> 0 | DR41: =+IF(DS41=0,"",DR40+1) | DS41: =+DU41/$H$9 -> 0 | DT41: =ROUNDDOWN(DU41/$C$13,0) -> 0 | DV41: =IF(DT41=0,0,DT41+1) -> 0 | DW41: =IF(DX41="","",1/(DX41+0.01)) | DX41: =IF(DU41>0,ROUNDDOWN(('Diseño estructura &CP'!$AZ$5/DU41),0),"") | DZ41: Lado 26 | EB41: metros | ED41: =IFERROR(IF(EA41="",0,ROUNDDOWN(('Diseño estructura &CP'!$AZ$6/EA41),0)),0) -> 0 | EL41: =+IF(EM41=0,"",EL40+1) | EM41: =+EO41/$H$9 -> 0 | EN41: =ROUNDDOWN(EO41/$C$13,0) -> 0 | EP41: =IF(EN41=0,0,EN41+1) -> 0 | EQ41: =IF(ER41="","",1/(ER41+0.01)) | ER41: =IF(EO41>0,ROUNDDOWN(('Diseño estructura &CP'!$AZ$5/EO41),0),"") | ET41: Lado 26 | EV41: metros | EX41: =IFERROR(IF(EU41="",0,ROUNDDOWN(('Diseño estructura &CP'!$AZ$6/EU41),0)),0) -> 0 | FF41: =+IF(FG41=0,"",FF40+1) | FG41: =+FI41/$H$9 -> 0 | FH41: =ROUNDDOWN(FI41/$C$13,0) -> 0 | FJ41: =IF(FH41=0,0,FH41+1) -> 0 | FK41: =IF(FL41="","",1/(FL41+0.01)) | FL41: =IF(FI41>0,ROUNDDOWN(('Diseño estructura &CP'!$AZ$5/FI41),0),"") | FN41: Lado 26 | FP41: metros | FR41: =IFERROR(IF(FO41="",0,ROUNDDOWN(('Diseño estructura &CP'!$AZ$6/FO41),0)),0) -> 0 | FZ41: =+IF(GA41=0,"",FZ40+1) | GA41: =+GC41/$H$9 -> 0 | GB41: =ROUNDDOWN(GC41/$C$13,0) -> 0 | GD41: =IF(GB41=0,0,GB41+1) -> 0 | GE41: =IF(GF41="","",1/(GF41+0.01)) | GF41: =IF(GC41>0,ROUNDDOWN(('Diseño estructura &CP'!$AZ$5/GC41),0),"") | GH41: Lado 26 | GJ41: metros | GL41: =IFERROR(IF(GI41="",0,ROUNDDOWN(('Diseño estructura &CP'!$AZ$6/GI41),0)),0) -> 0
B42: =+IF(C42=0,"",B41+1) -> 27 | C42: =+E42/$H$9 -> 47 | D42: =ROUNDDOWN(E42/$C$13,0) -> 7 | E42: 94 | F42: =IF(D42=0,0,D42+1) -> 8 | G42: =IF(H42="","",1/(H42+0.01)) -> 0.0999001 | H42: =IF(E42>0,ROUNDDOWN(('Diseño estructura &CP'!$AZ$5/E42),0),"") -> 10 | J42: Lado 27 | L42: metros | N42: =IFERROR(IF(K42="",0,ROUNDDOWN(('Diseño estructura &CP'!$AZ$6/K42),0)),0) -> 0 | V42: =+IF(W42=0,"",V41+1) -> 27 | W42: =+Y42/$H$9 -> 91 | X42: =ROUNDDOWN(Y42/$C$13,0) -> 15 | Y42: 182 | Z42: =IF(X42=0,0,X42+1) -> 16 | AA42: =IF(AB42="","",1/(AB42+0.01)) -> 0.1996008 | AB42: =IF(Y42>0,ROUNDDOWN(('Diseño estructura &CP'!$AZ$5/Y42),0),"") -> 5 | AD42: Lado 27 | AF42: metros | AH42: =IFERROR(IF(AE42="",0,ROUNDDOWN(('Diseño estructura &CP'!$AZ$6/AE42),0)),0) -> 0 | AP42: =+IF(AQ42=0,"",AP41+1) -> 27 | AQ42: =+AS42/$H$9 -> 81 | AR42: =ROUNDDOWN(AS42/$C$13,0) -> 13 | AS42: 162 | AT42: =IF(AR42=0,0,AR42+1) -> 14 | AU42: =IF(AV42="","",1/(AV42+0.01)) -> 0.16638935 | AV42: =IF(AS42>0,ROUNDDOWN(('Diseño estructura &CP'!$AZ$5/AS42),0),"") -> 6 | AX42: Lado 27 | AZ42: metros | BB42: =IFERROR(IF(AY42="",0,ROUNDDOWN(('Diseño estructura &CP'!$AZ$6/AY42),0)),0) -> 0 | BJ42: =+IF(BK42=0,"",BJ41+1) -> 27 | BK42: =+BM42/$H$9 -> 17.5 | BL42: =ROUNDDOWN(BM42/$BK$13,0) -> 3 | BM42: 35 | BN42: =IF(BL42=0,0,BL42+1) -> 4 | BO42: =IF(BP42="","",1/(BP42+0.01)) -> 0.035701535 | BP42: =IF(BM42>0,ROUNDDOWN(('Diseño estructura &CP'!$AZ$5/BM42),0),"") -> 28 | BR42: Lado 27 | BT42: metros | BV42: =IFERROR(IF(BS42="",0,ROUNDDOWN(('Diseño estructura &CP'!$AZ$6/BS42),0)),0) -> 0 | CD42: =+IF(CE42=0,"",CD41+1) | CE42: =+CG42/$H$9 -> 0 | CF42: =ROUNDDOWN(CG42/$C$13,0) -> 0 | CH42: =IF(CF42=0,0,CF42+1) -> 0 | CI42: =IF(CJ42="","",1/(CJ42+0.01)) | CJ42: =IF(CG42>0,ROUNDDOWN(('Diseño estructura &CP'!$AZ$5/CG42),0),"") | CL42: Lado 27 | CN42: metros | CP42: =IFERROR(IF(CM42="",0,ROUNDDOWN(('Diseño estructura &CP'!$AZ$6/CM42),0)),0) -> 0 | CX42: =+IF(CY42=0,"",CX41+1) | CY42: =+DA42/$H$9 -> 0 | CZ42: =ROUNDDOWN(DA42/$C$13,0) -> 0 | DB42: =IF(CZ42=0,0,CZ42+1) -> 0 | DC42: =IF(DD42="","",1/(DD42+0.01)) | DD42: =IF(DA42>0,ROUNDDOWN(('Diseño estructura &CP'!$AZ$5/DA42),0),"") | DF42: Lado 27 | DH42: metros | DJ42: =IFERROR(IF(DG42="",0,ROUNDDOWN(('Diseño estructura &CP'!$AZ$6/DG42),0)),0) -> 0 | DR42: =+IF(DS42=0,"",DR41+1) | DS42: =+DU42/$H$9 -> 0 | DT42: =ROUNDDOWN(DU42/$C$13,0) -> 0 | DV42: =IF(DT42=0,0,DT42+1) -> 0 | DW42: =IF(DX42="","",1/(DX42+0.01)) | DX42: =IF(DU42>0,ROUNDDOWN(('Diseño estructura &CP'!$AZ$5/DU42),0),"") | DZ42: Lado 27 | EB42: metros | ED42: =IFERROR(IF(EA42="",0,ROUNDDOWN(('Diseño estructura &CP'!$AZ$6/EA42),0)),0) -> 0 | EL42: =+IF(EM42=0,"",EL41+1) | EM42: =+EO42/$H$9 -> 0 | EN42: =ROUNDDOWN(EO42/$C$13,0) -> 0 | EP42: =IF(EN42=0,0,EN42+1) -> 0 | EQ42: =IF(ER42="","",1/(ER42+0.01)) | ER42: =IF(EO42>0,ROUNDDOWN(('Diseño estructura &CP'!$AZ$5/EO42),0),"") | ET42: Lado 27 | EV42: metros | EX42: =IFERROR(IF(EU42="",0,ROUNDDOWN(('Diseño estructura &CP'!$AZ$6/EU42),0)),0) -> 0 | FF42: =+IF(FG42=0,"",FF41+1) | FG42: =+FI42/$H$9 -> 0 | FH42: =ROUNDDOWN(FI42/$C$13,0) -> 0 | FJ42: =IF(FH42=0,0,FH42+1) -> 0 | FK42: =IF(FL42="","",1/(FL42+0.01)) | FL42: =IF(FI42>0,ROUNDDOWN(('Diseño estructura &CP'!$AZ$5/FI42),0),"") | FN42: Lado 27 | FP42: metros | FR42: =IFERROR(IF(FO42="",0,ROUNDDOWN(('Diseño estructura &CP'!$AZ$6/FO42),0)),0) -> 0 | FZ42: =+IF(GA42=0,"",FZ41+1) | GA42: =+GC42/$H$9 -> 0 | GB42: =ROUNDDOWN(GC42/$C$13,0) -> 0 | GD42: =IF(GB42=0,0,GB42+1) -> 0 | GE42: =IF(GF42="","",1/(GF42+0.01)) | GF42: =IF(GC42>0,ROUNDDOWN(('Diseño estructura &CP'!$AZ$5/GC42),0),"") | GH42: Lado 27 | GJ42: metros | GL42: =IFERROR(IF(GI42="",0,ROUNDDOWN(('Diseño estructura &CP'!$AZ$6/GI42),0)),0) -> 0
B43: =+IF(C43=0,"",B42+1) -> 28 | C43: =+E43/$H$9 -> 48 | D43: =ROUNDDOWN(E43/$C$13,0) -> 8 | E43: 96 | F43: =IF(D43=0,0,D43+1) -> 9 | G43: =IF(H43="","",1/(H43+0.01)) -> 0.0999001 | H43: =IF(E43>0,ROUNDDOWN(('Diseño estructura &CP'!$AZ$5/E43),0),"") -> 10 | J43: Lado 28 | L43: metros | N43: =IFERROR(IF(K43="",0,ROUNDDOWN(('Diseño estructura &CP'!$AZ$6/K43),0)),0) -> 0 | V43: =+IF(W43=0,"",V42+1) -> 28 | W43: =+Y43/$H$9 -> 90 | X43: =ROUNDDOWN(Y43/$C$13,0) -> 15 | Y43: 180 | Z43: =IF(X43=0,0,X43+1) -> 16 | AA43: =IF(AB43="","",1/(AB43+0.01)) -> 0.1996008 | AB43: =IF(Y43>0,ROUNDDOWN(('Diseño estructura &CP'!$AZ$5/Y43),0),"") -> 5 | AD43: Lado 28 | AF43: metros | AH43: =IFERROR(IF(AE43="",0,ROUNDDOWN(('Diseño estructura &CP'!$AZ$6/AE43),0)),0) -> 0 | AP43: =+IF(AQ43=0,"",AP42+1) -> 28 | AQ43: =+AS43/$H$9 -> 81 | AR43: =ROUNDDOWN(AS43/$C$13,0) -> 13 | AS43: 162 | AT43: =IF(AR43=0,0,AR43+1) -> 14 | AU43: =IF(AV43="","",1/(AV43+0.01)) -> 0.16638935 | AV43: =IF(AS43>0,ROUNDDOWN(('Diseño estructura &CP'!$AZ$5/AS43),0),"") -> 6 | AX43: Lado 28 | AZ43: metros | BB43: =IFERROR(IF(AY43="",0,ROUNDDOWN(('Diseño estructura &CP'!$AZ$6/AY43),0)),0) -> 0 | BJ43: =+IF(BK43=0,"",BJ42+1) -> 28 | BK43: =+BM43/$H$9 -> 13 | BL43: =ROUNDDOWN(BM43/$BK$13,0) -> 2 | BM43: 26 | BN43: =IF(BL43=0,0,BL43+1) -> 3 | BO43: =IF(BP43="","",1/(BP43+0.01)) -> 0.026308866 | BP43: =IF(BM43>0,ROUNDDOWN(('Diseño estructura &CP'!$AZ$5/BM43),0),"") -> 38 | BR43: Lado 28 | BT43: metros | BV43: =IFERROR(IF(BS43="",0,ROUNDDOWN(('Diseño estructura &CP'!$AZ$6/BS43),0)),0) -> 0 | CD43: =+IF(CE43=0,"",CD42+1) | CE43: =+CG43/$H$9 -> 0 | CF43: =ROUNDDOWN(CG43/$C$13,0) -> 0 | CH43: =IF(CF43=0,0,CF43+1) -> 0 | CI43: =IF(CJ43="","",1/(CJ43+0.01)) | CJ43: =IF(CG43>0,ROUNDDOWN(('Diseño estructura &CP'!$AZ$5/CG43),0),"") | CL43: Lado 28 | CN43: metros | CP43: =IFERROR(IF(CM43="",0,ROUNDDOWN(('Diseño estructura &CP'!$AZ$6/CM43),0)),0) -> 0 | CX43: =+IF(CY43=0,"",CX42+1) | CY43: =+DA43/$H$9 -> 0 | CZ43: =ROUNDDOWN(DA43/$C$13,0) -> 0 | DB43: =IF(CZ43=0,0,CZ43+1) -> 0 | DC43: =IF(DD43="","",1/(DD43+0.01)) | DD43: =IF(DA43>0,ROUNDDOWN(('Diseño estructura &CP'!$AZ$5/DA43),0),"") | DF43: Lado 28 | DH43: metros | DJ43: =IFERROR(IF(DG43="",0,ROUNDDOWN(('Diseño estructura &CP'!$AZ$6/DG43),0)),0) -> 0 | DR43: =+IF(DS43=0,"",DR42+1) | DS43: =+DU43/$H$9 -> 0 | DT43: =ROUNDDOWN(DU43/$C$13,0) -> 0 | DV43: =IF(DT43=0,0,DT43+1) -> 0 | DW43: =IF(DX43="","",1/(DX43+0.01)) | DX43: =IF(DU43>0,ROUNDDOWN(('Diseño estructura &CP'!$AZ$5/DU43),0),"") | DZ43: Lado 28 | EB43: metros | ED43: =IFERROR(IF(EA43="",0,ROUNDDOWN(('Diseño estructura &CP'!$AZ$6/EA43),0)),0) -> 0 | EL43: =+IF(EM43=0,"",EL42+1) | EM43: =+EO43/$H$9 -> 0 | EN43: =ROUNDDOWN(EO43/$C$13,0) -> 0 | EP43: =IF(EN43=0,0,EN43+1) -> 0 | EQ43: =IF(ER43="","",1/(ER43+0.01)) | ER43: =IF(EO43>0,ROUNDDOWN(('Diseño estructura &CP'!$AZ$5/EO43),0),"") | ET43: Lado 28 | EV43: metros | EX43: =IFERROR(IF(EU43="",0,ROUNDDOWN(('Diseño estructura &CP'!$AZ$6/EU43),0)),0) -> 0 | FF43: =+IF(FG43=0,"",FF42+1) | FG43: =+FI43/$H$9 -> 0 | FH43: =ROUNDDOWN(FI43/$C$13,0) -> 0 | FJ43: =IF(FH43=0,0,FH43+1) -> 0 | FK43: =IF(FL43="","",1/(FL43+0.01)) | FL43: =IF(FI43>0,ROUNDDOWN(('Diseño estructura &CP'!$AZ$5/FI43),0),"") | FN43: Lado 28 | FP43: metros | FR43: =IFERROR(IF(FO43="",0,ROUNDDOWN(('Diseño estructura &CP'!$AZ$6/FO43),0)),0) -> 0 | FZ43: =+IF(GA43=0,"",FZ42+1) | GA43: =+GC43/$H$9 -> 0 | GB43: =ROUNDDOWN(GC43/$C$13,0) -> 0 | GD43: =IF(GB43=0,0,GB43+1) -> 0 | GE43: =IF(GF43="","",1/(GF43+0.01)) | GF43: =IF(GC43>0,ROUNDDOWN(('Diseño estructura &CP'!$AZ$5/GC43),0),"") | GH43: Lado 28 | GJ43: metros | GL43: =IFERROR(IF(GI43="",0,ROUNDDOWN(('Diseño estructura &CP'!$AZ$6/GI43),0)),0) -> 0
B44: =+IF(C44=0,"",B43+1) -> 29 | C44: =+E44/$H$9 -> 49.5 | D44: =ROUNDDOWN(E44/$C$13,0) -> 8 | E44: 99 | F44: =IF(D44=0,0,D44+1) -> 9 | G44: =IF(H44="","",1/(H44+0.01)) -> 0.0999001 | H44: =IF(E44>0,ROUNDDOWN(('Diseño estructura &CP'!$AZ$5/E44),0),"") -> 10 | J44: Lado 29 | L44: metros | N44: =IFERROR(IF(K44="",0,ROUNDDOWN(('Diseño estructura &CP'!$AZ$6/K44),0)),0) -> 0 | V44: =+IF(W44=0,"",V43+1) -> 29 | W44: =+Y44/$H$9 -> 88.25 | X44: =ROUNDDOWN(Y44/$C$13,0) -> 14 | Y44: 176.5 | Z44: =IF(X44=0,0,X44+1) -> 15 | AA44: =IF(AB44="","",1/(AB44+0.01)) -> 0.1996008 | AB44: =IF(Y44>0,ROUNDDOWN(('Diseño estructura &CP'!$AZ$5/Y44),0),"") -> 5 | AD44: Lado 29 | AF44: metros | AH44: =IFERROR(IF(AE44="",0,ROUNDDOWN(('Diseño estructura &CP'!$AZ$6/AE44),0)),0) -> 0 | AP44: =+IF(AQ44=0,"",AP43+1) -> 29 | AQ44: =+AS44/$H$9 -> 81 | AR44: =ROUNDDOWN(AS44/$C$13,0) -> 13 | AS44: 162 | AT44: =IF(AR44=0,0,AR44+1) -> 14 | AU44: =IF(AV44="","",1/(AV44+0.01)) -> 0.16638935 | AV44: =IF(AS44>0,ROUNDDOWN(('Diseño estructura &CP'!$AZ$5/AS44),0),"") -> 6 | AX44: Lado 29 | AZ44: metros | BB44: =IFERROR(IF(AY44="",0,ROUNDDOWN(('Diseño estructura &CP'!$AZ$6/AY44),0)),0) -> 0 | BJ44: =+IF(BK44=0,"",BJ43+1) -> 29 | BK44: =+BM44/$H$9 -> 9.5 | BL44: =ROUNDDOWN(BM44/$BK$13,0) -> 1 | BM44: 19 | BN44: =IF(BL44=0,0,BL44+1) -> 2 | BO44: =IF(BP44="","",1/(BP44+0.01)) -> 0.019227072 | BP44: =IF(BM44>0,ROUNDDOWN(('Diseño estructura &CP'!$AZ$5/BM44),0),"") -> 52 | BR44: Lado 29 | BT44: metros | BV44: =IFERROR(IF(BS44="",0,ROUNDDOWN(('Diseño estructura &CP'!$AZ$6/BS44),0)),0) -> 0 | CD44: =+IF(CE44=0,"",CD43+1) | CE44: =+CG44/$H$9 -> 0 | CF44: =ROUNDDOWN(CG44/$C$13,0) -> 0 | CH44: =IF(CF44=0,0,CF44+1) -> 0 | CI44: =IF(CJ44="","",1/(CJ44+0.01)) | CJ44: =IF(CG44>0,ROUNDDOWN(('Diseño estructura &CP'!$AZ$5/CG44),0),"") | CL44: Lado 29 | CN44: metros | CP44: =IFERROR(IF(CM44="",0,ROUNDDOWN(('Diseño estructura &CP'!$AZ$6/CM44),0)),0) -> 0 | CX44: =+IF(CY44=0,"",CX43+1) | CY44: =+DA44/$H$9 -> 0 | CZ44: =ROUNDDOWN(DA44/$C$13,0) -> 0 | DB44: =IF(CZ44=0,0,CZ44+1) -> 0 | DC44: =IF(DD44="","",1/(DD44+0.01)) | DD44: =IF(DA44>0,ROUNDDOWN(('Diseño estructura &CP'!$AZ$5/DA44),0),"") | DF44: Lado 29 | DH44: metros | DJ44: =IFERROR(IF(DG44="",0,ROUNDDOWN(('Diseño estructura &CP'!$AZ$6/DG44),0)),0) -> 0 | DR44: =+IF(DS44=0,"",DR43+1) | DS44: =+DU44/$H$9 -> 0 | DT44: =ROUNDDOWN(DU44/$C$13,0) -> 0 | DV44: =IF(DT44=0,0,DT44+1) -> 0 | DW44: =IF(DX44="","",1/(DX44+0.01)) | DX44: =IF(DU44>0,ROUNDDOWN(('Diseño estructura &CP'!$AZ$5/DU44),0),"") | DZ44: Lado 29 | EB44: metros | ED44: =IFERROR(IF(EA44="",0,ROUNDDOWN(('Diseño estructura &CP'!$AZ$6/EA44),0)),0) -> 0 | EL44: =+IF(EM44=0,"",EL43+1) | EM44: =+EO44/$H$9 -> 0 | EN44: =ROUNDDOWN(EO44/$C$13,0) -> 0 | EP44: =IF(EN44=0,0,EN44+1) -> 0 | EQ44: =IF(ER44="","",1/(ER44+0.01)) | ER44: =IF(EO44>0,ROUNDDOWN(('Diseño estructura &CP'!$AZ$5/EO44),0),"") | ET44: Lado 29 | EV44: metros | EX44: =IFERROR(IF(EU44="",0,ROUNDDOWN(('Diseño estructura &CP'!$AZ$6/EU44),0)),0) -> 0 | FF44: =+IF(FG44=0,"",FF43+1) | FG44: =+FI44/$H$9 -> 0 | FH44: =ROUNDDOWN(FI44/$C$13,0) -> 0 | FJ44: =IF(FH44=0,0,FH44+1) -> 0 | FK44: =IF(FL44="","",1/(FL44+0.01)) | FL44: =IF(FI44>0,ROUNDDOWN(('Diseño estructura &CP'!$AZ$5/FI44),0),"") | FN44: Lado 29 | FP44: metros | FR44: =IFERROR(IF(FO44="",0,ROUNDDOWN(('Diseño estructura &CP'!$AZ$6/FO44),0)),0) -> 0 | FZ44: =+IF(GA44=0,"",FZ43+1) | GA44: =+GC44/$H$9 -> 0 | GB44: =ROUNDDOWN(GC44/$C$13,0) -> 0 | GD44: =IF(GB44=0,0,GB44+1) -> 0 | GE44: =IF(GF44="","",1/(GF44+0.01)) | GF44: =IF(GC44>0,ROUNDDOWN(('Diseño estructura &CP'!$AZ$5/GC44),0),"") | GH44: Lado 29 | GJ44: metros | GL44: =IFERROR(IF(GI44="",0,ROUNDDOWN(('Diseño estructura &CP'!$AZ$6/GI44),0)),0) -> 0
B45: =+IF(C45=0,"",B44+1) -> 30 | C45: =+E45/$H$9 -> 51 | D45: =ROUNDDOWN(E45/$C$13,0) -> 8 | E45: 102 | F45: =IF(D45=0,0,D45+1) -> 9 | G45: =IF(H45="","",1/(H45+0.01)) -> 0.11098779 | H45: =IF(E45>0,ROUNDDOWN(('Diseño estructura &CP'!$AZ$5/E45),0),"") -> 9 | J45: Lado 30 | L45: metros | N45: =IFERROR(IF(K45="",0,ROUNDDOWN(('Diseño estructura &CP'!$AZ$6/K45),0)),0) -> 0 | V45: =+IF(W45=0,"",V44+1) -> 30 | W45: =+Y45/$H$9 -> 87.5 | X45: =ROUNDDOWN(Y45/$C$13,0) -> 14 | Y45: 175 | Z45: =IF(X45=0,0,X45+1) -> 15 | AA45: =IF(AB45="","",1/(AB45+0.01)) -> 0.1996008 | AB45: =IF(Y45>0,ROUNDDOWN(('Diseño estructura &CP'!$AZ$5/Y45),0),"") -> 5 | AD45: Lado 30 | AF45: metros | AH45: =IFERROR(IF(AE45="",0,ROUNDDOWN(('Diseño estructura &CP'!$AZ$6/AE45),0)),0) -> 0 | AP45: =+IF(AQ45=0,"",AP44+1) -> 30 | AQ45: =+AS45/$H$9 -> 81 | AR45: =ROUNDDOWN(AS45/$C$13,0) -> 13 | AS45: 162 | AT45: =IF(AR45=0,0,AR45+1) -> 14 | AU45: =IF(AV45="","",1/(AV45+0.01)) -> 0.16638935 | AV45: =IF(AS45>0,ROUNDDOWN(('Diseño estructura &CP'!$AZ$5/AS45),0),"") -> 6 | AX45: Lado 30 | AZ45: metros | BB45: =IFERROR(IF(AY45="",0,ROUNDDOWN(('Diseño estructura &CP'!$AZ$6/AY45),0)),0) -> 0 | BJ45: =+IF(BK45=0,"",BJ44+1) -> 30 | BK45: =+BM45/$H$9 -> 5.75 | BL45: =ROUNDDOWN(BM45/$BK$13,0) -> 1 | BM45: 11.5 | BN45: =IF(BL45=0,0,BL45+1) -> 2 | BO45: =IF(BP45="","",1/(BP45+0.01)) -> 0.011626555 | BP45: =IF(BM45>0,ROUNDDOWN(('Diseño estructura &CP'!$AZ$5/BM45),0),"") -> 86 | BR45: Lado 30 | BT45: metros | BV45: =IFERROR(IF(BS45="",0,ROUNDDOWN(('Diseño estructura &CP'!$AZ$6/BS45),0)),0) -> 0 | CD45: =+IF(CE45=0,"",CD44+1) | CE45: =+CG45/$H$9 -> 0 | CF45: =ROUNDDOWN(CG45/$C$13,0) -> 0 | CH45: =IF(CF45=0,0,CF45+1) -> 0 | CI45: =IF(CJ45="","",1/(CJ45+0.01)) | CJ45: =IF(CG45>0,ROUNDDOWN(('Diseño estructura &CP'!$AZ$5/CG45),0),"") | CL45: Lado 30 | CN45: metros | CP45: =IFERROR(IF(CM45="",0,ROUNDDOWN(('Diseño estructura &CP'!$AZ$6/CM45),0)),0) -> 0 | CX45: =+IF(CY45=0,"",CX44+1) | CY45: =+DA45/$H$9 -> 0 | CZ45: =ROUNDDOWN(DA45/$C$13,0) -> 0 | DB45: =IF(CZ45=0,0,CZ45+1) -> 0 | DC45: =IF(DD45="","",1/(DD45+0.01)) | DD45: =IF(DA45>0,ROUNDDOWN(('Diseño estructura &CP'!$AZ$5/DA45),0),"") | DF45: Lado 30 | DH45: metros | DJ45: =IFERROR(IF(DG45="",0,ROUNDDOWN(('Diseño estructura &CP'!$AZ$6/DG45),0)),0) -> 0 | DR45: =+IF(DS45=0,"",DR44+1) | DS45: =+DU45/$H$9 -> 0 | DT45: =ROUNDDOWN(DU45/$C$13,0) -> 0 | DV45: =IF(DT45=0,0,DT45+1) -> 0 | DW45: =IF(DX45="","",1/(DX45+0.01)) | DX45: =IF(DU45>0,ROUNDDOWN(('Diseño estructura &CP'!$AZ$5/DU45),0),"") | DZ45: Lado 30 | EB45: metros | ED45: =IFERROR(IF(EA45="",0,ROUNDDOWN(('Diseño estructura &CP'!$AZ$6/EA45),0)),0) -> 0 | EL45: =+IF(EM45=0,"",EL44+1) | EM45: =+EO45/$H$9 -> 0 | EN45: =ROUNDDOWN(EO45/$C$13,0) -> 0 | EP45: =IF(EN45=0,0,EN45+1) -> 0 | EQ45: =IF(ER45="","",1/(ER45+0.01)) | ER45: =IF(EO45>0,ROUNDDOWN(('Diseño estructura &CP'!$AZ$5/EO45),0),"") | ET45: Lado 30 | EV45: metros | EX45: =IFERROR(IF(EU45="",0,ROUNDDOWN(('Diseño estructura &CP'!$AZ$6/EU45),0)),0) -> 0 | FF45: =+IF(FG45=0,"",FF44+1) | FG45: =+FI45/$H$9 -> 0 | FH45: =ROUNDDOWN(FI45/$C$13,0) -> 0 | FJ45: =IF(FH45=0,0,FH45+1) -> 0 | FK45: =IF(FL45="","",1/(FL45+0.01)) | FL45: =IF(FI45>0,ROUNDDOWN(('Diseño estructura &CP'!$AZ$5/FI45),0),"") | FN45: Lado 30 | FP45: metros | FR45: =IFERROR(IF(FO45="",0,ROUNDDOWN(('Diseño estructura &CP'!$AZ$6/FO45),0)),0) -> 0 | FZ45: =+IF(GA45=0,"",FZ44+1) | GA45: =+GC45/$H$9 -> 0 | GB45: =ROUNDDOWN(GC45/$C$13,0) -> 0 | GD45: =IF(GB45=0,0,GB45+1) -> 0 | GE45: =IF(GF45="","",1/(GF45+0.01)) | GF45: =IF(GC45>0,ROUNDDOWN(('Diseño estructura &CP'!$AZ$5/GC45),0),"") | GH45: Lado 30 | GJ45: metros | GL45: =IFERROR(IF(GI45="",0,ROUNDDOWN(('Diseño estructura &CP'!$AZ$6/GI45),0)),0) -> 0
B46: =+IF(C46=0,"",B45+1) -> 31 | C46: =+E46/$H$9 -> 52.5 | D46: =ROUNDDOWN(E46/$C$13,0) -> 8 | E46: 105 | F46: =IF(D46=0,0,D46+1) -> 9 | G46: =IF(H46="","",1/(H46+0.01)) -> 0.11098779 | H46: =IF(E46>0,ROUNDDOWN(('Diseño estructura &CP'!$AZ$5/E46),0),"") -> 9 | J46: Lado 31 | L46: metros | N46: =IFERROR(IF(K46="",0,ROUNDDOWN(('Diseño estructura &CP'!$AZ$6/K46),0)),0) -> 0 | V46: =+IF(W46=0,"",V45+1) -> 31 | W46: =+Y46/$H$9 -> 86 | X46: =ROUNDDOWN(Y46/$C$13,0) -> 14 | Y46: 172 | Z46: =IF(X46=0,0,X46+1) -> 15 | AA46: =IF(AB46="","",1/(AB46+0.01)) -> 0.1996008 | AB46: =IF(Y46>0,ROUNDDOWN(('Diseño estructura &CP'!$AZ$5/Y46),0),"") -> 5 | AD46: Lado 31 | AF46: metros | AH46: =IFERROR(IF(AE46="",0,ROUNDDOWN(('Diseño estructura &CP'!$AZ$6/AE46),0)),0) -> 0 | AP46: =+IF(AQ46=0,"",AP45+1) -> 31 | AQ46: =+AS46/$H$9 -> 81.5 | AR46: =ROUNDDOWN(AS46/$C$13,0) -> 13 | AS46: 163 | AT46: =IF(AR46=0,0,AR46+1) -> 14 | AU46: =IF(AV46="","",1/(AV46+0.01)) -> 0.16638935 | AV46: =IF(AS46>0,ROUNDDOWN(('Diseño estructura &CP'!$AZ$5/AS46),0),"") -> 6 | AX46: Lado 31 | AZ46: metros | BB46: =IFERROR(IF(AY46="",0,ROUNDDOWN(('Diseño estructura &CP'!$AZ$6/AY46),0)),0) -> 0 | BJ46: =+IF(BK46=0,"",BJ45+1) | BK46: =+BM46/$H$9 -> 0 | BL46: =ROUNDDOWN(BM46/$BK$13,0) -> 0 | BN46: =IF(BL46=0,0,BL46+1) -> 0 | BO46: =IF(BP46="","",1/(BP46+0.01)) | BP46: =IF(BM46>0,ROUNDDOWN(('Diseño estructura &CP'!$AZ$5/BM46),0),"") | BR46: Lado 31 | BT46: metros | BV46: =IFERROR(IF(BS46="",0,ROUNDDOWN(('Diseño estructura &CP'!$AZ$6/BS46),0)),0) -> 0 | CD46: =+IF(CE46=0,"",CD45+1) | CE46: =+CG46/$H$9 -> 0 | CF46: =ROUNDDOWN(CG46/$C$13,0) -> 0 | CH46: =IF(CF46=0,0,CF46+1) -> 0 | CI46: =IF(CJ46="","",1/(CJ46+0.01)) | CJ46: =IF(CG46>0,ROUNDDOWN(('Diseño estructura &CP'!$AZ$5/CG46),0),"") | CL46: Lado 31 | CN46: metros | CP46: =IFERROR(IF(CM46="",0,ROUNDDOWN(('Diseño estructura &CP'!$AZ$6/CM46),0)),0) -> 0 | CX46: =+IF(CY46=0,"",CX45+1) | CY46: =+DA46/$H$9 -> 0 | CZ46: =ROUNDDOWN(DA46/$C$13,0) -> 0 | DB46: =IF(CZ46=0,0,CZ46+1) -> 0 | DC46: =IF(DD46="","",1/(DD46+0.01)) | DD46: =IF(DA46>0,ROUNDDOWN(('Diseño estructura &CP'!$AZ$5/DA46),0),"") | DF46: Lado 31 | DH46: metros | DJ46: =IFERROR(IF(DG46="",0,ROUNDDOWN(('Diseño estructura &CP'!$AZ$6/DG46),0)),0) -> 0 | DR46: =+IF(DS46=0,"",DR45+1) | DS46: =+DU46/$H$9 -> 0 | DT46: =ROUNDDOWN(DU46/$C$13,0) -> 0 | DV46: =IF(DT46=0,0,DT46+1) -> 0 | DW46: =IF(DX46="","",1/(DX46+0.01)) | DX46: =IF(DU46>0,ROUNDDOWN(('Diseño estructura &CP'!$AZ$5/DU46),0),"") | DZ46: Lado 31 | EB46: metros | ED46: =IFERROR(IF(EA46="",0,ROUNDDOWN(('Diseño estructura &CP'!$AZ$6/EA46),0)),0) -> 0 | EL46: =+IF(EM46=0,"",EL45+1) | EM46: =+EO46/$H$9 -> 0 | EN46: =ROUNDDOWN(EO46/$C$13,0) -> 0 | EP46: =IF(EN46=0,0,EN46+1) -> 0 | EQ46: =IF(ER46="","",1/(ER46+0.01)) | ER46: =IF(EO46>0,ROUNDDOWN(('Diseño estructura &CP'!$AZ$5/EO46),0),"") | ET46: Lado 31 | EV46: metros | EX46: =IFERROR(IF(EU46="",0,ROUNDDOWN(('Diseño estructura &CP'!$AZ$6/EU46),0)),0) -> 0 | FF46: =+IF(FG46=0,"",FF45+1) | FG46: =+FI46/$H$9 -> 0 | FH46: =ROUNDDOWN(FI46/$C$13,0) -> 0 | FJ46: =IF(FH46=0,0,FH46+1) -> 0 | FK46: =IF(FL46="","",1/(FL46+0.01)) | FL46: =IF(FI46>0,ROUNDDOWN(('Diseño estructura &CP'!$AZ$5/FI46),0),"") | FN46: Lado 31 | FP46: metros | FR46: =IFERROR(IF(FO46="",0,ROUNDDOWN(('Diseño estructura &CP'!$AZ$6/FO46),0)),0) -> 0 | FZ46: =+IF(GA46=0,"",FZ45+1) | GA46: =+GC46/$H$9 -> 0 | GB46: =ROUNDDOWN(GC46/$C$13,0) -> 0 | GD46: =IF(GB46=0,0,GB46+1) -> 0 | GE46: =IF(GF46="","",1/(GF46+0.01)) | GF46: =IF(GC46>0,ROUNDDOWN(('Diseño estructura &CP'!$AZ$5/GC46),0),"") | GH46: Lado 31 | GJ46: metros | GL46: =IFERROR(IF(GI46="",0,ROUNDDOWN(('Diseño estructura &CP'!$AZ$6/GI46),0)),0) -> 0
B47: =+IF(C47=0,"",B46+1) -> 32 | C47: =+E47/$H$9 -> 52.75 | D47: =ROUNDDOWN(E47/$C$13,0) -> 8 | E47: 105.5 | F47: =IF(D47=0,0,D47+1) -> 9 | G47: =IF(H47="","",1/(H47+0.01)) -> 0.11098779 | H47: =IF(E47>0,ROUNDDOWN(('Diseño estructura &CP'!$AZ$5/E47),0),"") -> 9 | J47: Lado 32 | L47: metros | N47: =IFERROR(IF(K47="",0,ROUNDDOWN(('Diseño estructura &CP'!$AZ$6/K47),0)),0) -> 0 | V47: =+IF(W47=0,"",V46+1) -> 32 | W47: =+Y47/$H$9 -> 85 | X47: =ROUNDDOWN(Y47/$C$13,0) -> 14 | Y47: 170 | Z47: =IF(X47=0,0,X47+1) -> 15 | AA47: =IF(AB47="","",1/(AB47+0.01)) -> 0.1996008 | AB47: =IF(Y47>0,ROUNDDOWN(('Diseño estructura &CP'!$AZ$5/Y47),0),"") -> 5 | AD47: Lado 32 | AF47: metros | AH47: =IFERROR(IF(AE47="",0,ROUNDDOWN(('Diseño estructura &CP'!$AZ$6/AE47),0)),0) -> 0 | AP47: =+IF(AQ47=0,"",AP46+1) -> 32 | AQ47: =+AS47/$H$9 -> 81.5 | AR47: =ROUNDDOWN(AS47/$C$13,0) -> 13 | AS47: 163 | AT47: =IF(AR47=0,0,AR47+1) -> 14 | AU47: =IF(AV47="","",1/(AV47+0.01)) -> 0.16638935 | AV47: =IF(AS47>0,ROUNDDOWN(('Diseño estructura &CP'!$AZ$5/AS47),0),"") -> 6 | AX47: Lado 32 | AZ47: metros | BB47: =IFERROR(IF(AY47="",0,ROUNDDOWN(('Diseño estructura &CP'!$AZ$6/AY47),0)),0) -> 0 | BJ47: =+IF(BK47=0,"",BJ46+1) | BK47: =+BM47/$H$9 -> 0 | BL47: =ROUNDDOWN(BM47/$BK$13,0) -> 0 | BN47: =IF(BL47=0,0,BL47+1) -> 0 | BO47: =IF(BP47="","",1/(BP47+0.01)) | BP47: =IF(BM47>0,ROUNDDOWN(('Diseño estructura &CP'!$AZ$5/BM47),0),"") | BR47: Lado 32 | BT47: metros | BV47: =IFERROR(IF(BS47="",0,ROUNDDOWN(('Diseño estructura &CP'!$AZ$6/BS47),0)),0) -> 0 | CD47: =+IF(CE47=0,"",CD46+1) | CE47: =+CG47/$H$9 -> 0 | CF47: =ROUNDDOWN(CG47/$C$13,0) -> 0 | CH47: =IF(CF47=0,0,CF47+1) -> 0 | CI47: =IF(CJ47="","",1/(CJ47+0.01)) | CJ47: =IF(CG47>0,ROUNDDOWN(('Diseño estructura &CP'!$AZ$5/CG47),0),"") | CL47: Lado 32 | CN47: metros | CP47: =IFERROR(IF(CM47="",0,ROUNDDOWN(('Diseño estructura &CP'!$AZ$6/CM47),0)),0) -> 0 | CX47: =+IF(CY47=0,"",CX46+1) | CY47: =+DA47/$H$9 -> 0 | CZ47: =ROUNDDOWN(DA47/$C$13,0) -> 0 | DB47: =IF(CZ47=0,0,CZ47+1) -> 0 | DC47: =IF(DD47="","",1/(DD47+0.01)) | DD47: =IF(DA47>0,ROUNDDOWN(('Diseño estructura &CP'!$AZ$5/DA47),0),"") | DF47: Lado 32 | DH47: metros | DJ47: =IFERROR(IF(DG47="",0,ROUNDDOWN(('Diseño estructura &CP'!$AZ$6/DG47),0)),0) -> 0 | DR47: =+IF(DS47=0,"",DR46+1) | DS47: =+DU47/$H$9 -> 0 | DT47: =ROUNDDOWN(DU47/$C$13,0) -> 0 | DV47: =IF(DT47=0,0,DT47+1) -> 0 | DW47: =IF(DX47="","",1/(DX47+0.01)) | DX47: =IF(DU47>0,ROUNDDOWN(('Diseño estructura &CP'!$AZ$5/DU47),0),"") | DZ47: Lado 32 | EB47: metros | ED47: =IFERROR(IF(EA47="",0,ROUNDDOWN(('Diseño estructura &CP'!$AZ$6/EA47),0)),0) -> 0 | EL47: =+IF(EM47=0,"",EL46+1) | EM47: =+EO47/$H$9 -> 0 | EN47: =ROUNDDOWN(EO47/$C$13,0) -> 0 | EP47: =IF(EN47=0,0,EN47+1) -> 0 | EQ47: =IF(ER47="","",1/(ER47+0.01)) | ER47: =IF(EO47>0,ROUNDDOWN(('Diseño estructura &CP'!$AZ$5/EO47),0),"") | ET47: Lado 32 | EV47: metros | EX47: =IFERROR(IF(EU47="",0,ROUNDDOWN(('Diseño estructura &CP'!$AZ$6/EU47),0)),0) -> 0 | FF47: =+IF(FG47=0,"",FF46+1) | FG47: =+FI47/$H$9 -> 0 | FH47: =ROUNDDOWN(FI47/$C$13,0) -> 0 | FJ47: =IF(FH47=0,0,FH47+1) -> 0 | FK47: =IF(FL47="","",1/(FL47+0.01)) | FL47: =IF(FI47>0,ROUNDDOWN(('Diseño estructura &CP'!$AZ$5/FI47),0),"") | FN47: Lado 32 | FP47: metros | FR47: =IFERROR(IF(FO47="",0,ROUNDDOWN(('Diseño estructura &CP'!$AZ$6/FO47),0)),0) -> 0 | FZ47: =+IF(GA47=0,"",FZ46+1) | GA47: =+GC47/$H$9 -> 0 | GB47: =ROUNDDOWN(GC47/$C$13,0) -> 0 | GD47: =IF(GB47=0,0,GB47+1) -> 0 | GE47: =IF(GF47="","",1/(GF47+0.01)) | GF47: =IF(GC47>0,ROUNDDOWN(('Diseño estructura &CP'!$AZ$5/GC47),0),"") | GH47: Lado 32 | GJ47: metros | GL47: =IFERROR(IF(GI47="",0,ROUNDDOWN(('Diseño estructura &CP'!$AZ$6/GI47),0)),0) -> 0
B48: =+IF(C48=0,"",B47+1) -> 33 | C48: =+E48/$H$9 -> 54.5 | D48: =ROUNDDOWN(E48/$C$13,0) -> 9 | E48: 109 | F48: =IF(D48=0,0,D48+1) -> 10 | G48: =IF(H48="","",1/(H48+0.01)) -> 0.11098779 | H48: =IF(E48>0,ROUNDDOWN(('Diseño estructura &CP'!$AZ$5/E48),0),"") -> 9 | J48: Lado 33 | L48: metros | N48: =IFERROR(IF(K48="",0,ROUNDDOWN(('Diseño estructura &CP'!$AZ$6/K48),0)),0) -> 0 | V48: =+IF(W48=0,"",V47+1) -> 33 | W48: =+Y48/$H$9 -> 83.75 | X48: =ROUNDDOWN(Y48/$C$13,0) -> 13 | Y48: 167.5 | Z48: =IF(X48=0,0,X48+1) -> 14 | AA48: =IF(AB48="","",1/(AB48+0.01)) -> 0.1996008 | AB48: =IF(Y48>0,ROUNDDOWN(('Diseño estructura &CP'!$AZ$5/Y48),0),"") -> 5 | AD48: Lado 33 | AF48: metros | AH48: =IFERROR(IF(AE48="",0,ROUNDDOWN(('Diseño estructura &CP'!$AZ$6/AE48),0)),0) -> 0 | AP48: =+IF(AQ48=0,"",AP47+1) -> 33 | AQ48: =+AS48/$H$9 -> 81 | AR48: =ROUNDDOWN(AS48/$C$13,0) -> 13 | AS48: 162 | AT48: =IF(AR48=0,0,AR48+1) -> 14 | AU48: =IF(AV48="","",1/(AV48+0.01)) -> 0.16638935 | AV48: =IF(AS48>0,ROUNDDOWN(('Diseño estructura &CP'!$AZ$5/AS48),0),"") -> 6 | AX48: Lado 33 | AZ48: metros | BB48: =IFERROR(IF(AY48="",0,ROUNDDOWN(('Diseño estructura &CP'!$AZ$6/AY48),0)),0) -> 0 | BJ48: =+IF(BK48=0,"",BJ47+1) | BK48: =+BM48/$H$9 -> 0 | BL48: =ROUNDDOWN(BM48/$BK$13,0) -> 0 | BN48: =IF(BL48=0,0,BL48+1) -> 0 | BO48: =IF(BP48="","",1/(BP48+0.01)) | BP48: =IF(BM48>0,ROUNDDOWN(('Diseño estructura &CP'!$AZ$5/BM48),0),"") | BR48: Lado 33 | BT48: metros | BV48: =IFERROR(IF(BS48="",0,ROUNDDOWN(('Diseño estructura &CP'!$AZ$6/BS48),0)),0) -> 0 | CD48: =+IF(CE48=0,"",CD47+1) | CE48: =+CG48/$H$9 -> 0 | CF48: =ROUNDDOWN(CG48/$C$13,0) -> 0 | CH48: =IF(CF48=0,0,CF48+1) -> 0 | CI48: =IF(CJ48="","",1/(CJ48+0.01)) | CJ48: =IF(CG48>0,ROUNDDOWN(('Diseño estructura &CP'!$AZ$5/CG48),0),"") | CL48: Lado 33 | CN48: metros | CP48: =IFERROR(IF(CM48="",0,ROUNDDOWN(('Diseño estructura &CP'!$AZ$6/CM48),0)),0) -> 0 | CX48: =+IF(CY48=0,"",CX47+1) | CY48: =+DA48/$H$9 -> 0 | CZ48: =ROUNDDOWN(DA48/$C$13,0) -> 0 | DB48: =IF(CZ48=0,0,CZ48+1) -> 0 | DC48: =IF(DD48="","",1/(DD48+0.01)) | DD48: =IF(DA48>0,ROUNDDOWN(('Diseño estructura &CP'!$AZ$5/DA48),0),"") | DF48: Lado 33 | DH48: metros | DJ48: =IFERROR(IF(DG48="",0,ROUNDDOWN(('Diseño estructura &CP'!$AZ$6/DG48),0)),0) -> 0 | DR48: =+IF(DS48=0,"",DR47+1) | DS48: =+DU48/$H$9 -> 0 | DT48: =ROUNDDOWN(DU48/$C$13,0) -> 0 | DV48: =IF(DT48=0,0,DT48+1) -> 0 | DW48: =IF(DX48="","",1/(DX48+0.01)) | DX48: =IF(DU48>0,ROUNDDOWN(('Diseño estructura &CP'!$AZ$5/DU48),0),"") | DZ48: Lado 33 | EB48: metros | ED48: =IFERROR(IF(EA48="",0,ROUNDDOWN(('Diseño estructura &CP'!$AZ$6/EA48),0)),0) -> 0 | EL48: =+IF(EM48=0,"",EL47+1) | EM48: =+EO48/$H$9 -> 0 | EN48: =ROUNDDOWN(EO48/$C$13,0) -> 0 | EP48: =IF(EN48=0,0,EN48+1) -> 0 | EQ48: =IF(ER48="","",1/(ER48+0.01)) | ER48: =IF(EO48>0,ROUNDDOWN(('Diseño estructura &CP'!$AZ$5/EO48),0),"") | ET48: Lado 33 | EV48: metros | EX48: =IFERROR(IF(EU48="",0,ROUNDDOWN(('Diseño estructura &CP'!$AZ$6/EU48),0)),0) -> 0 | FF48: =+IF(FG48=0,"",FF47+1) | FG48: =+FI48/$H$9 -> 0 | FH48: =ROUNDDOWN(FI48/$C$13,0) -> 0 | FJ48: =IF(FH48=0,0,FH48+1) -> 0 | FK48: =IF(FL48="","",1/(FL48+0.01)) | FL48: =IF(FI48>0,ROUNDDOWN(('Diseño estructura &CP'!$AZ$5/FI48),0),"") | FN48: Lado 33 | FP48: metros | FR48: =IFERROR(IF(FO48="",0,ROUNDDOWN(('Diseño estructura &CP'!$AZ$6/FO48),0)),0) -> 0 | FZ48: =+IF(GA48=0,"",FZ47+1) | GA48: =+GC48/$H$9 -> 0 | GB48: =ROUNDDOWN(GC48/$C$13,0) -> 0 | GD48: =IF(GB48=0,0,GB48+1) -> 0 | GE48: =IF(GF48="","",1/(GF48+0.01)) | GF48: =IF(GC48>0,ROUNDDOWN(('Diseño estructura &CP'!$AZ$5/GC48),0),"") | GH48: Lado 33 | GJ48: metros | GL48: =IFERROR(IF(GI48="",0,ROUNDDOWN(('Diseño estructura &CP'!$AZ$6/GI48),0)),0) -> 0
B49: =+IF(C49=0,"",B48+1) -> 34 | C49: =+E49/$H$9 -> 55.5 | D49: =ROUNDDOWN(E49/$C$13,0) -> 9 | E49: 111 | F49: =IF(D49=0,0,D49+1) -> 10 | G49: =IF(H49="","",1/(H49+0.01)) -> 0.11098779 | H49: =IF(E49>0,ROUNDDOWN(('Diseño estructura &CP'!$AZ$5/E49),0),"") -> 9 | V49: =+IF(W49=0,"",V48+1) -> 34 | W49: =+Y49/$H$9 -> 81 | X49: =ROUNDDOWN(Y49/$C$13,0) -> 13 | Y49: 162 | Z49: =IF(X49=0,0,X49+1) -> 14 | AA49: =IF(AB49="","",1/(AB49+0.01)) -> 0.16638935 | AB49: =IF(Y49>0,ROUNDDOWN(('Diseño estructura &CP'!$AZ$5/Y49),0),"") -> 6 | AP49: =+IF(AQ49=0,"",AP48+1) -> 34 | AQ49: =+AS49/$H$9 -> 81 | AR49: =ROUNDDOWN(AS49/$C$13,0) -> 13 | AS49: 162 | AT49: =IF(AR49=0,0,AR49+1) -> 14 | AU49: =IF(AV49="","",1/(AV49+0.01)) -> 0.16638935 | AV49: =IF(AS49>0,ROUNDDOWN(('Diseño estructura &CP'!$AZ$5/AS49),0),"") -> 6 | BJ49: =+IF(BK49=0,"",BJ48+1) | BK49: =+BM49/$H$9 -> 0 | BL49: =ROUNDDOWN(BM49/$BK$13,0) -> 0 | BN49: =IF(BL49=0,0,BL49+1) -> 0 | BO49: =IF(BP49="","",1/(BP49+0.01)) | BP49: =IF(BM49>0,ROUNDDOWN(('Diseño estructura &CP'!$AZ$5/BM49),0),"") | CD49: =+IF(CE49=0,"",CD48+1) | CE49: =+CG49/$H$9 -> 0 | CF49: =ROUNDDOWN(CG49/$C$13,0) -> 0 | CH49: =IF(CF49=0,0,CF49+1) -> 0 | CI49: =IF(CJ49="","",1/(CJ49+0.01)) | CJ49: =IF(CG49>0,ROUNDDOWN(('Diseño estructura &CP'!$AZ$5/CG49),0),"") | CX49: =+IF(CY49=0,"",CX48+1) | CY49: =+DA49/$H$9 -> 0 | CZ49: =ROUNDDOWN(DA49/$C$13,0) -> 0 | DB49: =IF(CZ49=0,0,CZ49+1) -> 0 | DC49: =IF(DD49="","",1/(DD49+0.01)) | DD49: =IF(DA49>0,ROUNDDOWN(('Diseño estructura &CP'!$AZ$5/DA49),0),"") | DR49: =+IF(DS49=0,"",DR48+1) | DS49: =+DU49/$H$9 -> 0 | DT49: =ROUNDDOWN(DU49/$C$13,0) -> 0 | DV49: =IF(DT49=0,0,DT49+1) -> 0 | DW49: =IF(DX49="","",1/(DX49+0.01)) | DX49: =IF(DU49>0,ROUNDDOWN(('Diseño estructura &CP'!$AZ$5/DU49),0),"") | EL49: =+IF(EM49=0,"",EL48+1) | EM49: =+EO49/$H$9 -> 0 | EN49: =ROUNDDOWN(EO49/$C$13,0) -> 0 | EP49: =IF(EN49=0,0,EN49+1) -> 0 | EQ49: =IF(ER49="","",1/(ER49+0.01)) | ER49: =IF(EO49>0,ROUNDDOWN(('Diseño estructura &CP'!$AZ$5/EO49),0),"") | FF49: =+IF(FG49=0,"",FF48+1) | FG49: =+FI49/$H$9 -> 0 | FH49: =ROUNDDOWN(FI49/$C$13,0) -> 0 | FJ49: =IF(FH49=0,0,FH49+1) -> 0 | FK49: =IF(FL49="","",1/(FL49+0.01)) | FL49: =IF(FI49>0,ROUNDDOWN(('Diseño estructura &CP'!$AZ$5/FI49),0),"") | FZ49: =+IF(GA49=0,"",FZ48+1) | GA49: =+GC49/$H$9 -> 0 | GB49: =ROUNDDOWN(GC49/$C$13,0) -> 0 | GD49: =IF(GB49=0,0,GB49+1) -> 0 | GE49: =IF(GF49="","",1/(GF49+0.01)) | GF49: =IF(GC49>0,ROUNDDOWN(('Diseño estructura &CP'!$AZ$5/GC49),0),"")
B50: =+IF(C50=0,"",B49+1) -> 35 | C50: =+E50/$H$9 -> 57.5 | D50: =ROUNDDOWN(E50/$C$13,0) -> 9 | E50: 115 | F50: =IF(D50=0,0,D50+1) -> 10 | G50: =IF(H50="","",1/(H50+0.01)) -> 0.12484395 | H50: =IF(E50>0,ROUNDDOWN(('Diseño estructura &CP'!$AZ$5/E50),0),"") -> 8 | V50: =+IF(W50=0,"",V49+1) -> 35 | W50: =+Y50/$H$9 -> 78.5 | X50: =ROUNDDOWN(Y50/$C$13,0) -> 13 | Y50: 157 | Z50: =IF(X50=0,0,X50+1) -> 14 | AA50: =IF(AB50="","",1/(AB50+0.01)) -> 0.16638935 | AB50: =IF(Y50>0,ROUNDDOWN(('Diseño estructura &CP'!$AZ$5/Y50),0),"") -> 6 | AP50: =+IF(AQ50=0,"",AP49+1) -> 35 | AQ50: =+AS50/$H$9 -> 81 | AR50: =ROUNDDOWN(AS50/$C$13,0) -> 13 | AS50: 162 | AT50: =IF(AR50=0,0,AR50+1) -> 14 | AU50: =IF(AV50="","",1/(AV50+0.01)) -> 0.16638935 | AV50: =IF(AS50>0,ROUNDDOWN(('Diseño estructura &CP'!$AZ$5/AS50),0),"") -> 6 | BJ50: =+IF(BK50=0,"",BJ49+1) | BK50: =+BM50/$H$9 -> 0 | BL50: =ROUNDDOWN(BM50/$BK$13,0) -> 0 | BN50: =IF(BL50=0,0,BL50+1) -> 0 | BO50: =IF(BP50="","",1/(BP50+0.01)) | BP50: =IF(BM50>0,ROUNDDOWN(('Diseño estructura &CP'!$AZ$5/BM50),0),"") | CD50: =+IF(CE50=0,"",CD49+1) | CE50: =+CG50/$H$9 -> 0 | CF50: =ROUNDDOWN(CG50/$C$13,0) -> 0 | CH50: =IF(CF50=0,0,CF50+1) -> 0 | CI50: =IF(CJ50="","",1/(CJ50+0.01)) | CJ50: =IF(CG50>0,ROUNDDOWN(('Diseño estructura &CP'!$AZ$5/CG50),0),"") | CX50: =+IF(CY50=0,"",CX49+1) | CY50: =+DA50/$H$9 -> 0 | CZ50: =ROUNDDOWN(DA50/$C$13,0) -> 0 | DB50: =IF(CZ50=0,0,CZ50+1) -> 0 | DC50: =IF(DD50="","",1/(DD50+0.01)) | DD50: =IF(DA50>0,ROUNDDOWN(('Diseño estructura &CP'!$AZ$5/DA50),0),"") | DR50: =+IF(DS50=0,"",DR49+1) | DS50: =+DU50/$H$9 -> 0 | DT50: =ROUNDDOWN(DU50/$C$13,0) -> 0 | DV50: =IF(DT50=0,0,DT50+1) -> 0 | DW50: =IF(DX50="","",1/(DX50+0.01)) | DX50: =IF(DU50>0,ROUNDDOWN(('Diseño estructura &CP'!$AZ$5/DU50),0),"") | EL50: =+IF(EM50=0,"",EL49+1) | EM50: =+EO50/$H$9 -> 0 | EN50: =ROUNDDOWN(EO50/$C$13,0) -> 0 | EP50: =IF(EN50=0,0,EN50+1) -> 0 | EQ50: =IF(ER50="","",1/(ER50+0.01)) | ER50: =IF(EO50>0,ROUNDDOWN(('Diseño estructura &CP'!$AZ$5/EO50),0),"") | FF50: =+IF(FG50=0,"",FF49+1) | FG50: =+FI50/$H$9 -> 0 | FH50: =ROUNDDOWN(FI50/$C$13,0) -> 0 | FJ50: =IF(FH50=0,0,FH50+1) -> 0 | FK50: =IF(FL50="","",1/(FL50+0.01)) | FL50: =IF(FI50>0,ROUNDDOWN(('Diseño estructura &CP'!$AZ$5/FI50),0),"") | FZ50: =+IF(GA50=0,"",FZ49+1) | GA50: =+GC50/$H$9 -> 0 | GB50: =ROUNDDOWN(GC50/$C$13,0) -> 0 | GD50: =IF(GB50=0,0,GB50+1) -> 0 | GE50: =IF(GF50="","",1/(GF50+0.01)) | GF50: =IF(GC50>0,ROUNDDOWN(('Diseño estructura &CP'!$AZ$5/GC50),0),"")
B51: =+IF(C51=0,"",B50+1) -> 36 | C51: =+E51/$H$9 -> 59.5 | D51: =ROUNDDOWN(E51/$C$13,0) -> 9 | E51: 119 | F51: =IF(D51=0,0,D51+1) -> 10 | G51: =IF(H51="","",1/(H51+0.01)) -> 0.12484395 | H51: =IF(E51>0,ROUNDDOWN(('Diseño estructura &CP'!$AZ$5/E51),0),"") -> 8 | V51: =+IF(W51=0,"",V50+1) -> 36 | W51: =+Y51/$H$9 -> 74.5 | X51: =ROUNDDOWN(Y51/$C$13,0) -> 12 | Y51: 149 | Z51: =IF(X51=0,0,X51+1) -> 13 | AA51: =IF(AB51="","",1/(AB51+0.01)) -> 0.16638935 | AB51: =IF(Y51>0,ROUNDDOWN(('Diseño estructura &CP'!$AZ$5/Y51),0),"") -> 6 | AP51: =+IF(AQ51=0,"",AP50+1) -> 36 | AQ51: =+AS51/$H$9 -> 81 | AR51: =ROUNDDOWN(AS51/$C$13,0) -> 13 | AS51: 162 | AT51: =IF(AR51=0,0,AR51+1) -> 14 | AU51: =IF(AV51="","",1/(AV51+0.01)) -> 0.16638935 | AV51: =IF(AS51>0,ROUNDDOWN(('Diseño estructura &CP'!$AZ$5/AS51),0),"") -> 6 | BJ51: =+IF(BK51=0,"",BJ50+1) | BK51: =+BM51/$H$9 -> 0 | BL51: =ROUNDDOWN(BM51/$BK$13,0) -> 0 | BN51: =IF(BL51=0,0,BL51+1) -> 0 | BO51: =IF(BP51="","",1/(BP51+0.01)) | BP51: =IF(BM51>0,ROUNDDOWN(('Diseño estructura &CP'!$AZ$5/BM51),0),"") | CD51: =+IF(CE51=0,"",CD50+1) | CE51: =+CG51/$H$9 -> 0 | CF51: =ROUNDDOWN(CG51/$C$13,0) -> 0 | CH51: =IF(CF51=0,0,CF51+1) -> 0 | CI51: =IF(CJ51="","",1/(CJ51+0.01)) | CJ51: =IF(CG51>0,ROUNDDOWN(('Diseño estructura &CP'!$AZ$5/CG51),0),"") | CX51: =+IF(CY51=0,"",CX50+1) | CY51: =+DA51/$H$9 -> 0 | CZ51: =ROUNDDOWN(DA51/$C$13,0) -> 0 | DB51: =IF(CZ51=0,0,CZ51+1) -> 0 | DC51: =IF(DD51="","",1/(DD51+0.01)) | DD51: =IF(DA51>0,ROUNDDOWN(('Diseño estructura &CP'!$AZ$5/DA51),0),"") | DR51: =+IF(DS51=0,"",DR50+1) | DS51: =+DU51/$H$9 -> 0 | DT51: =ROUNDDOWN(DU51/$C$13,0) -> 0 | DV51: =IF(DT51=0,0,DT51+1) -> 0 | DW51: =IF(DX51="","",1/(DX51+0.01)) | DX51: =IF(DU51>0,ROUNDDOWN(('Diseño estructura &CP'!$AZ$5/DU51),0),"") | EL51: =+IF(EM51=0,"",EL50+1) | EM51: =+EO51/$H$9 -> 0 | EN51: =ROUNDDOWN(EO51/$C$13,0) -> 0 | EP51: =IF(EN51=0,0,EN51+1) -> 0 | EQ51: =IF(ER51="","",1/(ER51+0.01)) | ER51: =IF(EO51>0,ROUNDDOWN(('Diseño estructura &CP'!$AZ$5/EO51),0),"") | FF51: =+IF(FG51=0,"",FF50+1) | FG51: =+FI51/$H$9 -> 0 | FH51: =ROUNDDOWN(FI51/$C$13,0) -> 0 | FJ51: =IF(FH51=0,0,FH51+1) -> 0 | FK51: =IF(FL51="","",1/(FL51+0.01)) | FL51: =IF(FI51>0,ROUNDDOWN(('Diseño estructura &CP'!$AZ$5/FI51),0),"") | FZ51: =+IF(GA51=0,"",FZ50+1) | GA51: =+GC51/$H$9 -> 0 | GB51: =ROUNDDOWN(GC51/$C$13,0) -> 0 | GD51: =IF(GB51=0,0,GB51+1) -> 0 | GE51: =IF(GF51="","",1/(GF51+0.01)) | GF51: =IF(GC51>0,ROUNDDOWN(('Diseño estructura &CP'!$AZ$5/GC51),0),"")
B52: =+IF(C52=0,"",B51+1) -> 37 | C52: =+E52/$H$9 -> 61 | D52: =ROUNDDOWN(E52/$C$13,0) -> 10 | E52: 122 | F52: =IF(D52=0,0,D52+1) -> 11 | G52: =IF(H52="","",1/(H52+0.01)) -> 0.12484395 | H52: =IF(E52>0,ROUNDDOWN(('Diseño estructura &CP'!$AZ$5/E52),0),"") -> 8 | V52: =+IF(W52=0,"",V51+1) -> 37 | W52: =+Y52/$H$9 -> 33.5 | X52: =ROUNDDOWN(Y52/$C$13,0) -> 5 | Y52: 67 | Z52: =IF(X52=0,0,X52+1) -> 6 | AA52: =IF(AB52="","",1/(AB52+0.01)) -> 0.071377587 | AB52: =IF(Y52>0,ROUNDDOWN(('Diseño estructura &CP'!$AZ$5/Y52),0),"") -> 14 | AP52: =+IF(AQ52=0,"",AP51+1) -> 37 | AQ52: =+AS52/$H$9 -> 81 | AR52: =ROUNDDOWN(AS52/$C$13,0) -> 13 | AS52: 162 | AT52: =IF(AR52=0,0,AR52+1) -> 14 | AU52: =IF(AV52="","",1/(AV52+0.01)) -> 0.16638935 | AV52: =IF(AS52>0,ROUNDDOWN(('Diseño estructura &CP'!$AZ$5/AS52),0),"") -> 6 | BJ52: =+IF(BK52=0,"",BJ51+1) | BK52: =+BM52/$H$9 -> 0 | BL52: =ROUNDDOWN(BM52/$BK$13,0) -> 0 | BN52: =IF(BL52=0,0,BL52+1) -> 0 | BO52: =IF(BP52="","",1/(BP52+0.01)) | BP52: =IF(BM52>0,ROUNDDOWN(('Diseño estructura &CP'!$AZ$5/BM52),0),"") | CD52: =+IF(CE52=0,"",CD51+1) | CE52: =+CG52/$H$9 -> 0 | CF52: =ROUNDDOWN(CG52/$C$13,0) -> 0 | CH52: =IF(CF52=0,0,CF52+1) -> 0 | CI52: =IF(CJ52="","",1/(CJ52+0.01)) | CJ52: =IF(CG52>0,ROUNDDOWN(('Diseño estructura &CP'!$AZ$5/CG52),0),"") | CX52: =+IF(CY52=0,"",CX51+1) | CY52: =+DA52/$H$9 -> 0 | CZ52: =ROUNDDOWN(DA52/$C$13,0) -> 0 | DB52: =IF(CZ52=0,0,CZ52+1) -> 0 | DC52: =IF(DD52="","",1/(DD52+0.01)) | DD52: =IF(DA52>0,ROUNDDOWN(('Diseño estructura &CP'!$AZ$5/DA52),0),"") | DR52: =+IF(DS52=0,"",DR51+1) | DS52: =+DU52/$H$9 -> 0 | DT52: =ROUNDDOWN(DU52/$C$13,0) -> 0 | DV52: =IF(DT52=0,0,DT52+1) -> 0 | DW52: =IF(DX52="","",1/(DX52+0.01)) | DX52: =IF(DU52>0,ROUNDDOWN(('Diseño estructura &CP'!$AZ$5/DU52),0),"") | EL52: =+IF(EM52=0,"",EL51+1) | EM52: =+EO52/$H$9 -> 0 | EN52: =ROUNDDOWN(EO52/$C$13,0) -> 0 | EP52: =IF(EN52=0,0,EN52+1) -> 0 | EQ52: =IF(ER52="","",1/(ER52+0.01)) | ER52: =IF(EO52>0,ROUNDDOWN(('Diseño estructura &CP'!$AZ$5/EO52),0),"") | FF52: =+IF(FG52=0,"",FF51+1) | FG52: =+FI52/$H$9 -> 0 | FH52: =ROUNDDOWN(FI52/$C$13,0) -> 0 | FJ52: =IF(FH52=0,0,FH52+1) -> 0 | FK52: =IF(FL52="","",1/(FL52+0.01)) | FL52: =IF(FI52>0,ROUNDDOWN(('Diseño estructura &CP'!$AZ$5/FI52),0),"") | FZ52: =+IF(GA52=0,"",FZ51+1) | GA52: =+GC52/$H$9 -> 0 | GB52: =ROUNDDOWN(GC52/$C$13,0) -> 0 | GD52: =IF(GB52=0,0,GB52+1) -> 0 | GE52: =IF(GF52="","",1/(GF52+0.01)) | GF52: =IF(GC52>0,ROUNDDOWN(('Diseño estructura &CP'!$AZ$5/GC52),0),"")
B53: =+IF(C53=0,"",B52+1) -> 38 | C53: =+E53/$H$9 -> 62 | D53: =ROUNDDOWN(E53/$C$13,0) -> 10 | E53: 124 | F53: =IF(D53=0,0,D53+1) -> 11 | G53: =IF(H53="","",1/(H53+0.01)) -> 0.12484395 | H53: =IF(E53>0,ROUNDDOWN(('Diseño estructura &CP'!$AZ$5/E53),0),"") -> 8 | V53: =+IF(W53=0,"",V52+1) -> 38 | W53: =+Y53/$H$9 -> 31 | X53: =ROUNDDOWN(Y53/$C$13,0) -> 5 | Y53: 62 | Z53: =IF(X53=0,0,X53+1) -> 6 | AA53: =IF(AB53="","",1/(AB53+0.01)) -> 0.062460962 | AB53: =IF(Y53>0,ROUNDDOWN(('Diseño estructura &CP'!$AZ$5/Y53),0),"") -> 16 | AP53: =+IF(AQ53=0,"",AP52+1) -> 38 | AQ53: =+AS53/$H$9 -> 81 | AR53: =ROUNDDOWN(AS53/$C$13,0) -> 13 | AS53: 162 | AT53: =IF(AR53=0,0,AR53+1) -> 14 | AU53: =IF(AV53="","",1/(AV53+0.01)) -> 0.16638935 | AV53: =IF(AS53>0,ROUNDDOWN(('Diseño estructura &CP'!$AZ$5/AS53),0),"") -> 6 | BJ53: =+IF(BK53=0,"",BJ52+1) | BK53: =+BM53/$H$9 -> 0 | BL53: =ROUNDDOWN(BM53/$BK$13,0) -> 0 | BN53: =IF(BL53=0,0,BL53+1) -> 0 | BO53: =IF(BP53="","",1/(BP53+0.01)) | BP53: =IF(BM53>0,ROUNDDOWN(('Diseño estructura &CP'!$AZ$5/BM53),0),"") | CD53: =+IF(CE53=0,"",CD52+1) | CE53: =+CG53/$H$9 -> 0 | CF53: =ROUNDDOWN(CG53/$C$13,0) -> 0 | CH53: =IF(CF53=0,0,CF53+1) -> 0 | CI53: =IF(CJ53="","",1/(CJ53+0.01)) | CJ53: =IF(CG53>0,ROUNDDOWN(('Diseño estructura &CP'!$AZ$5/CG53),0),"") | CX53: =+IF(CY53=0,"",CX52+1) | CY53: =+DA53/$H$9 -> 0 | CZ53: =ROUNDDOWN(DA53/$C$13,0) -> 0 | DB53: =IF(CZ53=0,0,CZ53+1) -> 0 | DC53: =IF(DD53="","",1/(DD53+0.01)) | DD53: =IF(DA53>0,ROUNDDOWN(('Diseño estructura &CP'!$AZ$5/DA53),0),"") | DR53: =+IF(DS53=0,"",DR52+1) | DS53: =+DU53/$H$9 -> 0 | DT53: =ROUNDDOWN(DU53/$C$13,0) -> 0 | DV53: =IF(DT53=0,0,DT53+1) -> 0 | DW53: =IF(DX53="","",1/(DX53+0.01)) | DX53: =IF(DU53>0,ROUNDDOWN(('Diseño estructura &CP'!$AZ$5/DU53),0),"") | EL53: =+IF(EM53=0,"",EL52+1) | EM53: =+EO53/$H$9 -> 0 | EN53: =ROUNDDOWN(EO53/$C$13,0) -> 0 | EP53: =IF(EN53=0,0,EN53+1) -> 0 | EQ53: =IF(ER53="","",1/(ER53+0.01)) | ER53: =IF(EO53>0,ROUNDDOWN(('Diseño estructura &CP'!$AZ$5/EO53),0),"") | FF53: =+IF(FG53=0,"",FF52+1) | FG53: =+FI53/$H$9 -> 0 | FH53: =ROUNDDOWN(FI53/$C$13,0) -> 0 | FJ53: =IF(FH53=0,0,FH53+1) -> 0 | FK53: =IF(FL53="","",1/(FL53+0.01)) | FL53: =IF(FI53>0,ROUNDDOWN(('Diseño estructura &CP'!$AZ$5/FI53),0),"") | FZ53: =+IF(GA53=0,"",FZ52+1) | GA53: =+GC53/$H$9 -> 0 | GB53: =ROUNDDOWN(GC53/$C$13,0) -> 0 | GD53: =IF(GB53=0,0,GB53+1) -> 0 | GE53: =IF(GF53="","",1/(GF53+0.01)) | GF53: =IF(GC53>0,ROUNDDOWN(('Diseño estructura &CP'!$AZ$5/GC53),0),"")
B54: =+IF(C54=0,"",B53+1) -> 39 | C54: =+E54/$H$9 -> 63 | D54: =ROUNDDOWN(E54/$C$13,0) -> 10 | E54: 126 | F54: =IF(D54=0,0,D54+1) -> 11 | G54: =IF(H54="","",1/(H54+0.01)) -> 0.14265335 | H54: =IF(E54>0,ROUNDDOWN(('Diseño estructura &CP'!$AZ$5/E54),0),"") -> 7 | V54: =+IF(W54=0,"",V53+1) -> 39 | W54: =+Y54/$H$9 -> 25.25 | X54: =ROUNDDOWN(Y54/$C$13,0) -> 4 | Y54: 50.5 | Z54: =IF(X54=0,0,X54+1) -> 5 | AA54: =IF(AB54="","",1/(AB54+0.01)) -> 0.052603893 | AB54: =IF(Y54>0,ROUNDDOWN(('Diseño estructura &CP'!$AZ$5/Y54),0),"") -> 19 | AP54: =+IF(AQ54=0,"",AP53+1) -> 39 | AQ54: =+AS54/$H$9 -> 81 | AR54: =ROUNDDOWN(AS54/$C$13,0) -> 13 | AS54: 162 | AT54: =IF(AR54=0,0,AR54+1) -> 14 | AU54: =IF(AV54="","",1/(AV54+0.01)) -> 0.16638935 | AV54: =IF(AS54>0,ROUNDDOWN(('Diseño estructura &CP'!$AZ$5/AS54),0),"") -> 6 | BJ54: =+IF(BK54=0,"",BJ53+1) | BK54: =+BM54/$H$9 -> 0 | BL54: =ROUNDDOWN(BM54/$BK$13,0) -> 0 | BN54: =IF(BL54=0,0,BL54+1) -> 0 | BO54: =IF(BP54="","",1/(BP54+0.01)) | BP54: =IF(BM54>0,ROUNDDOWN(('Diseño estructura &CP'!$AZ$5/BM54),0),"") | CD54: =+IF(CE54=0,"",CD53+1) | CE54: =+CG54/$H$9 -> 0 | CF54: =ROUNDDOWN(CG54/$C$13,0) -> 0 | CH54: =IF(CF54=0,0,CF54+1) -> 0 | CI54: =IF(CJ54="","",1/(CJ54+0.01)) | CJ54: =IF(CG54>0,ROUNDDOWN(('Diseño estructura &CP'!$AZ$5/CG54),0),"") | CX54: =+IF(CY54=0,"",CX53+1) | CY54: =+DA54/$H$9 -> 0 | CZ54: =ROUNDDOWN(DA54/$C$13,0) -> 0 | DB54: =IF(CZ54=0,0,CZ54+1) -> 0 | DC54: =IF(DD54="","",1/(DD54+0.01)) | DD54: =IF(DA54>0,ROUNDDOWN(('Diseño estructura &CP'!$AZ$5/DA54),0),"") | DR54: =+IF(DS54=0,"",DR53+1) | DS54: =+DU54/$H$9 -> 0 | DT54: =ROUNDDOWN(DU54/$C$13,0) -> 0 | DV54: =IF(DT54=0,0,DT54+1) -> 0 | DW54: =IF(DX54="","",1/(DX54+0.01)) | DX54: =IF(DU54>0,ROUNDDOWN(('Diseño estructura &CP'!$AZ$5/DU54),0),"") | EL54: =+IF(EM54=0,"",EL53+1) | EM54: =+EO54/$H$9 -> 0 | EN54: =ROUNDDOWN(EO54/$C$13,0) -> 0 | EP54: =IF(EN54=0,0,EN54+1) -> 0 | EQ54: =IF(ER54="","",1/(ER54+0.01)) | ER54: =IF(EO54>0,ROUNDDOWN(('Diseño estructura &CP'!$AZ$5/EO54),0),"") | FF54: =+IF(FG54=0,"",FF53+1) | FG54: =+FI54/$H$9 -> 0 | FH54: =ROUNDDOWN(FI54/$C$13,0) -> 0 | FJ54: =IF(FH54=0,0,FH54+1) -> 0 | FK54: =IF(FL54="","",1/(FL54+0.01)) | FL54: =IF(FI54>0,ROUNDDOWN(('Diseño estructura &CP'!$AZ$5/FI54),0),"") | FZ54: =+IF(GA54=0,"",FZ53+1) | GA54: =+GC54/$H$9 -> 0 | GB54: =ROUNDDOWN(GC54/$C$13,0) -> 0 | GD54: =IF(GB54=0,0,GB54+1) -> 0 | GE54: =IF(GF54="","",1/(GF54+0.01)) | GF54: =IF(GC54>0,ROUNDDOWN(('Diseño estructura &CP'!$AZ$5/GC54),0),"")
B55: =+IF(C55=0,"",B54+1) -> 40 | C55: =+E55/$H$9 -> 63.75 | D55: =ROUNDDOWN(E55/$C$13,0) -> 10 | E55: 127.5 | F55: =IF(D55=0,0,D55+1) -> 11 | G55: =IF(H55="","",1/(H55+0.01)) -> 0.14265335 | H55: =IF(E55>0,ROUNDDOWN(('Diseño estructura &CP'!$AZ$5/E55),0),"") -> 7 | V55: =+IF(W55=0,"",V54+1) -> 40 | W55: =+Y55/$H$9 -> 28.5 | X55: =ROUNDDOWN(Y55/$C$13,0) -> 4 | Y55: 57 | Z55: =IF(X55=0,0,X55+1) -> 5 | AA55: =IF(AB55="","",1/(AB55+0.01)) -> 0.058788948 | AB55: =IF(Y55>0,ROUNDDOWN(('Diseño estructura &CP'!$AZ$5/Y55),0),"") -> 17 | AP55: =+IF(AQ55=0,"",AP54+1) -> 40 | AQ55: =+AS55/$H$9 -> 81 | AR55: =ROUNDDOWN(AS55/$C$13,0) -> 13 | AS55: 162 | AT55: =IF(AR55=0,0,AR55+1) -> 14 | AU55: =IF(AV55="","",1/(AV55+0.01)) -> 0.16638935 | AV55: =IF(AS55>0,ROUNDDOWN(('Diseño estructura &CP'!$AZ$5/AS55),0),"") -> 6 | BJ55: =+IF(BK55=0,"",BJ54+1) | BK55: =+BM55/$H$9 -> 0 | BL55: =ROUNDDOWN(BM55/$BK$13,0) -> 0 | BN55: =IF(BL55=0,0,BL55+1) -> 0 | BO55: =IF(BP55="","",1/(BP55+0.01)) | BP55: =IF(BM55>0,ROUNDDOWN(('Diseño estructura &CP'!$AZ$5/BM55),0),"") | CD55: =+IF(CE55=0,"",CD54+1) | CE55: =+CG55/$H$9 -> 0 | CF55: =ROUNDDOWN(CG55/$C$13,0) -> 0 | CH55: =IF(CF55=0,0,CF55+1) -> 0 | CI55: =IF(CJ55="","",1/(CJ55+0.01)) | CJ55: =IF(CG55>0,ROUNDDOWN(('Diseño estructura &CP'!$AZ$5/CG55),0),"") | CX55: =+IF(CY55=0,"",CX54+1) | CY55: =+DA55/$H$9 -> 0 | CZ55: =ROUNDDOWN(DA55/$C$13,0) -> 0 | DB55: =IF(CZ55=0,0,CZ55+1) -> 0 | DC55: =IF(DD55="","",1/(DD55+0.01)) | DD55: =IF(DA55>0,ROUNDDOWN(('Diseño estructura &CP'!$AZ$5/DA55),0),"") | DR55: =+IF(DS55=0,"",DR54+1) | DS55: =+DU55/$H$9 -> 0 | DT55: =ROUNDDOWN(DU55/$C$13,0) -> 0 | DV55: =IF(DT55=0,0,DT55+1) -> 0 | DW55: =IF(DX55="","",1/(DX55+0.01)) | DX55: =IF(DU55>0,ROUNDDOWN(('Diseño estructura &CP'!$AZ$5/DU55),0),"") | EL55: =+IF(EM55=0,"",EL54+1) | EM55: =+EO55/$H$9 -> 0 | EN55: =ROUNDDOWN(EO55/$C$13,0) -> 0 | EP55: =IF(EN55=0,0,EN55+1) -> 0 | EQ55: =IF(ER55="","",1/(ER55+0.01)) | ER55: =IF(EO55>0,ROUNDDOWN(('Diseño estructura &CP'!$AZ$5/EO55),0),"") | FF55: =+IF(FG55=0,"",FF54+1) | FG55: =+FI55/$H$9 -> 0 | FH55: =ROUNDDOWN(FI55/$C$13,0) -> 0 | FJ55: =IF(FH55=0,0,FH55+1) -> 0 | FK55: =IF(FL55="","",1/(FL55+0.01)) | FL55: =IF(FI55>0,ROUNDDOWN(('Diseño estructura &CP'!$AZ$5/FI55),0),"") | FZ55: =+IF(GA55=0,"",FZ54+1) | GA55: =+GC55/$H$9 -> 0 | GB55: =ROUNDDOWN(GC55/$C$13,0) -> 0 | GD55: =IF(GB55=0,0,GB55+1) -> 0 | GE55: =IF(GF55="","",1/(GF55+0.01)) | GF55: =IF(GC55>0,ROUNDDOWN(('Diseño estructura &CP'!$AZ$5/GC55),0),"")
B56: =+IF(C56=0,"",B55+1) -> 41 | C56: =+E56/$H$9 -> 64.5 | D56: =ROUNDDOWN(E56/$C$13,0) -> 10 | E56: 129 | F56: =IF(D56=0,0,D56+1) -> 11 | G56: =IF(H56="","",1/(H56+0.01)) -> 0.14265335 | H56: =IF(E56>0,ROUNDDOWN(('Diseño estructura &CP'!$AZ$5/E56),0),"") -> 7 | V56: =+IF(W56=0,"",V55+1) -> 41 | W56: =+Y56/$H$9 -> 26.5 | X56: =ROUNDDOWN(Y56/$C$13,0) -> 4 | Y56: 53 | Z56: =IF(X56=0,0,X56+1) -> 5 | AA56: =IF(AB56="","",1/(AB56+0.01)) -> 0.055524708 | AB56: =IF(Y56>0,ROUNDDOWN(('Diseño estructura &CP'!$AZ$5/Y56),0),"") -> 18 | AP56: =+IF(AQ56=0,"",AP55+1) -> 41 | AQ56: =+AS56/$H$9 -> 81.5 | AR56: =ROUNDDOWN(AS56/$C$13,0) -> 13 | AS56: 163 | AT56: =IF(AR56=0,0,AR56+1) -> 14 | AU56: =IF(AV56="","",1/(AV56+0.01)) -> 0.16638935 | AV56: =IF(AS56>0,ROUNDDOWN(('Diseño estructura &CP'!$AZ$5/AS56),0),"") -> 6 | BJ56: =+IF(BK56=0,"",BJ55+1) | BK56: =+BM56/$H$9 -> 0 | BL56: =ROUNDDOWN(BM56/$BK$13,0) -> 0 | BN56: =IF(BL56=0,0,BL56+1) -> 0 | BO56: =IF(BP56="","",1/(BP56+0.01)) | BP56: =IF(BM56>0,ROUNDDOWN(('Diseño estructura &CP'!$AZ$5/BM56),0),"") | CD56: =+IF(CE56=0,"",CD55+1) | CE56: =+CG56/$H$9 -> 0 | CF56: =ROUNDDOWN(CG56/$C$13,0) -> 0 | CH56: =IF(CF56=0,0,CF56+1) -> 0 | CI56: =IF(CJ56="","",1/(CJ56+0.01)) | CJ56: =IF(CG56>0,ROUNDDOWN(('Diseño estructura &CP'!$AZ$5/CG56),0),"") | CX56: =+IF(CY56=0,"",CX55+1) | CY56: =+DA56/$H$9 -> 0 | CZ56: =ROUNDDOWN(DA56/$C$13,0) -> 0 | DB56: =IF(CZ56=0,0,CZ56+1) -> 0 | DC56: =IF(DD56="","",1/(DD56+0.01)) | DD56: =IF(DA56>0,ROUNDDOWN(('Diseño estructura &CP'!$AZ$5/DA56),0),"") | DR56: =+IF(DS56=0,"",DR55+1) | DS56: =+DU56/$H$9 -> 0 | DT56: =ROUNDDOWN(DU56/$C$13,0) -> 0 | DV56: =IF(DT56=0,0,DT56+1) -> 0 | DW56: =IF(DX56="","",1/(DX56+0.01)) | DX56: =IF(DU56>0,ROUNDDOWN(('Diseño estructura &CP'!$AZ$5/DU56),0),"") | EL56: =+IF(EM56=0,"",EL55+1) | EM56: =+EO56/$H$9 -> 0 | EN56: =ROUNDDOWN(EO56/$C$13,0) -> 0 | EP56: =IF(EN56=0,0,EN56+1) -> 0 | EQ56: =IF(ER56="","",1/(ER56+0.01)) | ER56: =IF(EO56>0,ROUNDDOWN(('Diseño estructura &CP'!$AZ$5/EO56),0),"") | FF56: =+IF(FG56=0,"",FF55+1) | FG56: =+FI56/$H$9 -> 0 | FH56: =ROUNDDOWN(FI56/$C$13,0) -> 0 | FJ56: =IF(FH56=0,0,FH56+1) -> 0 | FK56: =IF(FL56="","",1/(FL56+0.01)) | FL56: =IF(FI56>0,ROUNDDOWN(('Diseño estructura &CP'!$AZ$5/FI56),0),"") | FZ56: =+IF(GA56=0,"",FZ55+1) | GA56: =+GC56/$H$9 -> 0 | GB56: =ROUNDDOWN(GC56/$C$13,0) -> 0 | GD56: =IF(GB56=0,0,GB56+1) -> 0 | GE56: =IF(GF56="","",1/(GF56+0.01)) | GF56: =IF(GC56>0,ROUNDDOWN(('Diseño estructura &CP'!$AZ$5/GC56),0),"")
B57: =+IF(C57=0,"",B56+1) -> 42 | C57: =+E57/$H$9 -> 65.5 | D57: =ROUNDDOWN(E57/$C$13,0) -> 10 | E57: 131 | F57: =IF(D57=0,0,D57+1) -> 11 | G57: =IF(H57="","",1/(H57+0.01)) -> 0.14265335 | H57: =IF(E57>0,ROUNDDOWN(('Diseño estructura &CP'!$AZ$5/E57),0),"") -> 7 | V57: =+IF(W57=0,"",V56+1) -> 42 | W57: =+Y57/$H$9 -> 25 | X57: =ROUNDDOWN(Y57/$C$13,0) -> 4 | Y57: 50 | Z57: =IF(X57=0,0,X57+1) -> 5 | AA57: =IF(AB57="","",1/(AB57+0.01)) -> 0.049975012 | AB57: =IF(Y57>0,ROUNDDOWN(('Diseño estructura &CP'!$AZ$5/Y57),0),"") -> 20 | AP57: =+IF(AQ57=0,"",AP56+1) -> 42 | AQ57: =+AS57/$H$9 -> 81.5 | AR57: =ROUNDDOWN(AS57/$C$13,0) -> 13 | AS57: 163 | AT57: =IF(AR57=0,0,AR57+1) -> 14 | AU57: =IF(AV57="","",1/(AV57+0.01)) -> 0.16638935 | AV57: =IF(AS57>0,ROUNDDOWN(('Diseño estructura &CP'!$AZ$5/AS57),0),"") -> 6 | BJ57: =+IF(BK57=0,"",BJ56+1) | BK57: =+BM57/$H$9 -> 0 | BL57: =ROUNDDOWN(BM57/$BK$13,0) -> 0 | BN57: =IF(BL57=0,0,BL57+1) -> 0 | BO57: =IF(BP57="","",1/(BP57+0.01)) | BP57: =IF(BM57>0,ROUNDDOWN(('Diseño estructura &CP'!$AZ$5/BM57),0),"") | CD57: =+IF(CE57=0,"",CD56+1) | CE57: =+CG57/$H$9 -> 0 | CF57: =ROUNDDOWN(CG57/$C$13,0) -> 0 | CH57: =IF(CF57=0,0,CF57+1) -> 0 | CI57: =IF(CJ57="","",1/(CJ57+0.01)) | CJ57: =IF(CG57>0,ROUNDDOWN(('Diseño estructura &CP'!$AZ$5/CG57),0),"") | CX57: =+IF(CY57=0,"",CX56+1) | CY57: =+DA57/$H$9 -> 0 | CZ57: =ROUNDDOWN(DA57/$C$13,0) -> 0 | DB57: =IF(CZ57=0,0,CZ57+1) -> 0 | DC57: =IF(DD57="","",1/(DD57+0.01)) | DD57: =IF(DA57>0,ROUNDDOWN(('Diseño estructura &CP'!$AZ$5/DA57),0),"") | DR57: =+IF(DS57=0,"",DR56+1) | DS57: =+DU57/$H$9 -> 0 | DT57: =ROUNDDOWN(DU57/$C$13,0) -> 0 | DV57: =IF(DT57=0,0,DT57+1) -> 0 | DW57: =IF(DX57="","",1/(DX57+0.01)) | DX57: =IF(DU57>0,ROUNDDOWN(('Diseño estructura &CP'!$AZ$5/DU57),0),"") | EL57: =+IF(EM57=0,"",EL56+1) | EM57: =+EO57/$H$9 -> 0 | EN57: =ROUNDDOWN(EO57/$C$13,0) -> 0 | EP57: =IF(EN57=0,0,EN57+1) -> 0 | EQ57: =IF(ER57="","",1/(ER57+0.01)) | ER57: =IF(EO57>0,ROUNDDOWN(('Diseño estructura &CP'!$AZ$5/EO57),0),"") | FF57: =+IF(FG57=0,"",FF56+1) | FG57: =+FI57/$H$9 -> 0 | FH57: =ROUNDDOWN(FI57/$C$13,0) -> 0 | FJ57: =IF(FH57=0,0,FH57+1) -> 0 | FK57: =IF(FL57="","",1/(FL57+0.01)) | FL57: =IF(FI57>0,ROUNDDOWN(('Diseño estructura &CP'!$AZ$5/FI57),0),"") | FZ57: =+IF(GA57=0,"",FZ56+1) | GA57: =+GC57/$H$9 -> 0 | GB57: =ROUNDDOWN(GC57/$C$13,0) -> 0 | GD57: =IF(GB57=0,0,GB57+1) -> 0 | GE57: =IF(GF57="","",1/(GF57+0.01)) | GF57: =IF(GC57>0,ROUNDDOWN(('Diseño estructura &CP'!$AZ$5/GC57),0),"")
